Workbook

Sheet Resumen
A1: EVALUACIÓN ECONÓMICA — PIZZERÍA B2B
A2: VERSIÓN VISUAL 2 · Flujo libre sin deuda · pesos nominales · horizonte de cinco años
A4: Decisión del escenario activo
A6: Inversión inicial | B6: =Calculos!$B$46 -> 43516722 | D6: Escenario | E6: =Inputs!$C$6 -> Base
A7: Fondeo máximo | B7: =Calculos!$B$51 -> 46682445 | D7: TMAR | E7: =Inputs!$C$7 -> 0.15
A8: VAN | B8: =Calculos!$B$47 -> 44017948 | D8: Capital disponible | E8: =Inputs!$C$9 -> 50000000
A9: TIR | B9: =Calculos!$B$48 -> 0.35689657
A10: Payback descontado | B10: =Calculos!$B$49 -> 4.0404197 | D10: Dictamen | E10: =IF(AND(Resumen!$B$8>0,Resumen!$B$9>Inputs!$C$7,Resumen!$B$7<=Inputs!$C$9),"VIABLE BAJO SUPUESTOS","RECHAZAR O REDISEÑAR") -> VIABLE BAJO SUPUESTOS
A11: Índice de rentabilidad | B11: =Calculos!$B$50 -> 2.011518
A12: Punto de equilibrio mensual | B12: =Calculos!$B$52 -> 2665.5593 | D12: Control VAN | E12: =IF(ABS(Resumen!$B$8-SUM(Calculos!$B$42:$G$42))<1,"OK","REVISAR") -> OK
D13: Flujo convencional | E13: =IF(AND(Calculos!$B$40<0,Calculos!$G$40>0),"OK","REVISAR TIR") -> OK
A15: Criterios de Ingeniería Económica
A17: • VAN > 0: el proyecto crea valor a la TMAR seleccionada.
A18: • TIR > TMAR: la rentabilidad interna supera el rendimiento mínimo exigido.
A19: • VAN y TIR no se comparan entre sí: tienen unidades diferentes.
A20: • El flujo es económico y no incorpora deuda, intereses ni dividendos.

Sheet Inputs
A1: INPUTS DEL MODELO · VERSIÓN VISUAL 2
A2: Edite solamente las celdas amarillas de la columna C. Todas las demás hojas usan fórmulas.
A4: Categoría | B4: Parámetro | C4: Valor | D4: Unidad | E4: Confianza | F4: Fuente | G4: Nota
A5: Modelo
A6: Modelo | B6: Escenario activo | C6: Base | D6: texto | E6: SUPUESTO | F6: Selección del usuario | G6: Valores permitidos: Pesimista, Base u Optimista.
A7: Modelo | B7: TMAR nominal anual | C7: 0.15 | D7: % anual | E7: SUPUESTO | F7: https://www.bcentral.cl/es/areas/politica-monetaria | G7: TMAR nominal para capital propio: TPM observada 4,5% más 10,5 puntos por riesgo comercial, escala, iliquidez y concentración. Debe sustituirse por costo de oportunidad del titular.
A8: Modelo | B8: Inflación anual | C8: 0.03 | D8: % anual desde año 2 | E8: ESTIMADO | F8: https://www.bcentral.cl/documents/33528/8413153/IPoM%2Bjunio%2B2026.pdf/93388589-0929-4ad6-b166-10981ca34946 | G8: IPoM junio 2026 ubica expectativas a uno y dos años en torno a 3%. Se escala precio y costos simétricamente.
A9: Modelo | B9: Capital máximo disponible | C9: 50000000 | D9: CLP | E9: VERIFICADO | F9: datos/supuestos.json#meta.restriccion_capital_clp | G9: Restricción declarada en el enunciado.
A10: Modelo | B10: Horizonte de evaluación | C10: 5 | D10: años | E10: SUPUESTO | F10: datos/supuestos.json#meta.horizonte_evaluacion_anios | G10: Horizonte fijado en el statement.
A11: Ventas
A12: Ventas | B12: Precio B2B neto base | C12: 4200 | D12: CLP neto/unidad en pesos base 2026 | E12: SUPUESTO | F12: 02-competencia/index.html | G12: Se usa solo porque el parámetro de etapa 02 está pendiente. Está entre PF retail neto ($3.017) y foodservice publicado ($5.034); no representa disposición a pagar validada.
A13: Ventas | B13: Volumen año 1 | C13: 30000 | D13: pizzas/año | E13: SUPUESTO | F13: 01-mercado/index.html | G13: 2.500 unidades/mes. Sustituir por mercado.som_ano1_pizzas_mes × 12 cuando etapa 03 lo valide.
A14: Ventas | B14: Volumen año 2 | C14: 42000 | D14: pizzas/año | E14: SUPUESTO | F14: Etapa 10 | G14: Rampa comercial no validada.
A15: Ventas | B15: Volumen año 3 | C15: 54000 | D15: pizzas/año | E15: SUPUESTO | F15: Etapa 10 | G15: Rampa comercial no validada.
A16: Ventas | B16: Volumen año 4 | C16: 66000 | D16: pizzas/año | E16: SUPUESTO | F16: Etapa 10 | G16: Rampa comercial no validada.
A17: Ventas | B17: Volumen año 5 | C17: 72000 | D17: pizzas/año | E17: SUPUESTO | F17: Etapa 10 | G17: Rampa comercial no validada.
A18: Tributación
A19: Tributación | B19: Impuesto año 1 | C19: 0.125 | D19: % IDPC Pro Pyme año comercial 2027 | E19: VERIFICADO | F19: https://www.sii.cl/normativa_legislacion/circulares/2025/circu53.pdf | G19: Aplica si la empresa califica al régimen Pro Pyme General del art. 14 D N°3.
A20: Tributación | B20: Impuesto año 2 | C20: 0.15 | D20: % IDPC Pro Pyme año comercial 2028 | E20: VERIFICADO | F20: https://www.sii.cl/normativa_legislacion/circulares/2025/circu53.pdf | G20: Tasa transitoria informada por Circular SII 53/2025.
A21: Tributación | B21: Impuesto año 3 | C21: 0.25 | D21: % IDPC permanente | E21: ESTIMADO | F21: https://www.sii.cl/destacados/modernizacion/tipos_regimenes_mt.html | G21: Tasa permanente vigente; se supone desde 2029 salvo nueva ley.
A22: Tributación | B22: Impuesto año 4 | C22: 0.25 | D22: % IDPC permanente | E22: ESTIMADO | F22: https://www.sii.cl/destacados/modernizacion/tipos_regimenes_mt.html | G22: Supone permanencia normativa.
A23: Tributación | B23: Impuesto año 5 | C23: 0.25 | D23: % IDPC permanente | E23: ESTIMADO | F23: https://www.sii.cl/destacados/modernizacion/tipos_regimenes_mt.html | G23: Supone permanencia normativa.
A24: Producto
A25: Producto | B25: Harina por pizza | C25: 0.2 | D25: kg/pizza | E25: SUPUESTO | F25: Etapa 10 | G25: Debe sustituirse por formulación de etapa 04.
A26: Producto | B26: Salsa por pizza | C26: 0.08 | D26: kg/pizza | E26: SUPUESTO | F26: Etapa 10 | G26: Debe sustituirse por formulación de etapa 04.
A27: Producto | B27: Mozzarella por pizza | C27: 0.12 | D27: kg/pizza | E27: SUPUESTO | F27: Etapa 10 | G27: Principal driver de costo; validar rendimiento y gramaje.
A28: Producto | B28: Otros ingredientes por pizza | C28: 550 | D28: CLP neto/pizza | E28: SUPUESTO | F28: Etapa 10 | G28: Aceite, levadura, sal, especias y topping; pendiente de receta y cotización.
A29: Producto | B29: Envase por pizza | C29: 300 | D29: CLP neto/pizza | E29: SUPUESTO | F29: 06-insumos/index.html | G29: Fallback hasta que etapa 06 cierre film, etiqueta y caja máster.
A30: Producto | B30: Energía variable por pizza | C30: 120 | D30: CLP/pizza | E30: SUPUESTO | F30: https://calvac.cl/venta/abatidor-10-bandejas-2/ | G30: Bolsa de costo para horno, abatimiento y congelación. Debe reemplazarse por balance kWh/ciclo y tarifa contratada.
A31: Producto | B31: Distribución variable por pizza | C31: 220 | D31: CLP/pizza | E31: SUPUESTO | F31: Etapa 10 | G31: Despacho consolidado local sin vehículo propio; cotizar por ruta.
A32: Producto | B32: Merma de ingredientes | C32: 0.05 | D32: % de ingredientes | E32: SUPUESTO | F32: Etapa 10 | G32: Sustituir por pruebas de proceso.
A33: Insumos
A34: Insumos | B34: Precio harina/kg | C34: 840 | D34: CLP neto/kg | E34: VERIFICADO | F34: https://metafood.cl/REV10100_Harina_Pizza | G34: Saco de harina para pizza 25 kg publicado a $21.000 + IVA. Falta confirmar flete y disponibilidad en Temuco.
A35: Insumos | B35: Precio tomate/kg | C35: 2383.8 | D35: CLP neto/kg | E35: VERIFICADO | F35: https://metafood.cl/REV10130_Tomate_Pelado_Lata_Bolsa | G35: Tomate pelado bolsa 5 kg a $11.919 + IVA. Es insumo para formular salsa, no salsa terminada; falta flete a Temuco.
A36: Insumos | B36: Precio mozzarella/kg | C36: 8403.36 | D36: CLP neto/kg | E36: ESTIMADO | F36: https://www.mercadolibre.cl/queso-mozzarella-barra-35-kg-aprox-molfino-argentino/up/MLCU67695246 | G36: Publicación de vendedor de Temuco a $10.000/kg IVA incluido, con factura y reparto refrigerado; normalizado /1,19. No es cotización por volumen ni demuestra suministro estable.
A37: Operación
A38: Operación | B38: Superficie | C38: 120 | D38: m² | E38: SUPUESTO | F38: 07-local-habilitacion/index.html | G38: Fallback hasta layout de etapa 04.
A39: Operación | B39: Arriendo por m²/mes | C39: 6331 | D39: CLP/m²/mes | E39: ESTIMADO | F39: https://chilepropiedades.cl/ver-publicacion/arriendo-mensual/temuco/bodega/bodega-nueva-de-1-500-m2-acceso-norte-de-tco-162267/117714745 ; https://propiedades.bmi.cl/6057 | G39: Punto medio entre avisos industriales de 0,15 y 0,16 UF/m²/mes, convertido con UF base $40.844,79. Son bodegas mayores; no prueba precio de un local alimentario pequeño.
A40: Operación | B40: Arriendo mensual directo (0 = calcular) | C40: 0 | D40: CLP/mes | E40: PENDIENTE | G40: Depende del metraje, gastos comunes y de encontrar un inmueble compatible con uso de suelo y habilitación sanitaria.
A41: Operación | B41: Nómina bruta mensual | C41: 2200000 | D41: CLP/mes | E41: SUPUESTO | F41: datos/supuestos.json#macro.ingreso_minimo_mensual_clp | G41: Incluye costo de oportunidad del trabajo del titular y apoyo productivo/comercial; etapa 09 debe reemplazarlo.
A42: Operación | B42: Factor costo empresa | C42: 1.22 | D42: multiplicador | E42: SUPUESTO | F42: datos/supuestos.json#macro.factor_costo_empresa | G42: Fallback dentro del rango preliminar declarado; requiere cálculo previsional de etapa 09.
A43: Operación | B43: Servicios fijos mensuales | C43: 180000 | D43: CLP/mes | E43: SUPUESTO | F43: Etapa 10 | G43: Cargo fijo de electricidad, agua, gas, internet y residuos, separado del consumo variable.
A44: Operación | B44: Mantenimiento mensual | C44: 100000 | D44: CLP/mes | E44: SUPUESTO | F44: Etapa 10 | G44: Reserva preventiva; validar con equipos elegidos.
A45: Operación | B45: Administración mensual | C45: 160000 | D45: CLP/mes | E45: SUPUESTO | F45: Etapa 10 | G45: Contabilidad, software básico, telefonía y gastos bancarios.
A46: Operación | B46: Ventas mensuales | C46: 180000 | D46: CLP/mes | E46: SUPUESTO | F46: Etapa 10 | G46: Muestras, visitas y material comercial.
A47: Operación | B47: Seguros mensuales | C47: 60000 | D47: CLP/mes | E47: SUPUESTO | F47: Etapa 10 | G47: Cotización pendiente.
A48: Operación | B48: Días cuentas por cobrar | C48: 30 | D48: días | E48: SUPUESTO | F48: datos/parametros-02-competencia.json#precios.plazo_cobro_dias | G48: Fallback consistente con el modelo de negocio; debe sustituirse por práctica validada.
A49: Operación | B49: Días inventario | C49: 15 | D49: días de costo variable | E49: SUPUESTO | F49: Etapa 10 | G49: Materia prima más producto terminado.
A50: Operación | B50: Días cuentas por pagar | C50: 0 | D50: días de costo variable | E50: SUPUESTO | F50: Etapa 10 | G50: Caso conservador sin crédito de proveedores.
A51: Inversión
A52: Inversión | B52: Abatidor | C52: 2779980 | D52: CLP neto | E52: VERIFICADO | F52: https://calvac.cl/venta/abatidor-10-bandejas-2/ | G52: 10 bandejas, congelación declarada hasta 30 kg; precio publicado + IVA.
A53: Inversión | B53: Amasadora | C53: 747815 | D53: CLP neto | E53: VERIFICADO | F53: https://www.supermaq.cl/amasadoras/amasadora_20_kilos/ | G53: Amasadora espiral 20 kg, precio internet + IVA.
A54: Inversión | B54: Horno | C54: 400000 | D54: CLP neto | E54: VERIFICADO | F54: https://www.supermaq.cl/hornos_pizza/horno_electrico_pizzero_2_camara_40x40.pdf | G54: Horno pizzero eléctrico dos cámaras, oferta + IVA; verificar capacidad real de precocción.
A55: Inversión | B55: Selladora al vacío | C55: 570000 | D55: CLP neto | E55: ESTIMADO | F55: https://www.supermaq.cl/pdf/camara.cl_selladora_al_vacio_300_mm_dz300.pdf | G55: Ficha con precio publicado; confirmar vigencia y compatibilidad con formato.
A56: Inversión | B56: Mesón refrigerado | C56: 620000 | D56: CLP neto | E56: ESTIMADO | F56: https://www.industriaminera.cl/producto/biggi-chile-sa-mesones-refrigerados/ | G56: Mesón 120 cm publicado + IVA; confirmar vigencia.
A57: Inversión | B57: Congeladores | C57: 700000 | D57: CLP neto | E57: SUPUESTO | F57: https://gastronomicareal.cl/refrigeracion/congeladoras | G57: Bolsa para almacenamiento −18 °C; requiere selección por capacidad y redundancia.
A58: Inversión | B58: Acero, lavado y extracción | C58: 1800000 | D58: CLP neto | E58: SUPUESTO | F58: Etapa 10 | G58: Mesones, lavaderos, campana y elementos fijos; cotización pendiente.
A59: Inversión | B59: Racks, bandejas e instrumentos | C59: 1200000 | D59: CLP neto | E59: SUPUESTO | F59: Etapa 10 | G59: Carros, bandejas, balanzas, sondas y utensilios.
A60: Inversión | B60: Flete e instalación | C60: 0.15 | D60: % sobre equipos | E60: SUPUESTO | F60: Etapa 10 | G60: Flete Santiago–Temuco, conexión y puesta en marcha.
A61: Inversión | B61: Habilitación sanitaria | C61: 12000000 | D61: CLP neto | E61: SUPUESTO | F61: 07-local-habilitacion/index.html | G61: Riesgo principal; reemplazar por presupuesto desglosado de un local real.
A62: Inversión | B62: Trámites, análisis y rotulado | C62: 1000000 | D62: CLP neto | E62: SUPUESTO | F62: 08-legal-normativo/index.html | G62: Aranceles, laboratorio y artes; cotización pendiente.
A63: Inversión | B63: Preoperación | C63: 1500000 | D63: CLP neto | E63: SUPUESTO | F63: Etapa 10 | G63: Pruebas, capacitación, muestras y apertura.
... A67: Inversión | B67: Valor residual | C67: 0.1 | D67: % del CAPEX depreciable | E67: SUPUESTO | F67: Etapa 10 | G67: Valor de realización al año 5 antes de impuesto.
A68: Escenarios
A69: Escenarios | B69: Pesimista: precio | C69: 0.9 | D69: multiplicador | E69: SUPUESTO | F69: Etapa 10 | G69: Editable para análisis de riesgo.
A70: Escenarios | B70: Pesimista: volumen | C70: 0.8 | D70: multiplicador | E70: SUPUESTO | F70: Etapa 10 | G70: Editable para análisis de riesgo.
A71: Escenarios | B71: Pesimista: costo variable | C71: 1.1 | D71: multiplicador | E71: SUPUESTO | F71: Etapa 10 | G71: Editable para análisis de riesgo.
A72: Escenarios | B72: Pesimista: costo fijo | C72: 1.1 | D72: multiplicador | E72: SUPUESTO | F72: Etapa 10 | G72: Editable para análisis de riesgo.
A73: Escenarios | B73: Pesimista: CAPEX | C73: 1.15 | D73: multiplicador | E73: SUPUESTO | F73: Etapa 10 | G73: Editable para análisis de riesgo.
A74: Escenarios | B74: Base: precio | C74: 1 | D74: multiplicador | E74: SUPUESTO | F74: Etapa 10 | G74: Editable para análisis de riesgo.
A75: Escenarios | B75: Base: volumen | C75: 1 | D75: multiplicador | E75: SUPUESTO | F75: Etapa 10 | G75: Editable para análisis de riesgo.
A76: Escenarios | B76: Base: costo variable | C76: 1 | D76: multiplicador | E76: SUPUESTO | F76: Etapa 10 | G76: Editable para análisis de riesgo.
A77: Escenarios | B77: Base: costo fijo | C77: 1 | D77: multiplicador | E77: SUPUESTO | F77: Etapa 10 | G77: Editable para análisis de riesgo.
A78: Escenarios | B78: Base: CAPEX | C78: 1 | D78: multiplicador | E78: SUPUESTO | F78: Etapa 10 | G78: Editable para análisis de riesgo.
A79: Escenarios | B79: Optimista: precio | C79: 1.1 | D79: multiplicador | E79: SUPUESTO | F79: Etapa 10 | G79: Editable para análisis de riesgo.
A80: Escenarios | B80: Optimista: volumen | C80: 1.2 | D80: multiplicador | E80: SUPUESTO | F80: Etapa 10 | G80: Editable para análisis de riesgo.
... A87: Escenarios | B87: Sensibilidad: volumen alto | C87: 1.2 | D87: multiplicador | E87: SUPUESTO | F87: Etapa 10 | G87: Editable para análisis de riesgo.

Sheet Inversion
A1: INVERSIÓN INICIAL
A2: Detalle del escenario activo; todos los montos provienen de Inputs o de fórmulas.
A4: Concepto | B4: Monto | C4: Tratamiento | D4: Referencia
A5: Equipos principales | B5: =Calculos!$B$11 -> 8817795 | C5: Depreciable | D5: Inputs / Calculos
A6: Flete e instalación | B6: =Calculos!$B$12 -> 1322669.2 | C6: Depreciable | D6: Inputs / Calculos
A7: Habilitación + contingencia | B7: =Calculos!$B$16-Calculos!$B$11-Calculos!$B$12 -> 15321070 | C7: Depreciable | D7: Inputs / Calculos
A8: Trámites y preoperación | B8: =Calculos!$B$17-Calculos!$B$16 -> 2500000 | C8: No depreciable en este modelo | D8: Inputs / Calculos
A9: Garantía de arriendo | B9: =Calculos!$B$20 -> 1519440 | C9: Recuperable al año 5 | D9: Inputs / Calculos
A10: Capital de trabajo inicial | B10: =Calculos!$C$37 -> 14035748 | C10: Recuperable al año 5 | D10: Inputs / Calculos
A12: INVERSIÓN INICIAL TOTAL | B12: =Calculos!$B$46 -> 43516722

Sheet Flujo_Caja
A1: FLUJO DE CAJA LIBRE DEL PROYECTO
A2: Escenario elegido en Inputs; cifras nominales, después de impuestos y antes de financiamiento.
A4: Concepto | B4: Año 0 | C4: Año 1 | D4: Año 2 | E4: Año 3 | F4: Año 4 | G4: Año 5
A5: Volumen | B5: =Calculos!$B$23 -> 0 | C5: =Calculos!$C$23 -> 30000 | D5: =Calculos!$D$23 -> 42000 | E5: =Calculos!$E$23 -> 54000 | F5: =Calculos!$F$23 -> 66000 | G5: =Calculos!$G$23 -> 72000
A6: Precio | B6: =Calculos!$B$25 -> 0 | C6: =Calculos!$C$25 -> 4326 | D6: =Calculos!$D$25 -> 4455.78 | E6: =Calculos!$E$25 -> 4589.4534 | F6: =Calculos!$F$25 -> 4727.137 | G6: =Calculos!$G$25 -> 4868.9511
A7: Ingresos | B7: =Calculos!$B$27 -> 0 | C7: =Calculos!$C$27 -> 129780000 | D7: =Calculos!$D$27 -> 187142760 | E7: =Calculos!$E$27 -> 2.4783048e+08 | F7: =Calculos!$F$27 -> 3.1199104e+08 | G7: =Calculos!$G$27 -> 3.5056448e+08
A8: Costos variables | B8: =Calculos!$B$28 -> 0 | C8: =Calculos!$C$28 -> 81976543 | D8: =Calculos!$D$28 -> 1.1821018e+08 | E8: =Calculos!$E$28 -> 1.5654405e+08 | F8: =Calculos!$F$28 -> 1.9707156e+08 | G8: =Calculos!$G$28 -> 2.2143677e+08
A9: Costos fijos | B9: =Calculos!$B$29 -> 0 | C9: =Calculos!$C$29 -> 50969179 | D9: =Calculos!$D$29 -> 52498255 | E9: =Calculos!$E$29 -> 54073202 | F9: =Calculos!$F$29 -> 55695398 | G9: =Calculos!$G$29 -> 57366260
A10: EBITDA | B10: =Calculos!$B$30 -> 0 | C10: =Calculos!$C$30 -> -3165722.3 | D10: =Calculos!$D$30 -> 16434330 | E10: =Calculos!$E$30 -> 37213235 | F10: =Calculos!$F$30 -> 59224083 | G10: =Calculos!$G$30 -> 71761448
A11: Depreciación | B11: =Calculos!$B$31 -> 0 | C11: =Calculos!$C$31 -> 5092306.8 | D11: =Calculos!$D$31 -> 5092306.8 | E11: =Calculos!$E$31 -> 5092306.8 | F11: =Calculos!$F$31 -> 5092306.8 | G11: =Calculos!$G$31 -> 5092306.8
A12: EBIT | B12: =Calculos!$B$32 -> 0 | C12: =Calculos!$C$32 -> -8258029.1 | D12: =Calculos!$D$32 -> 11342023 | E12: =Calculos!$E$32 -> 32120928 | F12: =Calculos!$F$32 -> 54131777 | G12: =Calculos!$G$32 -> 66669142
A13: Pérdida tributaria inicial | B13: =Calculos!$B$33 -> 0 | C13: =Calculos!$C$33 -> 0 | D13: =Calculos!$D$33 -> 8258029.1 | E13: =Calculos!$E$33 -> 0 | F13: =Calculos!$F$33 -> 0 | G13: =Calculos!$G$33 -> 0
A14: Renta imponible | B14: =Calculos!$B$34 -> 0 | C14: =Calculos!$C$34 -> 0 | D14: =Calculos!$D$34 -> 3083994.4 | E14: =Calculos!$E$34 -> 32120928 | F14: =Calculos!$F$34 -> 54131777 | G14: =Calculos!$G$34 -> 66669142
A15: Impuesto | B15: =Calculos!$B$35 -> 0 | C15: =Calculos!$C$35 -> 0 | D15: =Calculos!$D$35 -> 462599.16 | E15: =Calculos!$E$35 -> 8030232.1 | F15: =Calculos!$F$35 -> 13532944 | G15: =Calculos!$G$35 -> 16667285
A16: Pérdida tributaria final | B16: =Calculos!$B$36 -> 0 | C16: =Calculos!$C$36 -> 8258029.1 | D16: =Calculos!$D$36 -> 0 | E16: =Calculos!$E$36 -> 0 | F16: =Calculos!$F$36 -> 0 | G16: =Calculos!$G$36 -> 0
A17: Capital de trabajo | B17: =Calculos!$B$37 -> 0 | C17: =Calculos!$C$37 -> 14035748 | D17: =Calculos!$D$37 -> 20239549 | E17: =Calculos!$E$37 -> 26802946 | F17: =Calculos!$F$37 -> 33741931 | G17: =Calculos!$G$37 -> 37913660
A18: Variación capital de trabajo | B18: =Calculos!$B$38 -> 0 | C18: =Calculos!$C$38 -> 0 | D18: =Calculos!$D$38 -> 6203800.8 | E18: =Calculos!$E$38 -> 6563396.6 | F18: =Calculos!$F$38 -> 6938984.8 | G18: =Calculos!$G$38 -> 4171729.6
A19: Recuperaciones terminales | B19: =Calculos!$B$39 -> 0 | C19: =Calculos!$C$39 -> 0 | D19: =Calculos!$D$39 -> 0 | E19: =Calculos!$E$39 -> 0 | F19: =Calculos!$F$39 -> 0 | G19: =Calculos!$G$39 -> 41342715
A20: Flujo libre | B20: =Calculos!$B$40 -> -43516722 | C20: =Calculos!$C$40 -> -3165722.3 | D20: =Calculos!$D$40 -> 9767930.3 | E20: =Calculos!$E$40 -> 22619606 | F20: =Calculos!$F$40 -> 38752154 | G20: =Calculos!$G$40 -> 92265149
A21: Factor descuento | B21: =Calculos!$B$41 -> 1 | C21: =Calculos!$C$41 -> 0.86956522 | D21: =Calculos!$D$41 -> 0.75614367 | E21: =Calculos!$E$41 -> 0.65751623 | F21: =Calculos!$F$41 -> 0.57175325 | G21: =Calculos!$G$41 -> 0.49717674
A22: Flujo descontado | B22: =Calculos!$B$42 -> -43516722 | C22: =Calculos!$C$42 -> -2752802 | D22: =Calculos!$D$42 -> 7385958.7 | E22: =Calculos!$E$42 -> 14872758 | F22: =Calculos!$F$42 -> 22156670 | G22: =Calculos!$G$42 -> 45872085
A23: Flujo acumulado | B23: =Calculos!$B$43 -> -43516722 | C23: =Calculos!$C$43 -> -46682445 | D23: =Calculos!$D$43 -> -36914514 | E23: =Calculos!$E$43 -> -14294908 | F23: =Calculos!$F$43 -> 24457247 | G23: =Calculos!$G$43 -> 1.167224e+08
A24: Flujo descontado acumulado | B24: =Calculos!$B$44 -> -43516722 | C24: =Calculos!$C$44 -> -46269524 | D24: =Calculos!$D$44 -> -38883566 | E24: =Calculos!$E$44 -> -24010807 | F24: =Calculos!$F$44 -> -1854137.1 | G24: =Calculos!$G$44 -> 44017948

Sheet Escenarios
A1: ESCENARIOS
A2: Multiplicadores editables en Inputs; cada caso recalcula impuestos, capital de trabajo y valor terminal.
A4: Escenario | B4: VAN | C4: TIR | D4: Inversión inicial | E4: Fondeo máximo | F4: Payback descontado | G4: Punto equilibrio/mes
A5: Pesimista | B5: =Calculos!$B$98 -> -1.111331e+08 | C5: =Calculos!$B$99 -> -1 | D5: =Calculos!$B$97 -> 44319967 | E5: =Calculos!$B$102 -> 1.49915e+08 | F5: =Calculos!$B$100 -> 99 | G5: =Calculos!$B$103 -> 5263.8682
A6: Base | B6: =Calculos!$B$149 -> 44017948 | C6: =Calculos!$B$150 -> 0.35689657 | D6: =Calculos!$B$148 -> 43516722 | E6: =Calculos!$B$153 -> 46682445 | F6: =Calculos!$B$151 -> 4.0404197 | G6: =Calculos!$B$154 -> 2665.5593
A7: Optimista | B7: =Calculos!$B$200 -> 1.8260186e+08 | C7: =Calculos!$B$201 -> 0.92510305 | D7: =Calculos!$B$199 -> 46003683 | E7: =Calculos!$B$204 -> 46003683 | F7: =Calculos!$B$202 -> 1.7587594 | G7: =Calculos!$B$205 -> 1963.9703

Sheet Sensibilidad
A1: SENSIBILIDAD DEL VAN
A2: Filas: multiplicador de volumen. Columnas: multiplicador de precio; costos y CAPEX permanecen en caso base.
A4: Volumen \ Precio | B4: =Inputs!$C$84 -> 0.9 | C4: =1 -> 1 | D4: =Inputs!$C$85 -> 1.1
A5: =Inputs!$C$86 -> 0.8 | B5: =Calculos!$B$251 -> -49981716 | C5: =Calculos!$B$302 -> 2380852.2 | D5: =Calculos!$B$353 -> 49273963
A6: =1 -> 1 | B6: =Calculos!$B$404 -> -14715876 | C6: =Calculos!$B$455 -> 44017948 | D6: =Calculos!$B$506 -> 1.0377583e+08
A7: =Inputs!$C$87 -> 1.2 | B7: =Calculos!$B$557 -> 15458785 | C7: =Calculos!$B$608 -> 86556552 | D7: =Calculos!$B$659 -> 1.5831284e+08

Sheet Fuentes
A1: TRAZABILIDAD Y FUENTES
A2: Copia documental de Inputs. Los cambios posteriores deben realizarse en Inputs.
A4: Parámetro | B4: Valor actual | C4: Unidad | D4: Confianza | E4: Fuente | F4: Nota
A5: =Inputs!$B$7 -> TMAR nominal anual | B5: =Inputs!$C$7 -> 0.15 | C5: =Inputs!$D$7 -> % anual | D5: =Inputs!$E$7 -> SUPUESTO | E5: =Inputs!$F$7 -> https://www.bcentral.cl/es/areas/politica-monetaria | F5: =Inputs!$G$7 -> TMAR nominal para capital propio: TPM observada 4,5% más 10,5 puntos por riesgo comercial, escala, iliquidez y concentración. Debe sustituirse por costo de oportunidad del titular.
A6: =Inputs!$B$8 -> Inflación anual | B6: =Inputs!$C$8 -> 0.03 | C6: =Inputs!$D$8 -> % anual desde año 2 | D6: =Inputs!$E$8 -> ESTIMADO | E6: =Inputs!$F$8 -> https://www.bcentral.cl/documents/33528/8413153/IPoM%2Bjunio%2B2026.pdf/93388589-0929-4ad6-b166-10981ca34946 | F6: =Inputs!$G$8 -> IPoM junio 2026 ubica expectativas a uno y dos años en torno a 3%. Se escala precio y costos simétricamente.
A7: =Inputs!$B$9 -> Capital máximo disponible | B7: =Inputs!$C$9 -> 50000000 | C7: =Inputs!$D$9 -> CLP | D7: =Inputs!$E$9 -> VERIFICADO | E7: =Inputs!$F$9 -> datos/supuestos.json#meta.restriccion_capital_clp | F7: =Inputs!$G$9 -> Restricción declarada en el enunciado.
A8: =Inputs!$B$10 -> Horizonte de evaluación | B8: =Inputs!$C$10 -> 5 | C8: =Inputs!$D$10 -> años | D8: =Inputs!$E$10 -> SUPUESTO | E8: =Inputs!$F$10 -> datos/supuestos.json#meta.horizonte_evaluacion_anios | F8: =Inputs!$G$10 -> Horizonte fijado en el statement.
A9: =Inputs!$B$12 -> Precio B2B neto base | B9: =Inputs!$C$12 -> 4200 | C9: =Inputs!$D$12 -> CLP neto/unidad en pesos base 2026 | D9: =Inputs!$E$12 -> SUPUESTO | E9: =Inputs!$F$12 -> 02-competencia/index.html | F9: =Inputs!$G$12 -> Se usa solo porque el parámetro de etapa 02 está pendiente. Está entre PF retail neto ($3.017) y foodservice publicado ($5.034); no representa disposición a pagar validada.
A10: =Inputs!$B$13 -> Volumen año 1 | B10: =Inputs!$C$13 -> 30000 | C10: =Inputs!$D$13 -> pizzas/año | D10: =Inputs!$E$13 -> SUPUESTO | E10: =Inputs!$F$13 -> 01-mercado/index.html | F10: =Inputs!$G$13 -> 2.500 unidades/mes. Sustituir por mercado.som_ano1_pizzas_mes × 12 cuando etapa 03 lo valide.
A11: =Inputs!$B$14 -> Volumen año 2 | B11: =Inputs!$C$14 -> 42000 | C11: =Inputs!$D$14 -> pizzas/año | D11: =Inputs!$E$14 -> SUPUESTO | E11: =Inputs!$F$14 -> Etapa 10 | F11: =Inputs!$G$14 -> Rampa comercial no validada.
A12: =Inputs!$B$15 -> Volumen año 3 | B12: =Inputs!$C$15 -> 54000 | C12: =Inputs!$D$15 -> pizzas/año | D12: =Inputs!$E$15 -> SUPUESTO | E12: =Inputs!$F$15 -> Etapa 10 | F12: =Inputs!$G$15 -> Rampa comercial no validada.
A13: =Inputs!$B$16 -> Volumen año 4 | B13: =Inputs!$C$16 -> 66000 | C13: =Inputs!$D$16 -> pizzas/año | D13: =Inputs!$E$16 -> SUPUESTO | E13: =Inputs!$F$16 -> Etapa 10 | F13: =Inputs!$G$16 -> Rampa comercial no validada.
A14: =Inputs!$B$17 -> Volumen año 5 | B14: =Inputs!$C$17 -> 72000 | C14: =Inputs!$D$17 -> pizzas/año | D14: =Inputs!$E$17 -> SUPUESTO | E14: =Inputs!$F$17 -> Etapa 10 | F14: =Inputs!$G$17 -> Rampa comercial no validada.
A15: =Inputs!$B$19 -> Impuesto año 1 | B15: =Inputs!$C$19 -> 0.125 | C15: =Inputs!$D$19 -> % IDPC Pro Pyme año comercial 2027 | D15: =Inputs!$E$19 -> VERIFICADO | E15: =Inputs!$F$19 -> https://www.sii.cl/normativa_legislacion/circulares/2025/circu53.pdf | F15: =Inputs!$G$19 -> Aplica si la empresa califica al régimen Pro Pyme General del art. 14 D N°3.
A16: =Inputs!$B$20 -> Impuesto año 2 | B16: =Inputs!$C$20 -> 0.15 | C16: =Inputs!$D$20 -> % IDPC Pro Pyme año comercial 2028 | D16: =Inputs!$E$20 -> VERIFICADO | E16: =Inputs!$F$20 -> https://www.sii.cl/normativa_legislacion/circulares/2025/circu53.pdf | F16: =Inputs!$G$20 -> Tasa transitoria informada por Circular SII 53/2025.
A17: =Inputs!$B$21 -> Impuesto año 3 | B17: =Inputs!$C$21 -> 0.25 | C17: =Inputs!$D$21 -> % IDPC permanente | D17: =Inputs!$E$21 -> ESTIMADO | E17: =Inputs!$F$21 -> https://www.sii.cl/destacados/modernizacion/tipos_regimenes_mt.html | F17: =Inputs!$G$21 -> Tasa permanente vigente; se supone desde 2029 salvo nueva ley.
A18: =Inputs!$B$22 -> Impuesto año 4 | B18: =Inputs!$C$22 -> 0.25 | C18: =Inputs!$D$22 -> % IDPC permanente | D18: =Inputs!$E$22 -> ESTIMADO | E18: =Inputs!$F$22 -> https://www.sii.cl/destacados/modernizacion/tipos_regimenes_mt.html | F18: =Inputs!$G$22 -> Supone permanencia normativa.
A19: =Inputs!$B$23 -> Impuesto año 5 | B19: =Inputs!$C$23 -> 0.25 | C19: =Inputs!$D$23 -> % IDPC permanente | D19: =Inputs!$E$23 -> ESTIMADO | E19: =Inputs!$F$23 -> https://www.sii.cl/destacados/modernizacion/tipos_regimenes_mt.html | F19: =Inputs!$G$23 -> Supone permanencia normativa.
A20: =Inputs!$B$25 -> Harina por pizza | B20: =Inputs!$C$25 -> 0.2 | C20: =Inputs!$D$25 -> kg/pizza | D20: =Inputs!$E$25 -> SUPUESTO | E20: =Inputs!$F$25 -> Etapa 10 | F20: =Inputs!$G$25 -> Debe sustituirse por formulación de etapa 04.
A21: =Inputs!$B$26 -> Salsa por pizza | B21: =Inputs!$C$26 -> 0.08 | C21: =Inputs!$D$26 -> kg/pizza | D21: =Inputs!$E$26 -> SUPUESTO | E21: =Inputs!$F$26 -> Etapa 10 | F21: =Inputs!$G$26 -> Debe sustituirse por formulación de etapa 04.
A22: =Inputs!$B$27 -> Mozzarella por pizza | B22: =Inputs!$C$27 -> 0.12 | C22: =Inputs!$D$27 -> kg/pizza | D22: =Inputs!$E$27 -> SUPUESTO | E22: =Inputs!$F$27 -> Etapa 10 | F22: =Inputs!$G$27 -> Principal driver de costo; validar rendimiento y gramaje.
A23: =Inputs!$B$28 -> Otros ingredientes por pizza | B23: =Inputs!$C$28 -> 550 | C23: =Inputs!$D$28 -> CLP neto/pizza | D23: =Inputs!$E$28 -> SUPUESTO | E23: =Inputs!$F$28 -> Etapa 10 | F23: =Inputs!$G$28 -> Aceite, levadura, sal, especias y topping; pendiente de receta y cotización.
A24: =Inputs!$B$29 -> Envase por pizza | B24: =Inputs!$C$29 -> 300 | C24: =Inputs!$D$29 -> CLP neto/pizza | D24: =Inputs!$E$29 -> SUPUESTO | E24: =Inputs!$F$29 -> 06-insumos/index.html | F24: =Inputs!$G$29 -> Fallback hasta que etapa 06 cierre film, etiqueta y caja máster.
A25: =Inputs!$B$30 -> Energía variable por pizza | B25: =Inputs!$C$30 -> 120 | C25: =Inputs!$D$30 -> CLP/pizza | D25: =Inputs!$E$30 -> SUPUESTO | E25: =Inputs!$F$30 -> https://calvac.cl/venta/abatidor-10-bandejas-2/ | F25: =Inputs!$G$30 -> Bolsa de costo para horno, abatimiento y congelación. Debe reemplazarse por balance kWh/ciclo y tarifa contratada.
A26: =Inputs!$B$31 -> Distribución variable por pizza | B26: =Inputs!$C$31 -> 220 | C26: =Inputs!$D$31 -> CLP/pizza | D26: =Inputs!$E$31 -> SUPUESTO | E26: =Inputs!$F$31 -> Etapa 10 | F26: =Inputs!$G$31 -> Despacho consolidado local sin vehículo propio; cotizar por ruta.
A27: =Inputs!$B$32 -> Merma de ingredientes | B27: =Inputs!$C$32 -> 0.05 | C27: =Inputs!$D$32 -> % de ingredientes | D27: =Inputs!$E$32 -> SUPUESTO | E27: =Inputs!$F$32 -> Etapa 10 | F27: =Inputs!$G$32 -> Sustituir por pruebas de proceso.
A28: =Inputs!$B$34 -> Precio harina/kg | B28: =Inputs!$C$34 -> 840 | C28: =Inputs!$D$34 -> CLP neto/kg | D28: =Inputs!$E$34 -> VERIFICADO | E28: =Inputs!$F$34 -> https://metafood.cl/REV10100_Harina_Pizza | F28: =Inputs!$G$34 -> Saco de harina para pizza 25 kg publicado a $21.000 + IVA. Falta confirmar flete y disponibilidad en Temuco.
A29: =Inputs!$B$35 -> Precio tomate/kg | B29: =Inputs!$C$35 -> 2383.8 | C29: =Inputs!$D$35 -> CLP neto/kg | D29: =Inputs!$E$35 -> VERIFICADO | E29: =Inputs!$F$35 -> https://metafood.cl/REV10130_Tomate_Pelado_Lata_Bolsa | F29: =Inputs!$G$35 -> Tomate pelado bolsa 5 kg a $11.919 + IVA. Es insumo para formular salsa, no salsa terminada; falta flete a Temuco.
A30: =Inputs!$B$36 -> Precio mozzarella/kg | B30: =Inputs!$C$36 -> 8403.36 | C30: =Inputs!$D$36 -> CLP neto/kg | D30: =Inputs!$E$36 -> ESTIMADO | E30: =Inputs!$F$36 -> https://www.mercadolibre.cl/queso-mozzarella-barra-35-kg-aprox-molfino-argentino/up/MLCU67695246 | F30: =Inputs!$G$36 -> Publicación de vendedor de Temuco a $10.000/kg IVA incluido, con factura y reparto refrigerado; normalizado /1,19. No es cotización por volumen ni demuestra suministro estable.
A31: =Inputs!$B$38 -> Superficie | B31: =Inputs!$C$38 -> 120 | C31: =Inputs!$D$38 -> m² | D31: =Inputs!$E$38 -> SUPUESTO | E31: =Inputs!$F$38 -> 07-local-habilitacion/index.html | F31: =Inputs!$G$38 -> Fallback hasta layout de etapa 04.
A32: =Inputs!$B$39 -> Arriendo por m²/mes | B32: =Inputs!$C$39 -> 6331 | C32: =Inputs!$D$39 -> CLP/m²/mes | D32: =Inputs!$E$39 -> ESTIMADO | E32: =Inputs!$F$39 -> https://chilepropiedades.cl/ver-publicacion/arriendo-mensual/temuco/bodega/bodega-nueva-de-1-500-m2-acceso-norte-de-tco-162267/117714745 ; https://propiedades.bmi.cl/6057 | F32: =Inputs!$G$39 -> Punto medio entre avisos industriales de 0,15 y 0,16 UF/m²/mes, convertido con UF base $40.844,79. Son bodegas mayores; no prueba precio de un local alimentario pequeño.
A33: =Inputs!$B$40 -> Arriendo mensual directo (0 = calcular) | B33: =Inputs!$C$40 -> 0 | C33: =Inputs!$D$40 -> CLP/mes | D33: =Inputs!$E$40 -> PENDIENTE | E33: =Inputs!$F$40 -> 0 | F33: =Inputs!$G$40 -> Depende del metraje, gastos comunes y de encontrar un inmueble compatible con uso de suelo y habilitación sanitaria.
A34: =Inputs!$B$41 -> Nómina bruta mensual | B34: =Inputs!$C$41 -> 2200000 | C34: =Inputs!$D$41 -> CLP/mes | D34: =Inputs!$E$41 -> SUPUESTO | E34: =Inputs!$F$41 -> datos/supuestos.json#macro.ingreso_minimo_mensual_clp | F34: =Inputs!$G$41 -> Incluye costo de oportunidad del trabajo del titular y apoyo productivo/comercial; etapa 09 debe reemplazarlo.
A35: =Inputs!$B$42 -> Factor costo empresa | B35: =Inputs!$C$42 -> 1.22 | C35: =Inputs!$D$42 -> multiplicador | D35: =Inputs!$E$42 -> SUPUESTO | E35: =Inputs!$F$42 -> datos/supuestos.json#macro.factor_costo_empresa | F35: =Inputs!$G$42 -> Fallback dentro del rango preliminar declarado; requiere cálculo previsional de etapa 09.
A36: =Inputs!$B$43 -> Servicios fijos mensuales | B36: =Inputs!$C$43 -> 180000 | C36: =Inputs!$D$43 -> CLP/mes | D36: =Inputs!$E$43 -> SUPUESTO | E36: =Inputs!$F$43 -> Etapa 10 | F36: =Inputs!$G$43 -> Cargo fijo de electricidad, agua, gas, internet y residuos, separado del consumo variable.
A37: =Inputs!$B$44 -> Mantenimiento mensual | B37: =Inputs!$C$44 -> 100000 | C37: =Inputs!$D$44 -> CLP/mes | D37: =Inputs!$E$44 -> SUPUESTO | E37: =Inputs!$F$44 -> Etapa 10 | F37: =Inputs!$G$44 -> Reserva preventiva; validar con equipos elegidos.
A38: =Inputs!$B$45 -> Administración mensual | B38: =Inputs!$C$45 -> 160000 | C38: =Inputs!$D$45 -> CLP/mes | D38: =Inputs!$E$45 -> SUPUESTO | E38: =Inputs!$F$45 -> Etapa 10 | F38: =Inputs!$G$45 -> Contabilidad, software básico, telefonía y gastos bancarios.
A39: =Inputs!$B$46 -> Ventas mensuales | B39: =Inputs!$C$46 -> 180000 | C39: =Inputs!$D$46 -> CLP/mes | D39: =Inputs!$E$46 -> SUPUESTO | E39: =Inputs!$F$46 -> Etapa 10 | F39: =Inputs!$G$46 -> Muestras, visitas y material comercial.
A40: =Inputs!$B$47 -> Seguros mensuales | B40: =Inputs!$C$47 -> 60000 | C40: =Inputs!$D$47 -> CLP/mes | D40: =Inputs!$E$47 -> SUPUESTO | E40: =Inputs!$F$47 -> Etapa 10 | F40: =Inputs!$G$47 -> Cotización pendiente.
A41: =Inputs!$B$48 -> Días cuentas por cobrar | B41: =Inputs!$C$48 -> 30 | C41: =Inputs!$D$48 -> días | D41: =Inputs!$E$48 -> SUPUESTO | E41: =Inputs!$F$48 -> datos/parametros-02-competencia.json#precios.plazo_cobro_dias | F41: =Inputs!$G$48 -> Fallback consistente con el modelo de negocio; debe sustituirse por práctica validada.
A42: =Inputs!$B$49 -> Días inventario | B42: =Inputs!$C$49 -> 15 | C42: =Inputs!$D$49 -> días de costo variable | D42: =Inputs!$E$49 -> SUPUESTO | E42: =Inputs!$F$49 -> Etapa 10 | F42: =Inputs!$G$49 -> Materia prima más producto terminado.
A43: =Inputs!$B$50 -> Días cuentas por pagar | B43: =Inputs!$C$50 -> 0 | C43: =Inputs!$D$50 -> días de costo variable | D43: =Inputs!$E$50 -> SUPUESTO | E43: =Inputs!$F$50 -> Etapa 10 | F43: =Inputs!$G$50 -> Caso conservador sin crédito de proveedores.
A44: =Inputs!$B$52 -> Abatidor | B44: =Inputs!$C$52 -> 2779980 | C44: =Inputs!$D$52 -> CLP neto | D44: =Inputs!$E$52 -> VERIFICADO | E44: =Inputs!$F$52 -> https://calvac.cl/venta/abatidor-10-bandejas-2/ | F44: =Inputs!$G$52 -> 10 bandejas, congelación declarada hasta 30 kg; precio publicado + IVA.
A45: =Inputs!$B$53 -> Amasadora | B45: =Inputs!$C$53 -> 747815 | C45: =Inputs!$D$53 -> CLP neto | D45: =Inputs!$E$53 -> VERIFICADO | E45: =Inputs!$F$53 -> https://www.supermaq.cl/amasadoras/amasadora_20_kilos/ | F45: =Inputs!$G$53 -> Amasadora espiral 20 kg, precio internet + IVA.
A46: =Inputs!$B$54 -> Horno | B46: =Inputs!$C$54 -> 400000 | C46: =Inputs!$D$54 -> CLP neto | D46: =Inputs!$E$54 -> VERIFICADO | E46: =Inputs!$F$54 -> https://www.supermaq.cl/hornos_pizza/horno_electrico_pizzero_2_camara_40x40.pdf | F46: =Inputs!$G$54 -> Horno pizzero eléctrico dos cámaras, oferta + IVA; verificar capacidad real de precocción.
A47: =Inputs!$B$55 -> Selladora al vacío | B47: =Inputs!$C$55 -> 570000 | C47: =Inputs!$D$55 -> CLP neto | D47: =Inputs!$E$55 -> ESTIMADO | E47: =Inputs!$F$55 -> https://www.supermaq.cl/pdf/camara.cl_selladora_al_vacio_300_mm_dz300.pdf | F47: =Inputs!$G$55 -> Ficha con precio publicado; confirmar vigencia y compatibilidad con formato.
A48: =Inputs!$B$56 -> Mesón refrigerado | B48: =Inputs!$C$56 -> 620000 | C48: =Inputs!$D$56 -> CLP neto | D48: =Inputs!$E$56 -> ESTIMADO | E48: =Inputs!$F$56 -> https://www.industriaminera.cl/producto/biggi-chile-sa-mesones-refrigerados/ | F48: =Inputs!$G$56 -> Mesón 120 cm publicado + IVA; confirmar vigencia.
A49: =Inputs!$B$57 -> Congeladores | B49: =Inputs!$C$57 -> 700000 | C49: =Inputs!$D$57 -> CLP neto | D49: =Inputs!$E$57 -> SUPUESTO | E49: =Inputs!$F$57 -> https://gastronomicareal.cl/refrigeracion/congeladoras | F49: =Inputs!$G$57 -> Bolsa para almacenamiento −18 °C; requiere selección por capacidad y redundancia.
A50: =Inputs!$B$58 -> Acero, lavado y extracción | B50: =Inputs!$C$58 -> 1800000 | C50: =Inputs!$D$58 -> CLP neto | D50: =Inputs!$E$58 -> SUPUESTO | E50: =Inputs!$F$58 -> Etapa 10 | F50: =Inputs!$G$58 -> Mesones, lavaderos, campana y elementos fijos; cotización pendiente.
A51: =Inputs!$B$59 -> Racks, bandejas e instrumentos | B51: =Inputs!$C$59 -> 1200000 | C51: =Inputs!$D$59 -> CLP neto | D51: =Inputs!$E$59 -> SUPUESTO | E51: =Inputs!$F$59 -> Etapa 10 | F51: =Inputs!$G$59 -> Carros, bandejas, balanzas, sondas y utensilios.
A52: =Inputs!$B$60 -> Flete e instalación | B52: =Inputs!$C$60 -> 0.15 | C52: =Inputs!$D$60 -> % sobre equipos | D52: =Inputs!$E$60 -> SUPUESTO | E52: =Inputs!$F$60 -> Etapa 10 | F52: =Inputs!$G$60 -> Flete Santiago–Temuco, conexión y puesta en marcha.
A53: =Inputs!$B$61 -> Habilitación sanitaria | B53: =Inputs!$C$61 -> 12000000 | C53: =Inputs!$D$61 -> CLP neto | D53: =Inputs!$E$61 -> SUPUESTO | E53: =Inputs!$F$61 -> 07-local-habilitacion/index.html | F53: =Inputs!$G$61 -> Riesgo principal; reemplazar por presupuesto desglosado de un local real.
A54: =Inputs!$B$62 -> Trámites, análisis y rotulado | B54: =Inputs!$C$62 -> 1000000 | C54: =Inputs!$D$62 -> CLP neto | D54: =Inputs!$E$62 -> SUPUESTO | E54: =Inputs!$F$62 -> 08-legal-normativo/index.html | F54: =Inputs!$G$62 -> Aranceles, laboratorio y artes; cotización pendiente.
A55: =Inputs!$B$63 -> Preoperación | B55: =Inputs!$C$63 -> 1500000 | C55: =Inputs!$D$63 -> CLP neto | D55: =Inputs!$E$63 -> SUPUESTO | E55: =Inputs!$F$63 -> Etapa 10 | F55: =Inputs!$G$63 -> Pruebas, capacitación, muestras y apertura.
A56: =Inputs!$B$64 -> Contingencia | B56: =Inputs!$C$64 -> 0.15 | C56: =Inputs!$D$64 -> % sobre equipos, instalación y habilitación | D56: =Inputs!$E$64 -> SUPUESTO | E56: =Inputs!$F$64 -> Etapa 10 | F56: =Inputs!$G$64 -> Reserva de estimación conceptual; no reemplaza cotizaciones.
A57: =Inputs!$B$65 -> Garantía de arriendo | B57: =Inputs!$C$65 -> 2 | C57: =Inputs!$D$65 -> meses | D57: =Inputs!$E$65 -> SUPUESTO | E57: =Inputs!$F$65 -> Etapa 10 | F57: =Inputs!$G$65 -> Activo recuperable al final si no hay daños.
A58: =Inputs!$B$66 -> Vida depreciable | B58: =Inputs!$C$66 -> 5 | C58: =Inputs!$D$66 -> años lineales | D58: =Inputs!$E$66 -> SUPUESTO | E58: =Inputs!$F$66 -> https://www.sii.cl/valores_y_fechas/tabla_vida_util_activo_inmovilizado.html | F58: =Inputs!$G$66 -> Simplificación financiera; validar categoría y depreciación tributaria por activo.
A59: =Inputs!$B$67 -> Valor residual | B59: =Inputs!$C$67 -> 0.1 | C59: =Inputs!$D$67 -> % del CAPEX depreciable | D59: =Inputs!$E$67 -> SUPUESTO | E59: =Inputs!$F$67 -> Etapa 10 | F59: =Inputs!$G$67 -> Valor de realización al año 5 antes de impuesto.
A60: =Inputs!$B$69 -> Pesimista: precio | B60: =Inputs!$C$69 -> 0.9 | C60: =Inputs!$D$69 -> multiplicador | D60: =Inputs!$E$69 -> SUPUESTO | E60: =Inputs!$F$69 -> Etapa 10 | F60: =Inputs!$G$69 -> Editable para análisis de riesgo.
A61: =Inputs!$B$70 -> Pesimista: volumen | B61: =Inputs!$C$70 -> 0.8 | C61: =Inputs!$D$70 -> multiplicador | D61: =Inputs!$E$70 -> SUPUESTO | E61: =Inputs!$F$70 -> Etapa 10 | F61: =Inputs!$G$70 -> Editable para análisis de riesgo.
A62: =Inputs!$B$71 -> Pesimista: costo variable | B62: =Inputs!$C$71 -> 1.1 | C62: =Inputs!$D$71 -> multiplicador | D62: =Inputs!$E$71 -> SUPUESTO | E62: =Inputs!$F$71 -> Etapa 10 | F62: =Inputs!$G$71 -> Editable para análisis de riesgo.
A63: =Inputs!$B$72 -> Pesimista: costo fijo | B63: =Inputs!$C$72 -> 1.1 | C63: =Inputs!$D$72 -> multiplicador | D63: =Inputs!$E$72 -> SUPUESTO | E63: =Inputs!$F$72 -> Etapa 10 | F63: =Inputs!$G$72 -> Editable para análisis de riesgo.
A64: =Inputs!$B$73 -> Pesimista: CAPEX | B64: =Inputs!$C$73 -> 1.15 | C64: =Inputs!$D$73 -> multiplicador | D64: =Inputs!$E$73 -> SUPUESTO | E64: =Inputs!$F$73 -> Etapa 10 | F64: =Inputs!$G$73 -> Editable para análisis de riesgo.
A65: =Inputs!$B$74 -> Base: precio | B65: =Inputs!$C$74 -> 1 | C65: =Inputs!$D$74 -> multiplicador | D65: =Inputs!$E$74 -> SUPUESTO | E65: =Inputs!$F$74 -> Etapa 10 | F65: =Inputs!$G$74 -> Editable para análisis de riesgo.
A66: =Inputs!$B$75 -> Base: volumen | B66: =Inputs!$C$75 -> 1 | C66: =Inputs!$D$75 -> multiplicador | D66: =Inputs!$E$75 -> SUPUESTO | E66: =Inputs!$F$75 -> Etapa 10 | F66: =Inputs!$G$75 -> Editable para análisis de riesgo.
A67: =Inputs!$B$76 -> Base: costo variable | B67: =Inputs!$C$76 -> 1 | C67: =Inputs!$D$76 -> multiplicador | D67: =Inputs!$E$76 -> SUPUESTO | E67: =Inputs!$F$76 -> Etapa 10 | F67: =Inputs!$G$76 -> Editable para análisis de riesgo.
A68: =Inputs!$B$77 -> Base: costo fijo | B68: =Inputs!$C$77 -> 1 | C68: =Inputs!$D$77 -> multiplicador | D68: =Inputs!$E$77 -> SUPUESTO | E68: =Inputs!$F$77 -> Etapa 10 | F68: =Inputs!$G$77 -> Editable para análisis de riesgo.
A69: =Inputs!$B$78 -> Base: CAPEX | B69: =Inputs!$C$78 -> 1 | C69: =Inputs!$D$78 -> multiplicador | D69: =Inputs!$E$78 -> SUPUESTO | E69: =Inputs!$F$78 -> Etapa 10 | F69: =Inputs!$G$78 -> Editable para análisis de riesgo.
A70: =Inputs!$B$79 -> Optimista: precio | B70: =Inputs!$C$79 -> 1.1 | C70: =Inputs!$D$79 -> multiplicador | D70: =Inputs!$E$79 -> SUPUESTO | E70: =Inputs!$F$79 -> Etapa 10 | F70: =Inputs!$G$79 -> Editable para análisis de riesgo.
A71: =Inputs!$B$80 -> Optimista: volumen | B71: =Inputs!$C$80 -> 1.2 | C71: =Inputs!$D$80 -> multiplicador | D71: =Inputs!$E$80 -> SUPUESTO | E71: =Inputs!$F$80 -> Etapa 10 | F71: =Inputs!$G$80 -> Editable para análisis de riesgo.
A72: =Inputs!$B$81 -> Optimista: costo variable | B72: =Inputs!$C$81 -> 0.95 | C72: =Inputs!$D$81 -> multiplicador | D72: =Inputs!$E$81 -> SUPUESTO | E72: =Inputs!$F$81 -> Etapa 10 | F72: =Inputs!$G$81 -> Editable para análisis de riesgo.
A73: =Inputs!$B$82 -> Optimista: costo fijo | B73: =Inputs!$C$82 -> 1 | C73: =Inputs!$D$82 -> multiplicador | D73: =Inputs!$E$82 -> SUPUESTO | E73: =Inputs!$F$82 -> Etapa 10 | F73: =Inputs!$G$82 -> Editable para análisis de riesgo.
A74: =Inputs!$B$83 -> Optimista: CAPEX | B74: =Inputs!$C$83 -> 0.95 | C74: =Inputs!$D$83 -> multiplicador | D74: =Inputs!$E$83 -> SUPUESTO | E74: =Inputs!$F$83 -> Etapa 10 | F74: =Inputs!$G$83 -> Editable para análisis de riesgo.
A75: =Inputs!$B$84 -> Sensibilidad: precio bajo | B75: =Inputs!$C$84 -> 0.9 | C75: =Inputs!$D$84 -> multiplicador | D75: =Inputs!$E$84 -> SUPUESTO | E75: =Inputs!$F$84 -> Etapa 10 | F75: =Inputs!$G$84 -> Editable para análisis de riesgo.
A76: =Inputs!$B$85 -> Sensibilidad: precio alto | B76: =Inputs!$C$85 -> 1.1 | C76: =Inputs!$D$85 -> multiplicador | D76: =Inputs!$E$85 -> SUPUESTO | E76: =Inputs!$F$85 -> Etapa 10 | F76: =Inputs!$G$85 -> Editable para análisis de riesgo.
A77: =Inputs!$B$86 -> Sensibilidad: volumen bajo | B77: =Inputs!$C$86 -> 0.8 | C77: =Inputs!$D$86 -> multiplicador | D77: =Inputs!$E$86 -> SUPUESTO | E77: =Inputs!$F$86 -> Etapa 10 | F77: =Inputs!$G$86 -> Editable para análisis de riesgo.
A78: =Inputs!$B$87 -> Sensibilidad: volumen alto | B78: =Inputs!$C$87 -> 1.2 | C78: =Inputs!$D$87 -> multiplicador | D78: =Inputs!$E$87 -> SUPUESTO | E78: =Inputs!$F$87 -> Etapa 10 | F78: =Inputs!$G$87 -> Editable para análisis de riesgo.

Sheet Calculos
A1: MOTOR DE CÁLCULO
A2: Bloques formulados para escenario activo, escenarios comparables y sensibilidad.
A4: Escenario activo
A5: Precio | B5: =IF(Inputs!$C$6="Pesimista",Inputs!$C$69,IF(Inputs!$C$6="Optimista",Inputs!$C$79,Inputs!$C$74)) -> 1
A6: Volumen | B6: =IF(Inputs!$C$6="Pesimista",Inputs!$C$70,IF(Inputs!$C$6="Optimista",Inputs!$C$80,Inputs!$C$75)) -> 1
A7: Costo variable | B7: =IF(Inputs!$C$6="Pesimista",Inputs!$C$71,IF(Inputs!$C$6="Optimista",Inputs!$C$81,Inputs!$C$76)) -> 1
A8: Costo fijo | B8: =IF(Inputs!$C$6="Pesimista",Inputs!$C$72,IF(Inputs!$C$6="Optimista",Inputs!$C$82,Inputs!$C$77)) -> 1
A9: CAPEX | B9: =IF(Inputs!$C$6="Pesimista",Inputs!$C$73,IF(Inputs!$C$6="Optimista",Inputs!$C$83,Inputs!$C$78)) -> 1
A11: Equipos | B11: =Inputs!$C$52+Inputs!$C$53+Inputs!$C$54+Inputs!$C$55+Inputs!$C$56+Inputs!$C$57+Inputs!$C$58+Inputs!$C$59 -> 8817795
A12: Flete/instalación | B12: =Calculos!$B$11*Inputs!$C$60 -> 1322669.2
A13: Arriendo mensual | B13: =IF(Inputs!$C$40>0,Inputs!$C$40,Inputs!$C$38*Inputs!$C$39) -> 759720
A14: Costo variable unitario base | B14: =((Inputs!$C$25*Inputs!$C$34+Inputs!$C$26*Inputs!$C$35+Inputs!$C$27*Inputs!$C$36+Inputs!$C$28)*(1+Inputs!$C$32)+Inputs!$C$29+Inputs!$C$30+Inputs!$C$31) -> 2652.9626
A15: Costo fijo mensual base | B15: =(Calculos!$B$13+Inputs!$C$41*Inputs!$C$42+Inputs!$C$43+Inputs!$C$44+Inputs!$C$45+Inputs!$C$46+Inputs!$C$47) -> 4123720
A16: CAPEX depreciable | B16: =(Calculos!$B$11+Calculos!$B$12+Inputs!$C$61)*(1+Inputs!$C$64)*Calculos!$B$9 -> 25461534
A17: CAPEX total | B17: =Calculos!$B$16+(Inputs!$C$62+Inputs!$C$63)*Calculos!$B$9 -> 27961534
A18: Depreciación anual | B18: =Calculos!$B$16/Inputs!$C$66 -> 5092306.8
A19: Valor residual bruto | B19: =Calculos!$B$16*Inputs!$C$67 -> 2546153.4
A20: Garantía arriendo | B20: =Calculos!$B$13*Inputs!$C$65 -> 1519440
A22: Concepto | B22: Año 0 | C22: Año 1 | D22: Año 2 | E22: Año 3 | F22: Año 4 | G22: Año 5
A23: Volumen | C23: =Inputs!$C$13*Calculos!$B$6 -> 30000 | D23: =Inputs!$C$14*Calculos!$B$6 -> 42000 | E23: =Inputs!$C$15*Calculos!$B$6 -> 54000 | F23: =Inputs!$C$16*Calculos!$B$6 -> 66000 | G23: =Inputs!$C$17*Calculos!$B$6 -> 72000
A24: Escalador | C24: =(1+Inputs!$C$8)^1 -> 1.03 | D24: =(1+Inputs!$C$8)^2 -> 1.0609 | E24: =(1+Inputs!$C$8)^3 -> 1.092727 | F24: =(1+Inputs!$C$8)^4 -> 1.1255088 | G24: =(1+Inputs!$C$8)^5 -> 1.1592741
A25: Precio | C25: =Inputs!$C$12*Calculos!$B$5*Calculos!$C$24 -> 4326 | D25: =Inputs!$C$12*Calculos!$B$5*Calculos!$D$24 -> 4455.78 | E25: =Inputs!$C$12*Calculos!$B$5*Calculos!$E$24 -> 4589.4534 | F25: =Inputs!$C$12*Calculos!$B$5*Calculos!$F$24 -> 4727.137 | G25: =Inputs!$C$12*Calculos!$B$5*Calculos!$G$24 -> 4868.9511
A26: Costo variable unitario | C26: =Calculos!$B$14*Calculos!$B$7*Calculos!$C$24 -> 2732.5514 | D26: =Calculos!$B$14*Calculos!$B$7*Calculos!$D$24 -> 2814.528 | E26: =Calculos!$B$14*Calculos!$B$7*Calculos!$E$24 -> 2898.9638 | F26: =Calculos!$B$14*Calculos!$B$7*Calculos!$F$24 -> 2985.9327 | G26: =Calculos!$B$14*Calculos!$B$7*Calculos!$G$24 -> 3075.5107
A27: Ingresos | C27: =Calculos!$C$23*Calculos!$C$25 -> 129780000 | D27: =Calculos!$D$23*Calculos!$D$25 -> 187142760 | E27: =Calculos!$E$23*Calculos!$E$25 -> 2.4783048e+08 | F27: =Calculos!$F$23*Calculos!$F$25 -> 3.1199104e+08 | G27: =Calculos!$G$23*Calculos!$G$25 -> 3.5056448e+08
A28: Costos variables | C28: =Calculos!$C$23*Calculos!$C$26 -> 81976543 | D28: =Calculos!$D$23*Calculos!$D$26 -> 1.1821018e+08 | E28: =Calculos!$E$23*Calculos!$E$26 -> 1.5654405e+08 | F28: =Calculos!$F$23*Calculos!$F$26 -> 1.9707156e+08 | G28: =Calculos!$G$23*Calculos!$G$26 -> 2.2143677e+08
A29: Costos fijos | C29: =Calculos!$B$15*12*Calculos!$B$8*Calculos!$C$24 -> 50969179 | D29: =Calculos!$B$15*12*Calculos!$B$8*Calculos!$D$24 -> 52498255 | E29: =Calculos!$B$15*12*Calculos!$B$8*Calculos!$E$24 -> 54073202 | F29: =Calculos!$B$15*12*Calculos!$B$8*Calculos!$F$24 -> 55695398 | G29: =Calculos!$B$15*12*Calculos!$B$8*Calculos!$G$24 -> 57366260
A30: EBITDA | C30: =Calculos!$C$27-Calculos!$C$28-Calculos!$C$29 -> -3165722.3 | D30: =Calculos!$D$27-Calculos!$D$28-Calculos!$D$29 -> 16434330 | E30: =Calculos!$E$27-Calculos!$E$28-Calculos!$E$29 -> 37213235 | F30: =Calculos!$F$27-Calculos!$F$28-Calculos!$F$29 -> 59224083 | G30: =Calculos!$G$27-Calculos!$G$28-Calculos!$G$29 -> 71761448
A31: Depreciación | C31: =Calculos!$B$18 -> 5092306.8 | D31: =Calculos!$B$18 -> 5092306.8 | E31: =Calculos!$B$18 -> 5092306.8 | F31: =Calculos!$B$18 -> 5092306.8 | G31: =Calculos!$B$18 -> 5092306.8
A32: EBIT | C32: =Calculos!$C$30-Calculos!$C$31 -> -8258029.1 | D32: =Calculos!$D$30-Calculos!$D$31 -> 11342023 | E32: =Calculos!$E$30-Calculos!$E$31 -> 32120928 | F32: =Calculos!$F$30-Calculos!$F$31 -> 54131777 | G32: =Calculos!$G$30-Calculos!$G$31 -> 66669142
A33: Pérdida tributaria inicial | C33: =0 -> 0 | D33: =Calculos!$C$36 -> 8258029.1 | E33: =Calculos!$D$36 -> 0 | F33: =Calculos!$E$36 -> 0 | G33: =Calculos!$F$36 -> 0
A34: Renta imponible | C34: =MAX(0,Calculos!$C$32-Calculos!$C$33) -> 0 | D34: =MAX(0,Calculos!$D$32-Calculos!$D$33) -> 3083994.4 | E34: =MAX(0,Calculos!$E$32-Calculos!$E$33) -> 32120928 | F34: =MAX(0,Calculos!$F$32-Calculos!$F$33) -> 54131777 | G34: =MAX(0,Calculos!$G$32-Calculos!$G$33) -> 66669142
A35: Impuesto | C35: =Calculos!$C$34*Inputs!$C$19 -> 0 | D35: =Calculos!$D$34*Inputs!$C$20 -> 462599.16 | E35: =Calculos!$E$34*Inputs!$C$21 -> 8030232.1 | F35: =Calculos!$F$34*Inputs!$C$22 -> 13532944 | G35: =Calculos!$G$34*Inputs!$C$23 -> 16667285
A36: Pérdida tributaria final | C36: =MAX(0,Calculos!$C$33-Calculos!$C$32) -> 8258029.1 | D36: =MAX(0,Calculos!$D$33-Calculos!$D$32) -> 0 | E36: =MAX(0,Calculos!$E$33-Calculos!$E$32) -> 0 | F36: =MAX(0,Calculos!$F$33-Calculos!$F$32) -> 0 | G36: =MAX(0,Calculos!$G$33-Calculos!$G$32) -> 0
A37: Capital de trabajo | C37: =Calculos!$C$27*Inputs!$C$48/365+Calculos!$C$28*Inputs!$C$49/365-Calculos!$C$28*Inputs!$C$50/365 -> 14035748 | D37: =Calculos!$D$27*Inputs!$C$48/365+Calculos!$D$28*Inputs!$C$49/365-Calculos!$D$28*Inputs!$C$50/365 -> 20239549 | E37: =Calculos!$E$27*Inputs!$C$48/365+Calculos!$E$28*Inputs!$C$49/365-Calculos!$E$28*Inputs!$C$50/365 -> 26802946 | F37: =Calculos!$F$27*Inputs!$C$48/365+Calculos!$F$28*Inputs!$C$49/365-Calculos!$F$28*Inputs!$C$50/365 -> 33741931 | G37: =Calculos!$G$27*Inputs!$C$48/365+Calculos!$G$28*Inputs!$C$49/365-Calculos!$G$28*Inputs!$C$50/365 -> 37913660
A38: Variación capital de trabajo | C38: =Calculos!$C$37-Calculos!$C$37 -> 0 | D38: =Calculos!$D$37-Calculos!$C$37 -> 6203800.8 | E38: =Calculos!$E$37-Calculos!$D$37 -> 6563396.6 | F38: =Calculos!$F$37-Calculos!$E$37 -> 6938984.8 | G38: =Calculos!$G$37-Calculos!$F$37 -> 4171729.6
A39: Recuperaciones terminales | C39: =0 -> 0 | D39: =0 -> 0 | E39: =0 -> 0 | F39: =0 -> 0 | G39: =Calculos!$B$19*(1-Inputs!$C$23)+Calculos!$G$37+Calculos!$B$20 -> 41342715
A40: Flujo libre | B40: =-(Calculos!$B$17+Calculos!$B$20+Calculos!$C$37) -> -43516722 | C40: =Calculos!$C$30-Calculos!$C$35-Calculos!$C$38+Calculos!$C$39 -> -3165722.3 | D40: =Calculos!$D$30-Calculos!$D$35-Calculos!$D$38+Calculos!$D$39 -> 9767930.3 | E40: =Calculos!$E$30-Calculos!$E$35-Calculos!$E$38+Calculos!$E$39 -> 22619606 | F40: =Calculos!$F$30-Calculos!$F$35-Calculos!$F$38+Calculos!$F$39 -> 38752154 | G40: =Calculos!$G$30-Calculos!$G$35-Calculos!$G$38+Calculos!$G$39 -> 92265149
A41: Factor descuento | B41: 1 | C41: =1/(1+Inputs!$C$7)^1 -> 0.86956522 | D41: =1/(1+Inputs!$C$7)^2 -> 0.75614367 | E41: =1/(1+Inputs!$C$7)^3 -> 0.65751623 | F41: =1/(1+Inputs!$C$7)^4 -> 0.57175325 | G41: =1/(1+Inputs!$C$7)^5 -> 0.49717674
A42: Flujo descontado | B42: =Calculos!$B$40 -> -43516722 | C42: =Calculos!$C$40*Calculos!$C$41 -> -2752802 | D42: =Calculos!$D$40*Calculos!$D$41 -> 7385958.7 | E42: =Calculos!$E$40*Calculos!$E$41 -> 14872758 | F42: =Calculos!$F$40*Calculos!$F$41 -> 22156670 | G42: =Calculos!$G$40*Calculos!$G$41 -> 45872085
A43: Flujo acumulado | B43: =Calculos!$B$40 -> -43516722 | C43: =Calculos!$B$43+Calculos!$C$40 -> -46682445 | D43: =Calculos!$C$43+Calculos!$D$40 -> -36914514 | E43: =Calculos!$D$43+Calculos!$E$40 -> -14294908 | F43: =Calculos!$E$43+Calculos!$F$40 -> 24457247 | G43: =Calculos!$F$43+Calculos!$G$40 -> 1.167224e+08
A44: Flujo descontado acumulado | B44: =Calculos!$B$42 -> -43516722 | C44: =Calculos!$B$44+Calculos!$C$42 -> -46269524 | D44: =Calculos!$C$44+Calculos!$D$42 -> -38883566 | E44: =Calculos!$D$44+Calculos!$E$42 -> -24010807 | F44: =Calculos!$E$44+Calculos!$F$42 -> -1854137.1 | G44: =Calculos!$F$44+Calculos!$G$42 -> 44017948
A46: Inversión inicial | B46: =-Calculos!$B$40 -> 43516722
A47: VAN | B47: =SUM(Calculos!$B$42:$G$42) -> 44017948
A48: TIR | B48: =IFERROR(IRR(Calculos!$B$40:$G$40),-1) -> 0.35689657
A49: Payback descontado | B49: =IFERROR(IF(Calculos!$C$44>=0,0+(-Calculos!$B$44/Calculos!$C$42),IF(Calculos!$D$44>=0,1+(-Calculos!$C$44/Calculos!$D$42),IF(Calculos!$E$44>=0,2+(-Calculos!$D$44/Calculos!$E$42),IF(Calculos!$F$44>=0,3+(-Calculos!$E$44/Calculos!$F$42),IF(Calculos!$G$44>=0,4+(-Calculos!$F$44/Calculos!$G$42),NA()))))),99) -> 4.0404197
A50: Índice de rentabilidad | B50: =(Calculos!$C$42+Calculos!$D$42+Calculos!$E$42+Calculos!$F$42+Calculos!$G$42)/(-Calculos!$B$40) -> 2.011518
A51: Fondeo máximo | B51: =-MIN(Calculos!$B$43:$G$43) -> 46682445
A52: Punto de equilibrio mensual | B52: =IF((Calculos!$C$25-Calculos!$C$26)>0,Calculos!$C$29/(Calculos!$C$25-Calculos!$C$26)/12,NA()) -> 2665.5593
A55: Escenario Pesimista
A56: Precio | B56: =Inputs!$C$69 -> 0.9
A57: Volumen | B57: =Inputs!$C$70 -> 0.8
A58: Costo variable | B58: =Inputs!$C$71 -> 1.1
A59: Costo fijo | B59: =Inputs!$C$72 -> 1.1
A60: CAPEX | B60: =Inputs!$C$73 -> 1.15
A62: Equipos | B62: =Inputs!$C$52+Inputs!$C$53+Inputs!$C$54+Inputs!$C$55+Inputs!$C$56+Inputs!$C$57+Inputs!$C$58+Inputs!$C$59 -> 8817795
A63: Flete/instalación | B63: =Calculos!$B$62*Inputs!$C$60 -> 1322669.2
A64: Arriendo mensual | B64: =IF(Inputs!$C$40>0,Inputs!$C$40,Inputs!$C$38*Inputs!$C$39) -> 759720
A65: Costo variable unitario base | B65: =((Inputs!$C$25*Inputs!$C$34+Inputs!$C$26*Inputs!$C$35+Inputs!$C$27*Inputs!$C$36+Inputs!$C$28)*(1+Inputs!$C$32)+Inputs!$C$29+Inputs!$C$30+Inputs!$C$31) -> 2652.9626
A66: Costo fijo mensual base | B66: =(Calculos!$B$64+Inputs!$C$41*Inputs!$C$42+Inputs!$C$43+Inputs!$C$44+Inputs!$C$45+Inputs!$C$46+Inputs!$C$47) -> 4123720
A67: CAPEX depreciable | B67: =(Calculos!$B$62+Calculos!$B$63+Inputs!$C$61)*(1+Inputs!$C$64)*Calculos!$B$60 -> 29280764
A68: CAPEX total | B68: =Calculos!$B$67+(Inputs!$C$62+Inputs!$C$63)*Calculos!$B$60 -> 32155764
A69: Depreciación anual | B69: =Calculos!$B$67/Inputs!$C$66 -> 5856152.8
A70: Valor residual bruto | B70: =Calculos!$B$67*Inputs!$C$67 -> 2928076.4
A71: Garantía arriendo | B71: =Calculos!$B$64*Inputs!$C$65 -> 1519440
A73: Concepto | B73: Año 0 | C73: Año 1 | D73: Año 2 | E73: Año 3 | F73: Año 4 | G73: Año 5
A74: Volumen | C74: =Inputs!$C$13*Calculos!$B$57 -> 24000 | D74: =Inputs!$C$14*Calculos!$B$57 -> 33600 | E74: =Inputs!$C$15*Calculos!$B$57 -> 43200 | F74: =Inputs!$C$16*Calculos!$B$57 -> 52800 | G74: =Inputs!$C$17*Calculos!$B$57 -> 57600
A75: Escalador | C75: =(1+Inputs!$C$8)^1 -> 1.03 | D75: =(1+Inputs!$C$8)^2 -> 1.0609 | E75: =(1+Inputs!$C$8)^3 -> 1.092727 | F75: =(1+Inputs!$C$8)^4 -> 1.1255088 | G75: =(1+Inputs!$C$8)^5 -> 1.1592741
A76: Precio | C76: =Inputs!$C$12*Calculos!$B$56*Calculos!$C$75 -> 3893.4 | D76: =Inputs!$C$12*Calculos!$B$56*Calculos!$D$75 -> 4010.202 | E76: =Inputs!$C$12*Calculos!$B$56*Calculos!$E$75 -> 4130.5081 | F76: =Inputs!$C$12*Calculos!$B$56*Calculos!$F$75 -> 4254.4233 | G76: =Inputs!$C$12*Calculos!$B$56*Calculos!$G$75 -> 4382.056
A77: Costo variable unitario | C77: =Calculos!$B$65*Calculos!$B$58*Calculos!$C$75 -> 3005.8066 | D77: =Calculos!$B$65*Calculos!$B$58*Calculos!$D$75 -> 3095.9808 | E77: =Calculos!$B$65*Calculos!$B$58*Calculos!$E$75 -> 3188.8602 | F77: =Calculos!$B$65*Calculos!$B$58*Calculos!$F$75 -> 3284.526 | G77: =Calculos!$B$65*Calculos!$B$58*Calculos!$G$75 -> 3383.0618
A78: Ingresos | C78: =Calculos!$C$74*Calculos!$C$76 -> 93441600 | D78: =Calculos!$D$74*Calculos!$D$76 -> 1.3474279e+08 | E78: =Calculos!$E$74*Calculos!$E$76 -> 1.7843795e+08 | F78: =Calculos!$F$74*Calculos!$F$76 -> 2.2463355e+08 | G78: =Calculos!$G$74*Calculos!$G$76 -> 2.5240643e+08
A79: Costos variables | C79: =Calculos!$C$74*Calculos!$C$77 -> 72139358 | D79: =Calculos!$D$74*Calculos!$D$77 -> 1.0402495e+08 | E79: =Calculos!$E$74*Calculos!$E$77 -> 1.3775876e+08 | F79: =Calculos!$F$74*Calculos!$F$77 -> 1.7342297e+08 | G79: =Calculos!$G$74*Calculos!$G$77 -> 1.9486436e+08
A80: Costos fijos | C80: =Calculos!$B$66*12*Calculos!$B$59*Calculos!$C$75 -> 56066097 | D80: =Calculos!$B$66*12*Calculos!$B$59*Calculos!$D$75 -> 57748080 | E80: =Calculos!$B$66*12*Calculos!$B$59*Calculos!$E$75 -> 59480522 | F80: =Calculos!$B$66*12*Calculos!$B$59*Calculos!$F$75 -> 61264938 | G80: =Calculos!$B$66*12*Calculos!$B$59*Calculos!$G$75 -> 63102886
A81: EBITDA | C81: =Calculos!$C$78-Calculos!$C$79-Calculos!$C$80 -> -34763855 | D81: =Calculos!$D$78-Calculos!$D$79-Calculos!$D$80 -> -27030247 | E81: =Calculos!$E$78-Calculos!$E$79-Calculos!$E$80 -> -18801335 | F81: =Calculos!$F$78-Calculos!$F$79-Calculos!$F$80 -> -10054361 | G81: =Calculos!$G$78-Calculos!$G$79-Calculos!$G$80 -> -5560819.6
A82: Depreciación | C82: =Calculos!$B$69 -> 5856152.8 | D82: =Calculos!$B$69 -> 5856152.8 | E82: =Calculos!$B$69 -> 5856152.8 | F82: =Calculos!$B$69 -> 5856152.8 | G82: =Calculos!$B$69 -> 5856152.8
A83: EBIT | C83: =Calculos!$C$81-Calculos!$C$82 -> -40620008 | D83: =Calculos!$D$81-Calculos!$D$82 -> -32886400 | E83: =Calculos!$E$81-Calculos!$E$82 -> -24657488 | F83: =Calculos!$F$81-Calculos!$F$82 -> -15910514 | G83: =Calculos!$G$81-Calculos!$G$82 -> -11416972
A84: Pérdida tributaria inicial | C84: =0 -> 0 | D84: =Calculos!$C$87 -> 40620008 | E84: =Calculos!$D$87 -> 73506408 | F84: =Calculos!$E$87 -> 98163895 | G84: =Calculos!$F$87 -> 1.1407441e+08
A85: Renta imponible | C85: =MAX(0,Calculos!$C$83-Calculos!$C$84) -> 0 | D85: =MAX(0,Calculos!$D$83-Calculos!$D$84) -> 0 | E85: =MAX(0,Calculos!$E$83-Calculos!$E$84) -> 0 | F85: =MAX(0,Calculos!$F$83-Calculos!$F$84) -> 0 | G85: =MAX(0,Calculos!$G$83-Calculos!$G$84) -> 0
A86: Impuesto | C86: =Calculos!$C$85*Inputs!$C$19 -> 0 | D86: =Calculos!$D$85*Inputs!$C$20 -> 0 | E86: =Calculos!$E$85*Inputs!$C$21 -> 0 | F86: =Calculos!$F$85*Inputs!$C$22 -> 0 | G86: =Calculos!$G$85*Inputs!$C$23 -> 0
A87: Pérdida tributaria final | C87: =MAX(0,Calculos!$C$84-Calculos!$C$83) -> 40620008 | D87: =MAX(0,Calculos!$D$84-Calculos!$D$83) -> 73506408 | E87: =MAX(0,Calculos!$E$84-Calculos!$E$83) -> 98163895 | F87: =MAX(0,Calculos!$F$84-Calculos!$F$83) -> 1.1407441e+08 | G87: =MAX(0,Calculos!$G$84-Calculos!$G$83) -> 1.2549138e+08
A88: Capital de trabajo | C88: =Calculos!$C$78*Inputs!$C$48/365+Calculos!$C$79*Inputs!$C$49/365-Calculos!$C$79*Inputs!$C$50/365 -> 10644763 | D88: =Calculos!$D$78*Inputs!$C$48/365+Calculos!$D$79*Inputs!$C$49/365-Calculos!$D$79*Inputs!$C$50/365 -> 15349748 | E88: =Calculos!$E$78*Inputs!$C$48/365+Calculos!$E$79*Inputs!$C$49/365-Calculos!$E$79*Inputs!$C$50/365 -> 20327452 | F88: =Calculos!$F$78*Inputs!$C$48/365+Calculos!$F$79*Inputs!$C$49/365-Calculos!$F$79*Inputs!$C$50/365 -> 25590003 | G88: =Calculos!$G$78*Inputs!$C$48/365+Calculos!$G$79*Inputs!$C$49/365-Calculos!$G$79*Inputs!$C$50/365 -> 28753858
A89: Variación capital de trabajo | C89: =Calculos!$C$88-Calculos!$C$88 -> 0 | D89: =Calculos!$D$88-Calculos!$C$88 -> 4704985.1 | E89: =Calculos!$E$88-Calculos!$D$88 -> 4977703.9 | F89: =Calculos!$F$88-Calculos!$E$88 -> 5262551.4 | G89: =Calculos!$G$88-Calculos!$F$88 -> 3163854.9
A90: Recuperaciones terminales | C90: =0 -> 0 | D90: =0 -> 0 | E90: =0 -> 0 | F90: =0 -> 0 | G90: =Calculos!$B$70*(1-Inputs!$C$23)+Calculos!$G$88+Calculos!$B$71 -> 32469355
A91: Flujo libre | B91: =-(Calculos!$B$68+Calculos!$B$71+Calculos!$C$88) -> -44319967 | C91: =Calculos!$C$81-Calculos!$C$86-Calculos!$C$89+Calculos!$C$90 -> -34763855 | D91: =Calculos!$D$81-Calculos!$D$86-Calculos!$D$89+Calculos!$D$90 -> -31735232 | E91: =Calculos!$E$81-Calculos!$E$86-Calculos!$E$89+Calculos!$E$90 -> -23779039 | F91: =Calculos!$F$81-Calculos!$F$86-Calculos!$F$89+Calculos!$F$90 -> -15316912 | G91: =Calculos!$G$81-Calculos!$G$86-Calculos!$G$89+Calculos!$G$90 -> 23744681
A92: Factor descuento | B92: 1 | C92: =1/(1+Inputs!$C$7)^1 -> 0.86956522 | D92: =1/(1+Inputs!$C$7)^2 -> 0.75614367 | E92: =1/(1+Inputs!$C$7)^3 -> 0.65751623 | F92: =1/(1+Inputs!$C$7)^4 -> 0.57175325 | G92: =1/(1+Inputs!$C$7)^5 -> 0.49717674
A93: Flujo descontado | B93: =Calculos!$B$91 -> -44319967 | C93: =Calculos!$C$91*Calculos!$C$92 -> -30229439 | D93: =Calculos!$D$91*Calculos!$D$92 -> -23996395 | E93: =Calculos!$E$91*Calculos!$E$92 -> -15635104 | F93: =Calculos!$F$91*Calculos!$F$92 -> -8757494.3 | G93: =Calculos!$G$91*Calculos!$G$92 -> 11805303
A94: Flujo acumulado | B94: =Calculos!$B$91 -> -44319967 | C94: =Calculos!$B$94+Calculos!$C$91 -> -79083822 | D94: =Calculos!$C$94+Calculos!$D$91 -> -1.1081905e+08 | E94: =Calculos!$D$94+Calculos!$E$91 -> -1.3459809e+08 | F94: =Calculos!$E$94+Calculos!$F$91 -> -1.49915e+08 | G94: =Calculos!$F$94+Calculos!$G$91 -> -1.2617032e+08
A95: Flujo descontado acumulado | B95: =Calculos!$B$93 -> -44319967 | C95: =Calculos!$B$95+Calculos!$C$93 -> -74549406 | D95: =Calculos!$C$95+Calculos!$D$93 -> -98545801 | E95: =Calculos!$D$95+Calculos!$E$93 -> -1.141809e+08 | F95: =Calculos!$E$95+Calculos!$F$93 -> -1.229384e+08 | G95: =Calculos!$F$95+Calculos!$G$93 -> -1.111331e+08
A97: Inversión inicial | B97: =-Calculos!$B$91 -> 44319967
A98: VAN | B98: =SUM(Calculos!$B$93:$G$93) -> -1.111331e+08
A99: TIR | B99: =IFERROR(IRR(Calculos!$B$91:$G$91),-1) -> -1
A100: Payback descontado | B100: =IFERROR(IF(Calculos!$C$95>=0,0+(-Calculos!$B$95/Calculos!$C$93),IF(Calculos!$D$95>=0,1+(-Calculos!$C$95/Calculos!$D$93),IF(Calculos!$E$95>=0,2+(-Calculos!$D$95/Calculos!$E$93),IF(Calculos!$F$95>=0,3+(-Calculos!$E$95/Calculos!$F$93),IF(Calculos!$G$95>=0,4+(-Calculos!$F$95/Calculos!$G$93),NA()))))),99) -> 99
A101: Índice de rentabilidad | B101: =(Calculos!$C$93+Calculos!$D$93+Calculos!$E$93+Calculos!$F$93+Calculos!$G$93)/(-Calculos!$B$91) -> -1.5075176
A102: Fondeo máximo | B102: =-MIN(Calculos!$B$94:$G$94) -> 1.49915e+08
A103: Punto de equilibrio mensual | B103: =IF((Calculos!$C$76-Calculos!$C$77)>0,Calculos!$C$80/(Calculos!$C$76-Calculos!$C$77)/12,NA()) -> 5263.8682
A106: Escenario Base
A107: Precio | B107: =Inputs!$C$74 -> 1
A108: Volumen | B108: =Inputs!$C$75 -> 1
A109: Costo variable | B109: =Inputs!$C$76 -> 1
A110: Costo fijo | B110: =Inputs!$C$77 -> 1
A111: CAPEX | B111: =Inputs!$C$78 -> 1
...
