Workbook

Sheet Resumen
A1: EVALUACIÓN ECONÓMICA — PIZZERÍA B2B
A2: Flujo libre sin deuda · CLP nominales · 5 años
A4: Decisión del escenario activo
A6: Inversión inicial | B6: =Calculos!$B$46 -> 38467030 | D6: Escenario | E6: =Inputs!$C$5 -> Base
A7: Fondeo máximo | B7: =Calculos!$B$51 -> 1.2549356e+08 | D7: TMAR | E7: =Inputs!$C$6 -> 0.2046
A8: VAN | B8: =Calculos!$B$47 -> -91764381 | D8: Capital disponible | E8: =Inputs!$C$8 -> 50000000
A9: TIR | B9: =Calculos!$B$48 -> #N/A
A10: Payback descontado | B10: =Calculos!$B$49 -> #N/A | D10: Dictamen | E10: =IF(AND(Resumen!$B$8>0,IF(ISNA(Resumen!$B$9),FALSE(),Resumen!$B$9>Inputs!$C$6),Resumen!$B$7<=Inputs!$C$8),"VIABLE · SUPUESTOS","RECHAZAR / REDISEÑAR") -> RECHAZAR / REDISEÑAR
A11: Índice de rentabilidad | B11: =Calculos!$B$50 -> -1.3855333
A12: Punto equilibrio (u./mes) | B12: =Calculos!$B$52 -> 2169.8611 | D12: Control VAN | E12: =IF(ABS(Resumen!$B$8-SUM(Calculos!$B$42:$G$42))<1,"OK","REVISAR") -> OK
D13: Flujo convencional | E13: =IF(AND(Calculos!$B$40<0,Calculos!$G$40>0),"OK","REVISAR TIR") -> REVISAR TIR
A15: Criterios de Ingeniería Económica
A17: • VAN > 0: el proyecto crea valor a la TMAR seleccionada.
A18: • TIR > TMAR: la rentabilidad interna supera el rendimiento mínimo exigido.
A19: • VAN y TIR no se comparan entre sí: tienen unidades diferentes.
A20: • El flujo es económico y no incorpora deuda, intereses ni dividendos.
A22: Guía de lectura del modelo
A24: Input editable | B24: Azul sobre amarillo | D24: Fórmula | E24: Negro sobre claro
A25: Vínculo interno | B25: Verde en Fuentes | D25: Alerta | E25: Rojo = alerta

Sheet Inputs
A1: INPUTS Y SUPUESTOS DEL MODELO
A2: Edite sólo las celdas amarillas con fuente azul.
A4: Categoría | B4: Parámetro | C4: Valor | D4: Unidad | E4: Confianza | F4: Fuente | G4: Nota
A5: Modelo | B5: Escenario activo | C5: Base | D5: texto | E5: SUPUESTO | F5: Selección del usuario | G5: Valores permitidos: Pesimista, Base u Optimista.
A6: Modelo | B6: TMAR nominal anual | C6: 0.2046 | D6: % anual nominal | E6: ESTIMADO | F6: https://www.cmfchile.cl/portal/estadisticas/626/w4-article-111825.html | G6: PISO OBSERVADO, no el costo de oportunidad del titular. CMF, Certificado 07/2026 (promedios de junio 2026, vigente desde el 14-07-2026): interés corriente de 20,46% anual para operaciones no reajustables en moneda nacional de 90 días o más entre 200 y 5.000 UF. La inversión inicial de $43.516.722 equivale a 1.065 UF, dentro de ese tramo. El capital propio es subordinado a esa deuda, luego la TMAR correcta es MAYOR. Reemplaza el stub de 15% de la etapa 10, que quedaba por DEBAJO del costo observado de deuda del mismo tamaño. Spread sobre la TPM (4,5%, Banco Central, https://www.bcentral.cl/areas/politica-monetaria): 15,96 puntos. NO se descompone riesgo por riesgo: no existe fuente pública que lo permita para una microempresa de alimentos en Temuco y repartir los puntos con decimales sería inventar. Límite: el interés corriente es un promedio de operaciones heterogéneas, expresado en forma lineal anual base 360 días, no una cotización para esta empresa. La decisión no es sensible a la tasa: el VAN se anula recién en 35,69% (la TIR); VAN@15% $44.017.948, VAN@20,46% $28.308.713. Gestión que lo cerraría: que el titular declare por escrito el retorno de su alternativa real de inversión.
A7: Modelo | B7: Inflación anual | C7: 0.03 | D7: % anual desde año 2 | E7: ESTIMADO | F7: https://www.bcentral.cl/documents/33528/8413153/IPoM%2Bjunio%2B2026.pdf/93388589-0929-4ad6-b166-10981ca34946 | G7: IPoM junio 2026 ubica expectativas a uno y dos años en torno a 3%. Se escala precio y costos simétricamente.
A8: Modelo | B8: Capital máximo disponible | C8: 50000000 | D8: CLP | E8: VERIFICADO | F8: datos/supuestos.json#meta.restriccion_capital_clp | G8: Restricción declarada en el enunciado.
A9: Modelo | B9: Horizonte de evaluación | C9: 5 | D9: años | E9: SUPUESTO | F9: datos/supuestos.json#meta.horizonte_evaluacion_anios | G9: Horizonte fijado en el statement.
A10: Ventas | B10: Precio B2B neto base | C10: 4200 | D10: CLP neto/unidad en pesos base 2026 | E10: SUPUESTO | F10: 02-competencia/index.html | G10: Se usa solo porque el parámetro de etapa 02 está pendiente. Está entre PF retail neto ($3.017) y foodservice publicado ($5.034); no representa disposición a pagar validada.
A11: Ventas | B11: SOM año 1 (0 = usar referencia) | C11: 0 | D11: pizzas/mes | E11: PENDIENTE | F11: datos/supuestos.json#mercado.som_ano1_pizzas_mes | G11: 0 = usar el volumen año 1 de referencia. La etapa 03 lo cierra en terreno.
A12: Ventas | B12: Volumen año 1 (referencia) | C12: 30000 | D12: pizzas/año | E12: SUPUESTO | F12: 01-mercado/index.html | G12: 2.500 unidades/mes. Sustituir por mercado.som_ano1_pizzas_mes × 12 cuando etapa 03 lo valide.
A13: Ventas | B13: Volumen año 2 (referencia) | C13: 42000 | D13: pizzas/año | E13: SUPUESTO | F13: Etapa 10 | G13: Rampa comercial no validada.
A14: Ventas | B14: Volumen año 3 (referencia) | C14: 54000 | D14: pizzas/año | E14: SUPUESTO | F14: Etapa 10 | G14: Rampa comercial no validada.
A15: Ventas | B15: Volumen año 4 (referencia) | C15: 66000 | D15: pizzas/año | E15: SUPUESTO | F15: Etapa 10 | G15: Rampa comercial no validada.
A16: Ventas | B16: Volumen año 5 (referencia) | C16: 72000 | D16: pizzas/año | E16: SUPUESTO | F16: Etapa 10 | G16: Rampa comercial no validada.
A17: Ventas | B17: Rampa año 2 (0 = derivar) | C17: 0 | D17: multiplicador sobre año 1 | E17: PENDIENTE | F17: datos/supuestos.json#comercial.rampa_ano2_factor | G17: 0 = derivar la forma de los volúmenes de referencia. La etapa 11 no publicó factor y no se inventa uno.
... A38: Operación | B38: Arriendo por m²/mes | C38: 6331 | D38: CLP/m²/mes | E38: ESTIMADO | F38: https://chilepropiedades.cl/ver-publicacion/arriendo-mensual/temuco/bodega/bodega-nueva-de-1-500-m2-acceso-norte-de-tco-162267/117714745 ; https://propiedades.bmi.cl/6057 | G38: Punto medio entre avisos industriales de 0,15 y 0,16 UF/m²/mes, convertido con UF base $40.844,79. Son bodegas mayores; no prueba precio de un local alimentario pequeño.
A39: Operación | B39: Arriendo mensual directo (0 = calcular) | C39: 0 | D39: CLP/mes | E39: PENDIENTE | G39: Depende del metraje, gastos comunes y de encontrar un inmueble compatible con uso de suelo y habilitación sanitaria.
A40: Operación | B40: Nómina bruta mensual | C40: 1100000 | D40: CLP/mes, suma de sueldos brutos imponibles de trabajadores dependientes | E40: ESTIMADO | F40: https://www.ine.gob.cl/estadisticas-por-tema/mercado-laboral/encuesta-suplementaria-de-ingresos ; https://fcje.ufro.cl/noticias/la-araucania-frente-a-la-esi-2025-desafios-para-un-desarrollo-con-mejores-ingresos/ ; datos/supuestos.json#macro.ingreso_minimo_mensual_clp | G40: RÉGIMEN, desde el mes 4. Dotación dependiente: 1 operario de producción a jornada completa 42 h ($700.000 bruto) + 1 operario polivalente a jornada parcial 24 h ($400.000 bruto). Cada bruto incluye sueldo base + gratificación art. 50 del Código del Trabajo (25% con tope de 4,75 IMM anuales = $219.115/mes); no volver a sumarla. ESTE VALOR NO INCLUYE EL RETIRO DE LA TITULAR: el modelo debe sumar rrhh.retiro_titular_mensual_clp SIN aplicarle macro.factor_costo_empresa. Si se prefiere una sola línea ya calculada, usar rrhh.costo_personal_mensual_regimen_clp. Los sueldos son ESTIMADOS: no existe serie pública de remuneración por cargo y comuna; se anclaron en el ingreso mínimo legal y en la ESI 2025 convertida de líquido a bruto.
A41: Operación | B41: Factor costo empresa | C41: 1.0853 | D41: multiplicador sobre sueldo bruto imponible de trabajador dependiente | E41: VERIFICADO | F41: https://www.spensiones.cl/portal/institucional/594/w3-propertyvalue-10906.html ; https://www.chileatiende.gob.cl/fichas/130987-aportes-del-empleador-al-sistema-de-pensiones ; https://www.isl.gob.cl/cotizaciones/ ; https://www.isl.gob.cl/wp-content/uploads/2024/08/Clasificador-Actividades-Economicas-2021.pdf ; https://www.previred.com/indicadores-previsionales/ | G41: MULTIPLICADOR DESNUDO, se usa tal cual (1,0853 = 8,53% sobre el bruto). Suma: 3,50% cotización de cargo del empleador Ley 21.735 vigente 08-2026 a 07-2027 (incluye el SIS, que desde agosto 2026 se financia dentro del Seguro Social Previsional y ya no se cotiza aparte) + 2,40% seguro de cesantía AFC contrato indefinido + 0,93% tasa base Ley 16.744 (0,90% básica + 0,03% SANNA) + 1,70% cotización adicional DS 110 para CIIU 107500 'elaboración de comidas y platos preparados envasados, rotulados y con información nutricional'. CONDICIONES: contrato indefinido (a plazo fijo el AFC sube a 3,00% y el factor a 1,0913); empresa nueva sin evaluación de siniestralidad (DS 67 puede subir o bajar la adicional desde el tercer año); rentas muy por debajo del tope imponible de 90 UF, por lo que todas las tasas aplican íntegras. NO APLICA al retiro de la titular por sueldo empresarial (ver rrhh.retiro_titular_mensual_clp). NO incluye provisiones de feriado ni de indemnización: para eso ver rrhh.factor_costo_empresa_con_provisiones. ADVERTENCIA: el stub 1,22 de la etapa 10 sobrestima el desembolso mensual exigible en ~14 puntos porcentuales.
A42: Operación | B42: Servicios fijos mensuales | C42: 180000 | D42: CLP/mes | E42: SUPUESTO | F42: Etapa 10 | G42: Cargo fijo de electricidad, agua, gas, internet y residuos, separado del consumo variable.
A43: Operación | B43: Mantenimiento mensual | C43: 100000 | D43: CLP/mes | E43: SUPUESTO | F43: Etapa 10 | G43: Reserva preventiva; validar con equipos elegidos.
A44: Operación | B44: Administración mensual | C44: 160000 | D44: CLP/mes | E44: SUPUESTO | F44: Etapa 10 | G44: Contabilidad, software básico, telefonía y gastos bancarios.
A45: Operación | B45: Ventas mensuales | C45: 180000 | D45: CLP/mes | E45: SUPUESTO | F45: Etapa 10 | G45: Muestras, visitas y material comercial.
A46: Operación | B46: Seguros mensuales | C46: 60000 | D46: CLP/mes | E46: SUPUESTO | F46: Etapa 10 | G46: Cotización pendiente.
A47: Operación | B47: Días cuentas por cobrar | C47: 30 | D47: días | E47: SUPUESTO | F47: datos/parametros-02-competencia.json#precios.plazo_cobro_dias | G47: Fallback consistente con el modelo de negocio; debe sustituirse por práctica validada.
A48: Operación | B48: Días inventario | C48: 15 | D48: días de costo variable | E48: SUPUESTO | F48: Etapa 10 | G48: Materia prima más producto terminado.
A49: Operación | B49: Días cuentas por pagar | C49: 0 | D49: días de costo variable | E49: SUPUESTO | F49: Etapa 10 | G49: Caso conservador sin crédito de proveedores.
A50: Operación | B50: Costo de personal mensual (0 = calcular) | C50: 2393830 | D50: CLP/mes | E50: ESTIMADO | F50: 09-rrhh/index.html | G50: DERIVADO, no es un dato independiente: 1.100.000 × 1,0853 + 1.200.000. Existe sólo para evitar que el retiro de la titular se pierda si el modelo cablea una sola línea de personal. Si se usa esta clave, NO multiplicar de nuevo por macro.factor_costo_empresa. Compara contra el stub de E10 (2.200.000 × 1,22 = 2.684.000): $290.170/mes menos, $3.482.040 al año.
A51: Operación | B51: Capacidad instalada (un/día, 0 = sin tope) | C51: 60 | D51: unidades/día (SKU familiar 30 cm) | E51: ESTIMADO | F51: https://calvac.cl/venta/abatidor-10-bandejas-2/ + https://www.supermaq.cl/abatidor/abatidor_congelador_5_bandejas.pdf | G51: Cuello de botella GEOMÉTRICO, no térmico. Bandeja de 610x410 mm: floor(610/300) x floor(410/300) = 2 discos de 300 mm por bandeja; 10 bandejas = 20 pizzas/ciclo = 8,5 kg, el 28% de los 30 kg declarados. Con ciclo de 240 min: 2 ciclos en jornada de 8,4 h más 1 ciclo desatendido que el equipo almacena solo al terminar = 3 ciclos/día x 20 = 60. Techo absoluto con operación 24 h: 6 ciclos = 120/día. El horno pizzero de 2 cámaras 40x40 (~24 pizzas/h) y la amasadora de 20 kg (83 bollos de 240 g) NO son limitantes. En SKU individual de 200 mm: 3x2 = 6 por bandeja = 60/ciclo = 180/día.
... A88: Escenarios | B88: Sensibilidad: volumen alto | C88: 1 | D88: multiplicador | E88: PENDIENTE | F88: datos/supuestos.json#escenarios.volumen_optimista_factor | G88: SIN ANCLA — eje neutro mientras la etapa 12 no publique banda.

Sheet Inversion
A1: INVERSIÓN INICIAL
A2: Escenario activo · montos desde Inputs y fórmulas.
A4: Concepto | B4: Monto | C4: Tratamiento | D4: Referencia
A5: Equipos principales | B5: =Calculos!$B$11 -> 10120237 | C5: Depreciable | D5: Inputs / Calculos
A6: Flete e instalación | B6: =Calculos!$B$12 -> 1518035.6 | C6: Depreciable | D6: Inputs / Calculos
A7: Habilitación + contingencia | B7: =Calculos!$B$16-Calculos!$B$11-Calculos!$B$12 -> 15545741 | C7: Depreciable | D7: Inputs / Calculos
A8: Trámites y preoperación | B8: =Calculos!$B$17-Calculos!$B$16 -> 2500000 | C8: No depreciable en este modelo | D8: Inputs / Calculos
A9: Garantía de arriendo | B9: =Calculos!$B$20 -> 1519440 | C9: Recuperable al año 5 | D9: Inputs / Calculos
A10: Capital de trabajo inicial | B10: =Calculos!$C$37 -> 7263576.7 | C10: Recuperable al año 5 | D10: Inputs / Calculos
A12: INVERSIÓN INICIAL TOTAL | B12: =Calculos!$B$46 -> 38467030

Sheet Flujo_Caja
A1: FLUJO DE CAJA LIBRE DEL PROYECTO
A2: Escenario de Inputs · CLP nominales · sin financiamiento.
A4: Concepto | B4: Año 0 | C4: Año 1 | D4: Año 2 | E4: Año 3 | F4: Año 4 | G4: Año 5
A5: Volumen | B5: =Calculos!$B$23 -> 0 | C5: =Calculos!$C$23 -> 15840 | D5: =Calculos!$D$23 -> 15840 | E5: =Calculos!$E$23 -> 15840 | F5: =Calculos!$F$23 -> 15840 | G5: =Calculos!$G$23 -> 15840
A6: Precio | B6: =Calculos!$B$25 -> 0 | C6: =Calculos!$C$25 -> 4326 | D6: =Calculos!$D$25 -> 4455.78 | E6: =Calculos!$E$25 -> 4589.4534 | F6: =Calculos!$F$25 -> 4727.137 | G6: =Calculos!$G$25 -> 4868.9511
A7: Ingresos | B7: =Calculos!$B$27 -> 0 | C7: =Calculos!$C$27 -> 68523840 | D7: =Calculos!$D$27 -> 70579555 | E7: =Calculos!$E$27 -> 72696942 | F7: =Calculos!$F$27 -> 74877850 | G7: =Calculos!$G$27 -> 77124186
A8: Costos variables | B8: =Calculos!$B$28 -> 0 | C8: =Calculos!$C$28 -> 39699352 | D8: =Calculos!$D$28 -> 40890333 | E8: =Calculos!$E$28 -> 42117042 | F8: =Calculos!$F$28 -> 43380554 | G8: =Calculos!$G$28 -> 44681970
A9: Costos fijos | B9: =Calculos!$B$29 -> 0 | C9: =Calculos!$C$29 -> 47382678 | D9: =Calculos!$D$29 -> 48804158 | E9: =Calculos!$E$29 -> 50268283 | F9: =Calculos!$F$29 -> 51776332 | G9: =Calculos!$G$29 -> 53329622
A10: EBITDA | B10: =Calculos!$B$30 -> 0 | C10: =Calculos!$C$30 -> -18558190 | D10: =Calculos!$D$30 -> -19114936 | E10: =Calculos!$E$30 -> -19688384 | F10: =Calculos!$F$30 -> -20279035 | G10: =Calculos!$G$30 -> -20887406
A11: Depreciación | B11: =Calculos!$B$31 -> 0 | C11: =Calculos!$C$31 -> 2718401.3 | D11: =Calculos!$D$31 -> 2718401.3 | E11: =Calculos!$E$31 -> 2718401.3 | F11: =Calculos!$F$31 -> 2718401.3 | G11: =Calculos!$G$31 -> 2718401.3
A12: EBIT | B12: =Calculos!$B$32 -> 0 | C12: =Calculos!$C$32 -> -21276591 | D12: =Calculos!$D$32 -> -21833337 | E12: =Calculos!$E$32 -> -22406785 | F12: =Calculos!$F$32 -> -22997437 | G12: =Calculos!$G$32 -> -23605808
A13: Pérdida tributaria inicial | B13: =Calculos!$B$33 -> 0 | C13: =Calculos!$C$33 -> 0 | D13: =Calculos!$D$33 -> 21276591 | E13: =Calculos!$E$33 -> 43109928 | F13: =Calculos!$F$33 -> 65516713 | G13: =Calculos!$G$33 -> 88514150
A14: Renta imponible | B14: =Calculos!$B$34 -> 0 | C14: =Calculos!$C$34 -> 0 | D14: =Calculos!$D$34 -> 0 | E14: =Calculos!$E$34 -> 0 | F14: =Calculos!$F$34 -> 0 | G14: =Calculos!$G$34 -> 0
A15: Impuesto | B15: =Calculos!$B$35 -> 0 | C15: =Calculos!$C$35 -> 0 | D15: =Calculos!$D$35 -> 0 | E15: =Calculos!$E$35 -> 0 | F15: =Calculos!$F$35 -> 0 | G15: =Calculos!$G$35 -> 0
A16: Pérdida tributaria final | B16: =Calculos!$B$36 -> 0 | C16: =Calculos!$C$36 -> 21276591 | D16: =Calculos!$D$36 -> 43109928 | E16: =Calculos!$E$36 -> 65516713 | F16: =Calculos!$F$36 -> 88514150 | G16: =Calculos!$G$36 -> 1.1211996e+08
A17: Capital de trabajo | B17: =Calculos!$B$37 -> 0 | C17: =Calculos!$C$37 -> 7263576.7 | D17: =Calculos!$D$37 -> 7481484 | E17: =Calculos!$E$37 -> 7705928.5 | F17: =Calculos!$F$37 -> 7937106.3 | G17: =Calculos!$G$37 -> 8175219.5
A18: Variación capital de trabajo | B18: =Calculos!$B$38 -> 0 | C18: =Calculos!$C$38 -> 0 | D18: =Calculos!$D$38 -> 217907.3 | E18: =Calculos!$E$38 -> 224444.52 | F18: =Calculos!$F$38 -> 231177.85 | G18: =Calculos!$G$38 -> 238113.19
A19: Recuperaciones terminales | B19: =Calculos!$B$39 -> 0 | C19: =Calculos!$C$39 -> 0 | D19: =Calculos!$D$39 -> 0 | E19: =Calculos!$E$39 -> 0 | F19: =Calculos!$F$39 -> 0 | G19: =Calculos!$G$39 -> 12413061
A20: Flujo libre | B20: =Calculos!$B$40 -> -38467030 | C20: =Calculos!$C$40 -> -18558190 | D20: =Calculos!$D$40 -> -19332843 | E20: =Calculos!$E$40 -> -19912828 | F20: =Calculos!$F$40 -> -20510213 | G20: =Calculos!$G$40 -> -8712458.6
A21: Factor descuento | B21: =Calculos!$B$41 -> 1 | C21: =Calculos!$C$41 -> 0.83015109 | D21: =Calculos!$D$41 -> 0.68915083 | E21: =Calculos!$E$41 -> 0.57209931 | F21: =Calculos!$F$41 -> 0.47492886 | G21: =Calculos!$G$41 -> 0.39426271
A22: Flujo descontado | B22: =Calculos!$B$42 -> -38467030 | C22: =Calculos!$C$42 -> -15406102 | D22: =Calculos!$D$42 -> -13323245 | E22: =Calculos!$E$42 -> -11392115 | F22: =Calculos!$F$42 -> -9740892.2 | G22: =Calculos!$G$42 -> -3434997.6
A23: Flujo acumulado | B23: =Calculos!$B$43 -> -38467030 | C23: =Calculos!$C$43 -> -57025220 | D23: =Calculos!$D$43 -> -76358063 | E23: =Calculos!$E$43 -> -96270891 | F23: =Calculos!$F$43 -> -1.167811e+08 | G23: =Calculos!$G$43 -> -1.2549356e+08
A24: Flujo descontado acumulado | B24: =Calculos!$B$44 -> -38467030 | C24: =Calculos!$C$44 -> -53873132 | D24: =Calculos!$D$44 -> -67196376 | E24: =Calculos!$E$44 -> -78588492 | F24: =Calculos!$F$44 -> -88329384 | G24: =Calculos!$G$44 -> -91764381

Sheet Escenarios
A1: ESCENARIOS
A2: Cada caso recalcula impuestos, capital de trabajo y valor terminal.
A4: Escenario | B4: VAN | C4: TIR | D4: Inversión inicial | E4: Fondeo máximo | F4: Payback descontado | G4: Punto equilibrio/mes
A5: Pesimista | B5: =Calculos!$B$102 -> -1.5902962e+08 | C5: =Calculos!$B$103 -> #N/A | D5: =Calculos!$B$101 -> 45795247 | E5: =Calculos!$B$106 -> 2.3544791e+08 | F5: =Calculos!$B$104 -> #N/A | G5: =Calculos!$B$107 -> 6489.5569
A6: Base | B6: =Calculos!$B$157 -> -91764381 | C6: =Calculos!$B$158 -> #N/A | D6: =Calculos!$B$156 -> 38467030 | E6: =Calculos!$B$161 -> 1.2549356e+08 | F6: =Calculos!$B$159 -> #N/A | G6: =Calculos!$B$162 -> 2169.8611
A7: Optimista | B7: =Calculos!$B$212 -> -44126530 | C7: =Calculos!$B$213 -> #N/A | D7: =Calculos!$B$211 -> 33656647 | E7: =Calculos!$B$216 -> 54739533 | F7: =Calculos!$B$214 -> #N/A | G7: =Calculos!$B$217 -> 1470.6379

Sheet Sensibilidad
A1: SENSIBILIDAD DEL VAN
A2: Filas: cambio de volumen · columnas: cambio de precio · costos y CAPEX en caso base.
A4: Volumen \ Precio | B4: =(Inputs!$C$85)-1 -> -0.28 | C4: =(1)-1 -> 0 | D4: =(Inputs!$C$86)-1 -> 0.2
A5: =(Inputs!$C$87)-1 -> 0 | B5: =Calculos!$B$267 -> -1.5044594e+08 | C5: =Calculos!$B$322 -> -91764381 | D5: =Calculos!$B$377 -> -49848980
A6: =(1)-1 -> 0 | B6: =Calculos!$B$432 -> -1.5044594e+08 | C6: =Calculos!$B$487 -> -91764381 | D6: =Calculos!$B$542 -> -49848980
A7: =(Inputs!$C$88)-1 -> 0 | B7: =Calculos!$B$597 -> -1.5044594e+08 | C7: =Calculos!$B$652 -> -91764381 | D7: =Calculos!$B$707 -> -49848980

Sheet Fuentes
A1: TRAZABILIDAD Y FUENTES
A2: Copia documental de Inputs; los cambios se realizan en Inputs.
A4: Parámetro | B4: Valor actual | C4: Unidad | D4: Confianza | E4: Fuente | F4: Nota
A5: =Inputs!$B$6 -> TMAR nominal anual | B5: =Inputs!$C$6 -> 0.2046 | C5: =Inputs!$D$6 -> % anual nominal | D5: =Inputs!$E$6 -> ESTIMADO | E5: =Inputs!$F$6 -> https://www.cmfchile.cl/portal/estadisticas/626/w4-article-111825.html | F5: =Inputs!$G$6 -> PISO OBSERVADO, no el costo de oportunidad del titular. CMF, Certificado 07/2026 (promedios de junio 2026, vigente desde el 14-07-2026): interés corriente de 20,46% anual para operaciones no reajustables en moneda nacional de 90 días o más entre 200 y 5.000 UF. La inversión inicial de $43.516.722 equivale a 1.065 UF, dentro de ese tramo. El capital propio es subordinado a esa deuda, luego la TMAR correcta es MAYOR. Reemplaza el stub de 15% de la etapa 10, que quedaba por DEBAJO del costo observado de deuda del mismo tamaño. Spread sobre la TPM (4,5%, Banco Central, https://www.bcentral.cl/areas/politica-monetaria): 15,96 puntos. NO se descompone riesgo por riesgo: no existe fuente pública que lo permita para una microempresa de alimentos en Temuco y repartir los puntos con decimales sería inventar. Límite: el interés corriente es un promedio de operaciones heterogéneas, expresado en forma lineal anual base 360 días, no una cotización para esta empresa. La decisión no es sensible a la tasa: el VAN se anula recién en 35,69% (la TIR); VAN@15% $44.017.948, VAN@20,46% $28.308.713. Gestión que lo cerraría: que el titular declare por escrito el retorno de su alternativa real de inversión.
A6: =Inputs!$B$7 -> Inflación anual | B6: =Inputs!$C$7 -> 0.03 | C6: =Inputs!$D$7 -> % anual desde año 2 | D6: =Inputs!$E$7 -> ESTIMADO | E6: =Inputs!$F$7 -> https://www.bcentral.cl/documents/33528/8413153/IPoM%2Bjunio%2B2026.pdf/93388589-0929-4ad6-b166-10981ca34946 | F6: =Inputs!$G$7 -> IPoM junio 2026 ubica expectativas a uno y dos años en torno a 3%. Se escala precio y costos simétricamente.
A7: =Inputs!$B$8 -> Capital máximo disponible | B7: =Inputs!$C$8 -> 50000000 | C7: =Inputs!$D$8 -> CLP | D7: =Inputs!$E$8 -> VERIFICADO | E7: =Inputs!$F$8 -> datos/supuestos.json#meta.restriccion_capital_clp | F7: =Inputs!$G$8 -> Restricción declarada en el enunciado.
A8: =Inputs!$B$9 -> Horizonte de evaluación | B8: =Inputs!$C$9 -> 5 | C8: =Inputs!$D$9 -> años | D8: =Inputs!$E$9 -> SUPUESTO | E8: =Inputs!$F$9 -> datos/supuestos.json#meta.horizonte_evaluacion_anios | F8: =Inputs!$G$9 -> Horizonte fijado en el statement.
A9: =Inputs!$B$10 -> Precio B2B neto base | B9: =Inputs!$C$10 -> 4200 | C9: =Inputs!$D$10 -> CLP neto/unidad en pesos base 2026 | D9: =Inputs!$E$10 -> SUPUESTO | E9: =Inputs!$F$10 -> 02-competencia/index.html | F9: =Inputs!$G$10 -> Se usa solo porque el parámetro de etapa 02 está pendiente. Está entre PF retail neto ($3.017) y foodservice publicado ($5.034); no representa disposición a pagar validada.
A10: =Inputs!$B$11 -> SOM año 1 (0 = usar referencia) | B10: =Inputs!$C$11 -> 0 | C10: =Inputs!$D$11 -> pizzas/mes | D10: =Inputs!$E$11 -> PENDIENTE | E10: =Inputs!$F$11 -> datos/supuestos.json#mercado.som_ano1_pizzas_mes | F10: =Inputs!$G$11 -> 0 = usar el volumen año 1 de referencia. La etapa 03 lo cierra en terreno.
A11: =Inputs!$B$12 -> Volumen año 1 (referencia) | B11: =Inputs!$C$12 -> 30000 | C11: =Inputs!$D$12 -> pizzas/año | D11: =Inputs!$E$12 -> SUPUESTO | E11: =Inputs!$F$12 -> 01-mercado/index.html | F11: =Inputs!$G$12 -> 2.500 unidades/mes. Sustituir por mercado.som_ano1_pizzas_mes × 12 cuando etapa 03 lo valide.
A12: =Inputs!$B$13 -> Volumen año 2 (referencia) | B12: =Inputs!$C$13 -> 42000 | C12: =Inputs!$D$13 -> pizzas/año | D12: =Inputs!$E$13 -> SUPUESTO | E12: =Inputs!$F$13 -> Etapa 10 | F12: =Inputs!$G$13 -> Rampa comercial no validada.
A13: =Inputs!$B$14 -> Volumen año 3 (referencia) | B13: =Inputs!$C$14 -> 54000 | C13: =Inputs!$D$14 -> pizzas/año | D13: =Inputs!$E$14 -> SUPUESTO | E13: =Inputs!$F$14 -> Etapa 10 | F13: =Inputs!$G$14 -> Rampa comercial no validada.
A14: =Inputs!$B$15 -> Volumen año 4 (referencia) | B14: =Inputs!$C$15 -> 66000 | C14: =Inputs!$D$15 -> pizzas/año | D14: =Inputs!$E$15 -> SUPUESTO | E14: =Inputs!$F$15 -> Etapa 10 | F14: =Inputs!$G$15 -> Rampa comercial no validada.
A15: =Inputs!$B$16 -> Volumen año 5 (referencia) | B15: =Inputs!$C$16 -> 72000 | C15: =Inputs!$D$16 -> pizzas/año | D15: =Inputs!$E$16 -> SUPUESTO | E15: =Inputs!$F$16 -> Etapa 10 | F15: =Inputs!$G$16 -> Rampa comercial no validada.
A16: =Inputs!$B$17 -> Rampa año 2 (0 = derivar) | B16: =Inputs!$C$17 -> 0 | C16: =Inputs!$D$17 -> multiplicador sobre año 1 | D16: =Inputs!$E$17 -> PENDIENTE | E16: =Inputs!$F$17 -> datos/supuestos.json#comercial.rampa_ano2_factor | F16: =Inputs!$G$17 -> 0 = derivar la forma de los volúmenes de referencia. La etapa 11 no publicó factor y no se inventa uno.
A17: =Inputs!$B$18 -> Rampa año 3 (0 = derivar) | B17: =Inputs!$C$18 -> 0 | C17: =Inputs!$D$18 -> multiplicador sobre año 1 | D17: =Inputs!$E$18 -> PENDIENTE | E17: =Inputs!$F$18 -> datos/supuestos.json#comercial.rampa_ano3_factor | F17: =Inputs!$G$18 -> 0 = derivar la forma de los volúmenes de referencia. La etapa 11 no publicó factor y no se inventa uno.
A18: =Inputs!$B$19 -> Rampa año 4 (0 = derivar) | B18: =Inputs!$C$19 -> 0 | C18: =Inputs!$D$19 -> multiplicador sobre año 1 | D18: =Inputs!$E$19 -> PENDIENTE | E18: =Inputs!$F$19 -> datos/supuestos.json#comercial.rampa_ano4_factor | F18: =Inputs!$G$19 -> 0 = derivar la forma de los volúmenes de referencia. La etapa 11 no publicó factor y no se inventa uno.
A19: =Inputs!$B$20 -> Rampa año 5 (0 = derivar) | B19: =Inputs!$C$20 -> 0 | C19: =Inputs!$D$20 -> multiplicador sobre año 1 | D19: =Inputs!$E$20 -> PENDIENTE | E19: =Inputs!$F$20 -> datos/supuestos.json#comercial.rampa_ano5_factor | F19: =Inputs!$G$20 -> 0 = derivar la forma de los volúmenes de referencia. La etapa 11 no publicó factor y no se inventa uno.
A20: =Inputs!$B$21 -> Impuesto año 1 | B20: =Inputs!$C$21 -> 0.125 | C20: =Inputs!$D$21 -> % IDPC Pro Pyme año comercial 2027 | D20: =Inputs!$E$21 -> VERIFICADO | E20: =Inputs!$F$21 -> https://www.sii.cl/normativa_legislacion/circulares/2025/circu53.pdf | F20: =Inputs!$G$21 -> Aplica si la empresa califica al régimen Pro Pyme General del art. 14 D N°3.
A21: =Inputs!$B$22 -> Impuesto año 2 | B21: =Inputs!$C$22 -> 0.125 | C21: =Inputs!$D$22 -> % IDPC Pro Pyme año comercial 2028 | D21: =Inputs!$E$22 -> VERIFICADO | E21: =Inputs!$F$22 -> https://www.sii.cl/preguntas_frecuentes/declaracion_renta/001_140_4708.htm | F21: =Inputs!$G$22 -> Año comercial 2027. La tabla de tasas IDPC del SII muestra 12,5% para los años comerciales 2025, 2026 y 2027 bajo el art. 14 D N°3 (rebaja de la Ley 21.755, art. vigésimo quinto). Corrige el 15% anterior, que adelantaba un año la escala.
A22: =Inputs!$B$23 -> Impuesto año 3 | B22: =Inputs!$C$23 -> 0.15 | C22: =Inputs!$D$23 -> % IDPC permanente | D22: =Inputs!$E$23 -> ESTIMADO | E22: =Inputs!$F$23 -> https://www.sii.cl/preguntas_frecuentes/declaracion_renta/001_140_4708.htm | F22: =Inputs!$G$23 -> Año comercial 2028. Corrige el 25% anterior, que contradecía su propia nota: ésta decía que el 25% rige desde 2029, pero se aplicaba al año 3, que es 2028.
A23: =Inputs!$B$24 -> Impuesto año 4 | B23: =Inputs!$C$24 -> 0.25 | C23: =Inputs!$D$24 -> % IDPC permanente | D23: =Inputs!$E$24 -> ESTIMADO | E23: =Inputs!$F$24 -> https://www.sii.cl/preguntas_frecuentes/declaracion_renta/001_140_4708.htm | F23: =Inputs!$G$24 -> Año comercial 2029: tasa permanente del régimen. Supone permanencia normativa.
A24: =Inputs!$B$25 -> Impuesto año 5 | B24: =Inputs!$C$25 -> 0.25 | C24: =Inputs!$D$25 -> % IDPC permanente | D24: =Inputs!$E$25 -> ESTIMADO | E24: =Inputs!$F$25 -> https://www.sii.cl/preguntas_frecuentes/declaracion_renta/001_140_4708.htm | F24: =Inputs!$G$25 -> Año comercial 2030: tasa permanente del régimen. Supone permanencia normativa.
A25: =Inputs!$B$26 -> Harina por pizza | B25: =Inputs!$C$26 -> 0.151 | C25: =Inputs!$D$26 -> kg/pizza familiar 30 cm | D25: =Inputs!$E$26 -> ESTIMADO | E25: =Inputs!$F$26 -> https://eur-lex.europa.eu/legal-content/ES/TXT/HTML/?uri=CELEX:32010R0097 | F25: =Inputs!$G$26 -> Reglamento (UE) 97/2010, pliego Pizza Napoletana ETG: harina 1.800 g : agua 1 L : sal 50-55 g : levadura 3 g, total 2.855 g, de donde la harina es el 63,0% de la masa. Bollo de 240 g (techo del rango ETG 180-250 g) x 0,630 = 151 g. Se toma el techo porque un disco precocido congelado debe resistir manipulación, apilado en caja de 12 y transporte: densidad 0,34 g/cm² sobre 300 mm, más gruesa que una napoletana. Sustituye el supuesto de 0,2 kg de etapa 10, que era 32% mayor.
A26: =Inputs!$B$27 -> Salsa por pizza | B26: =Inputs!$C$27 -> 0.08 | C26: =Inputs!$D$27 -> kg/pizza familiar 30 cm | D26: =Inputs!$E$27 -> ESTIMADO | E26: =Inputs!$F$27 -> https://eur-lex.europa.eu/legal-content/ES/TXT/HTML/?uri=CELEX:32010R0097 | F26: =Inputs!$G$27 -> Pliego ETG para la Margherita: 'entre 60 y 80 g de tomates pelados triturados'. Se toma el techo. CUADRA CON EL PRECIO DE 06: la salsa es tomate pelado triturado en crudo con sal y aceite, sin reducción, así que 1 kg de insumo ≈ 1 kg de salsa y el gramaje se valoriza directamente con datos/parametros-06-insumos.json#insumos.salsa_tomate_clp_kg. Si se decide cocer y reducir la salsa, este número sube por pérdida de agua.
A27: =Inputs!$B$28 -> Mozzarella por pizza | B27: =Inputs!$C$28 -> 0.1 | C27: =Inputs!$D$28 -> kg/pizza familiar 30 cm | D27: =Inputs!$E$28 -> ESTIMADO | E27: =Inputs!$F$28 -> https://eur-lex.europa.eu/legal-content/ES/TXT/HTML/?uri=CELEX:32010R0097 | F27: =Inputs!$G$28 -> LÍNEA MÁS SENSIBLE DEL MODELO. Dos anclas independientes convergen: (a) pliego ETG Margherita, 'entre 80 y 100 g' de mozzarella; (b) ficha técnica comercial de minipizza congelada que declara mozzarella 20,5% en masa, que sobre 426 g da 89 g. Se toma 100 g, techo del rango ETG, porque sobre 300 mm da mayor densidad superficial que 100 g sobre los 350 mm que el ETG permite, y porque la carga de queso visible es el atributo que el canal compra. Sustituye el supuesto de 0,12 kg de etapa 10: a $8.403,36/kg el costo de queso baja de $1.008 a $840 por unidad. NINGUNA de las dos anclas es chilena ni foodservice, y el rendimiento al fundir no está probado: cerrar con panel de degustación en etapa 03 y con el piloto.
A28: =Inputs!$B$29 -> Otros ingredientes por pizza | B28: =Inputs!$C$29 -> 550 | C28: =Inputs!$D$29 -> CLP neto/pizza | D28: =Inputs!$E$29 -> SUPUESTO | E28: =Inputs!$F$29 -> Etapa 10 | F28: =Inputs!$G$29 -> Aceite, levadura, sal, especias y topping; pendiente de receta y cotización.
A29: =Inputs!$B$30 -> Envase por pizza | B29: =Inputs!$C$30 -> 300 | C29: =Inputs!$D$30 -> CLP neto/pizza | D29: =Inputs!$E$30 -> SUPUESTO | E29: =Inputs!$F$30 -> 06-insumos/index.html | F29: =Inputs!$G$30 -> Fallback hasta que etapa 06 cierre film, etiqueta y caja máster.
A30: =Inputs!$B$31 -> Energía variable por pizza | B30: =Inputs!$C$31 -> 120 | C30: =Inputs!$D$31 -> CLP/pizza | D30: =Inputs!$E$31 -> SUPUESTO | E30: =Inputs!$F$31 -> https://calvac.cl/venta/abatidor-10-bandejas-2/ | F30: =Inputs!$G$31 -> Bolsa de costo para horno, abatimiento y congelación. Debe reemplazarse por balance kWh/ciclo y tarifa contratada.
A31: =Inputs!$B$32 -> Distribución variable por pizza | B31: =Inputs!$C$32 -> 220 | C31: =Inputs!$D$32 -> CLP/pizza | D31: =Inputs!$E$32 -> SUPUESTO | E31: =Inputs!$F$32 -> Etapa 10 | F31: =Inputs!$G$32 -> Despacho consolidado local sin vehículo propio; cotizar por ruta.
A32: =Inputs!$B$33 -> Merma de ingredientes | B32: =Inputs!$C$33 -> 0.05 | C32: =Inputs!$D$33 -> % | D32: =Inputs!$E$33 -> SUPUESTO | E32: =Inputs!$F$33 -> datos/parametros-10-financiero.json#producto.merma_pct | F32: =Inputs!$G$33 -> PUNTOS PORCENTUALES: 5 = 5%. modelo.js lo divide por 100. NO EXISTE fuente pública chilena de merma de proceso para esta línea; se mantiene el marcador heredado de etapa 10 en vez de inventar precisión. Componentes esperados: recorte de masa al formar, residuo de dosificado de salsa y queso, y producto no conforme de arranque (el dominante). Solo lo cierra un piloto de 3 lotes con pesaje de entrada y salida.
A33: =Inputs!$B$34 -> Precio harina/kg | B33: =Inputs!$C$34 -> 840 | C33: =Inputs!$D$34 -> CLP neto/kg | D33: =Inputs!$E$34 -> VERIFICADO | E33: =Inputs!$F$34 -> https://metafood.cl/REV10100_Harina_Pizza | F33: =Inputs!$G$34 -> Saco de harina para pizza 25 kg publicado a $21.000 + IVA. Falta confirmar flete y disponibilidad en Temuco.
A34: =Inputs!$B$35 -> Precio tomate/kg | B34: =Inputs!$C$35 -> 2383.8 | C34: =Inputs!$D$35 -> CLP neto/kg | D34: =Inputs!$E$35 -> VERIFICADO | E34: =Inputs!$F$35 -> https://metafood.cl/REV10130_Tomate_Pelado_Lata_Bolsa | F34: =Inputs!$G$35 -> Tomate pelado bolsa 5 kg a $11.919 + IVA. Es insumo para formular salsa, no salsa terminada; falta flete a Temuco.
A35: =Inputs!$B$36 -> Precio mozzarella/kg | B35: =Inputs!$C$36 -> 8403.36 | C35: =Inputs!$D$36 -> CLP neto/kg | D35: =Inputs!$E$36 -> ESTIMADO | E35: =Inputs!$F$36 -> https://www.mercadolibre.cl/queso-mozzarella-barra-35-kg-aprox-molfino-argentino/up/MLCU67695246 | F35: =Inputs!$G$36 -> Publicación de vendedor de Temuco a $10.000/kg IVA incluido, con factura y reparto refrigerado; normalizado /1,19. No es cotización por volumen ni demuestra suministro estable.
A36: =Inputs!$B$37 -> Superficie | B36: =Inputs!$C$37 -> 120 | C36: =Inputs!$D$37 -> m² | D36: =Inputs!$E$37 -> SUPUESTO | E36: =Inputs!$F$37 -> 07-local-habilitacion/index.html | F36: =Inputs!$G$37 -> Fallback hasta layout de etapa 04.
A37: =Inputs!$B$38 -> Arriendo por m²/mes | B37: =Inputs!$C$38 -> 6331 | C37: =Inputs!$D$38 -> CLP/m²/mes | D37: =Inputs!$E$38 -> ESTIMADO | E37: =Inputs!$F$38 -> https://chilepropiedades.cl/ver-publicacion/arriendo-mensual/temuco/bodega/bodega-nueva-de-1-500-m2-acceso-norte-de-tco-162267/117714745 ; https://propiedades.bmi.cl/6057 | F37: =Inputs!$G$38 -> Punto medio entre avisos industriales de 0,15 y 0,16 UF/m²/mes, convertido con UF base $40.844,79. Son bodegas mayores; no prueba precio de un local alimentario pequeño.
A38: =Inputs!$B$39 -> Arriendo mensual directo (0 = calcular) | B38: =Inputs!$C$39 -> 0 | C38: =Inputs!$D$39 -> CLP/mes | D38: =Inputs!$E$39 -> PENDIENTE | E38: =Inputs!$F$39 -> 0 | F38: =Inputs!$G$39 -> Depende del metraje, gastos comunes y de encontrar un inmueble compatible con uso de suelo y habilitación sanitaria.
A39: =Inputs!$B$40 -> Nómina bruta mensual | B39: =Inputs!$C$40 -> 1100000 | C39: =Inputs!$D$40 -> CLP/mes, suma de sueldos brutos imponibles de trabajadores dependientes | D39: =Inputs!$E$40 -> ESTIMADO | E39: =Inputs!$F$40 -> https://www.ine.gob.cl/estadisticas-por-tema/mercado-laboral/encuesta-suplementaria-de-ingresos ; https://fcje.ufro.cl/noticias/la-araucania-frente-a-la-esi-2025-desafios-para-un-desarrollo-con-mejores-ingresos/ ; datos/supuestos.json#macro.ingreso_minimo_mensual_clp | F39: =Inputs!$G$40 -> RÉGIMEN, desde el mes 4. Dotación dependiente: 1 operario de producción a jornada completa 42 h ($700.000 bruto) + 1 operario polivalente a jornada parcial 24 h ($400.000 bruto). Cada bruto incluye sueldo base + gratificación art. 50 del Código del Trabajo (25% con tope de 4,75 IMM anuales = $219.115/mes); no volver a sumarla. ESTE VALOR NO INCLUYE EL RETIRO DE LA TITULAR: el modelo debe sumar rrhh.retiro_titular_mensual_clp SIN aplicarle macro.factor_costo_empresa. Si se prefiere una sola línea ya calculada, usar rrhh.costo_personal_mensual_regimen_clp. Los sueldos son ESTIMADOS: no existe serie pública de remuneración por cargo y comuna; se anclaron en el ingreso mínimo legal y en la ESI 2025 convertida de líquido a bruto.
A40: =Inputs!$B$41 -> Factor costo empresa | B40: =Inputs!$C$41 -> 1.0853 | C40: =Inputs!$D$41 -> multiplicador sobre sueldo bruto imponible de trabajador dependiente | D40: =Inputs!$E$41 -> VERIFICADO | E40: =Inputs!$F$41 -> https://www.spensiones.cl/portal/institucional/594/w3-propertyvalue-10906.html ; https://www.chileatiende.gob.cl/fichas/130987-aportes-del-empleador-al-sistema-de-pensiones ; https://www.isl.gob.cl/cotizaciones/ ; https://www.isl.gob.cl/wp-content/uploads/2024/08/Clasificador-Actividades-Economicas-2021.pdf ; https://www.previred.com/indicadores-previsionales/ | F40: =Inputs!$G$41 -> MULTIPLICADOR DESNUDO, se usa tal cual (1,0853 = 8,53% sobre el bruto). Suma: 3,50% cotización de cargo del empleador Ley 21.735 vigente 08-2026 a 07-2027 (incluye el SIS, que desde agosto 2026 se financia dentro del Seguro Social Previsional y ya no se cotiza aparte) + 2,40% seguro de cesantía AFC contrato indefinido + 0,93% tasa base Ley 16.744 (0,90% básica + 0,03% SANNA) + 1,70% cotización adicional DS 110 para CIIU 107500 'elaboración de comidas y platos preparados envasados, rotulados y con información nutricional'. CONDICIONES: contrato indefinido (a plazo fijo el AFC sube a 3,00% y el factor a 1,0913); empresa nueva sin evaluación de siniestralidad (DS 67 puede subir o bajar la adicional desde el tercer año); rentas muy por debajo del tope imponible de 90 UF, por lo que todas las tasas aplican íntegras. NO APLICA al retiro de la titular por sueldo empresarial (ver rrhh.retiro_titular_mensual_clp). NO incluye provisiones de feriado ni de indemnización: para eso ver rrhh.factor_costo_empresa_con_provisiones. ADVERTENCIA: el stub 1,22 de la etapa 10 sobrestima el desembolso mensual exigible en ~14 puntos porcentuales.
A41: =Inputs!$B$42 -> Servicios fijos mensuales | B41: =Inputs!$C$42 -> 180000 | C41: =Inputs!$D$42 -> CLP/mes | D41: =Inputs!$E$42 -> SUPUESTO | E41: =Inputs!$F$42 -> Etapa 10 | F41: =Inputs!$G$42 -> Cargo fijo de electricidad, agua, gas, internet y residuos, separado del consumo variable.
A42: =Inputs!$B$43 -> Mantenimiento mensual | B42: =Inputs!$C$43 -> 100000 | C42: =Inputs!$D$43 -> CLP/mes | D42: =Inputs!$E$43 -> SUPUESTO | E42: =Inputs!$F$43 -> Etapa 10 | F42: =Inputs!$G$43 -> Reserva preventiva; validar con equipos elegidos.
A43: =Inputs!$B$44 -> Administración mensual | B43: =Inputs!$C$44 -> 160000 | C43: =Inputs!$D$44 -> CLP/mes | D43: =Inputs!$E$44 -> SUPUESTO | E43: =Inputs!$F$44 -> Etapa 10 | F43: =Inputs!$G$44 -> Contabilidad, software básico, telefonía y gastos bancarios.
A44: =Inputs!$B$45 -> Ventas mensuales | B44: =Inputs!$C$45 -> 180000 | C44: =Inputs!$D$45 -> CLP/mes | D44: =Inputs!$E$45 -> SUPUESTO | E44: =Inputs!$F$45 -> Etapa 10 | F44: =Inputs!$G$45 -> Muestras, visitas y material comercial.
A45: =Inputs!$B$46 -> Seguros mensuales | B45: =Inputs!$C$46 -> 60000 | C45: =Inputs!$D$46 -> CLP/mes | D45: =Inputs!$E$46 -> SUPUESTO | E45: =Inputs!$F$46 -> Etapa 10 | F45: =Inputs!$G$46 -> Cotización pendiente.
A46: =Inputs!$B$47 -> Días cuentas por cobrar | B46: =Inputs!$C$47 -> 30 | C46: =Inputs!$D$47 -> días | D46: =Inputs!$E$47 -> SUPUESTO | E46: =Inputs!$F$47 -> datos/parametros-02-competencia.json#precios.plazo_cobro_dias | F46: =Inputs!$G$47 -> Fallback consistente con el modelo de negocio; debe sustituirse por práctica validada.
A47: =Inputs!$B$48 -> Días inventario | B47: =Inputs!$C$48 -> 15 | C47: =Inputs!$D$48 -> días de costo variable | D47: =Inputs!$E$48 -> SUPUESTO | E47: =Inputs!$F$48 -> Etapa 10 | F47: =Inputs!$G$48 -> Materia prima más producto terminado.
A48: =Inputs!$B$49 -> Días cuentas por pagar | B48: =Inputs!$C$49 -> 0 | C48: =Inputs!$D$49 -> días de costo variable | D48: =Inputs!$E$49 -> SUPUESTO | E48: =Inputs!$F$49 -> Etapa 10 | F48: =Inputs!$G$49 -> Caso conservador sin crédito de proveedores.
A49: =Inputs!$B$50 -> Costo de personal mensual (0 = calcular) | B49: =Inputs!$C$50 -> 2393830 | C49: =Inputs!$D$50 -> CLP/mes | D49: =Inputs!$E$50 -> ESTIMADO | E49: =Inputs!$F$50 -> 09-rrhh/index.html | F49: =Inputs!$G$50 -> DERIVADO, no es un dato independiente: 1.100.000 × 1,0853 + 1.200.000. Existe sólo para evitar que el retiro de la titular se pierda si el modelo cablea una sola línea de personal. Si se usa esta clave, NO multiplicar de nuevo por macro.factor_costo_empresa. Compara contra el stub de E10 (2.200.000 × 1,22 = 2.684.000): $290.170/mes menos, $3.482.040 al año.
A50: =Inputs!$B$51 -> Capacidad instalada (un/día, 0 = sin tope) | B50: =Inputs!$C$51 -> 60 | C50: =Inputs!$D$51 -> unidades/día (SKU familiar 30 cm) | D50: =Inputs!$E$51 -> ESTIMADO | E50: =Inputs!$F$51 -> https://calvac.cl/venta/abatidor-10-bandejas-2/ + https://www.supermaq.cl/abatidor/abatidor_congelador_5_bandejas.pdf | F50: =Inputs!$G$51 -> Cuello de botella GEOMÉTRICO, no térmico. Bandeja de 610x410 mm: floor(610/300) x floor(410/300) = 2 discos de 300 mm por bandeja; 10 bandejas = 20 pizzas/ciclo = 8,5 kg, el 28% de los 30 kg declarados. Con ciclo de 240 min: 2 ciclos en jornada de 8,4 h más 1 ciclo desatendido que el equipo almacena solo al terminar = 3 ciclos/día x 20 = 60. Techo absoluto con operación 24 h: 6 ciclos = 120/día. El horno pizzero de 2 cámaras 40x40 (~24 pizzas/h) y la amasadora de 20 kg (83 bollos de 240 g) NO son limitantes. En SKU individual de 200 mm: 3x2 = 6 por bandeja = 60/ciclo = 180/día.
A51: =Inputs!$B$52 -> Días de operación al mes | B51: =Inputs!$C$52 -> 22 | C51: =Inputs!$D$52 -> días/mes | D51: =Inputs!$E$52 -> ESTIMADO | E51: =Inputs!$F$52 -> https://www.dt.gob.cl/legislacion/1624/w3-article-129189.html | F51: =Inputs!$G$52 -> CLAVE NUEVA. Jornada de 42 horas semanales desde el 26-04-2026 (Ley 21.561, confirmado por ORD. 253/21 de la Dirección del Trabajo). Turno único de 5 días x 8,4 h; 52/12 = 4,333 semanas/mes x 5 = 21,7, redondeado a 22. Es decisión de diseño operacional, no un dato: un segundo turno o sábados la cambian. Capacidad mensual = 60 x 22 = 1.320 pizzas familiares.
A52: =Inputs!$B$53 -> Abatidor | B52: =Inputs!$C$53 -> 2779980 | C52: =Inputs!$D$53 -> CLP neto | D52: =Inputs!$E$53 -> VERIFICADO | E52: =Inputs!$F$53 -> https://calvac.cl/venta/abatidor-10-bandejas-2/ | F52: =Inputs!$G$53 -> 10 bandejas, congelación declarada hasta 30 kg; precio publicado + IVA.
A53: =Inputs!$B$54 -> Amasadora | B53: =Inputs!$C$54 -> 747815 | C53: =Inputs!$D$54 -> CLP neto | D53: =Inputs!$E$54 -> VERIFICADO | E53: =Inputs!$F$54 -> https://www.supermaq.cl/amasadoras/amasadora_20_kilos/ | F53: =Inputs!$G$54 -> Amasadora espiral 20 kg, precio internet + IVA.
A54: =Inputs!$B$55 -> Horno | B54: =Inputs!$C$55 -> 400000 | C54: =Inputs!$D$55 -> CLP neto | D54: =Inputs!$E$55 -> VERIFICADO | E54: =Inputs!$F$55 -> https://www.supermaq.cl/hornos_pizza/horno_electrico_pizzero_2_camara_40x40.pdf | F54: =Inputs!$G$55 -> Horno pizzero eléctrico dos cámaras, oferta + IVA; verificar capacidad real de precocción.
A55: =Inputs!$B$56 -> Selladora al vacío | B55: =Inputs!$C$56 -> 570000 | C55: =Inputs!$D$56 -> CLP neto | D55: =Inputs!$E$56 -> ESTIMADO | E55: =Inputs!$F$56 -> https://www.supermaq.cl/pdf/camara.cl_selladora_al_vacio_300_mm_dz300.pdf | F55: =Inputs!$G$56 -> Ficha con precio publicado; confirmar vigencia y compatibilidad con formato.
A56: =Inputs!$B$57 -> Mesón refrigerado | B56: =Inputs!$C$57 -> 620000 | C56: =Inputs!$D$57 -> CLP neto | D56: =Inputs!$E$57 -> ESTIMADO | E56: =Inputs!$F$57 -> https://www.industriaminera.cl/producto/biggi-chile-sa-mesones-refrigerados/ | F56: =Inputs!$G$57 -> Mesón 120 cm publicado + IVA; confirmar vigencia.
A57: =Inputs!$B$58 -> Congeladores | B57: =Inputs!$C$58 -> 700000 | C57: =Inputs!$D$58 -> CLP neto | D57: =Inputs!$E$58 -> SUPUESTO | E57: =Inputs!$F$58 -> https://gastronomicareal.cl/refrigeracion/congeladoras | F57: =Inputs!$G$58 -> Bolsa para almacenamiento −18 °C; requiere selección por capacidad y redundancia.
A58: =Inputs!$B$59 -> Acero, lavado y extracción | B58: =Inputs!$C$59 -> 1800000 | C58: =Inputs!$D$59 -> CLP neto | D58: =Inputs!$E$59 -> SUPUESTO | E58: =Inputs!$F$59 -> Etapa 10 | F58: =Inputs!$G$59 -> Mesones, lavaderos, campana y elementos fijos; cotización pendiente.
A59: =Inputs!$B$60 -> Racks, bandejas e instrumentos | B59: =Inputs!$C$60 -> 1200000 | C59: =Inputs!$D$60 -> CLP neto | D59: =Inputs!$E$60 -> SUPUESTO | E59: =Inputs!$F$60 -> Etapa 10 | F59: =Inputs!$G$60 -> Carros, bandejas, balanzas, sondas y utensilios.
A60: =Inputs!$B$61 -> Envolvente de equipos etapa 05 (0 = sumar líneas) | B60: =Inputs!$C$61 -> 10120237 | C60: =Inputs!$D$61 -> CLP neto | D60: =Inputs!$E$61 -> ESTIMADO | E60: =Inputs!$F$61 -> https://calvac.cl/venta/abatidor-de-temperatura-10-bandejas-290-litros/ ; https://www.supermaq.cl/amasadoras/amasadora_20_kilos/ ; https://www.supermaq.cl/sobadoras/laminadora_de_masa_40_cm_ventus./ ; https://www.industriaminera.cl/producto/biggi-chile-sa-mesones-refrigerados/ ; https://lacasita.cl/producto/congelador-industrial-2-puertas-500-litros-maigas/ ; https://lacasita.cl/producto/campana-mural-acero-inoxidable-200x100-maigas/ ; https://gastromaq.cl/producto/carro-bandejero-15-niveles-acero-inoxidable-bandejas-60x40-cm-mod-1-gastromaq/ | F60: =Inputs!$G$61 -> Suma de precios de publicación netos, NO de cotizaciones. Canasta: abatidor 10 bandejas 290 L EN STOCK $3.898.990 + amasadora 20 kg $747.815 + horno pizzero 2 cámaras 40x40 $400.000 + laminadora 40 cm $231.000 + mesón refrigerado 120 cm $620.000 + dos congeladores 500 L $2.596.700 + campana 200x100 $546.250 + mesones 240x60 y 140x60 $352.140 + dos carros bandejeros $403.362 + lavafondo doble $219.990 + lavamanos $103.990. EXCLUYE lo mismo que el escenario austero (envasado, bandejas, balanza, sonda, registrador) más ductos de campana, empalme y obra civil, que son de E7. Reemplaza a las ocho líneas hardcodeadas de datos/parametros-10-financiero.json#inversion, que suman $8.817.795 y contienen un abatidor sin stock, un horno de cámara 40x40 cm y una selladora de vacío incompatible con el producto.
A61: =Inputs!$B$62 -> Flete e instalación | B61: =Inputs!$C$62 -> 0.15 | C61: =Inputs!$D$62 -> % sobre equipos | D61: =Inputs!$E$62 -> SUPUESTO | E61: =Inputs!$F$62 -> Etapa 10 | F61: =Inputs!$G$62 -> Flete Santiago–Temuco, conexión y puesta en marcha.
A62: =Inputs!$B$63 -> Habilitación sanitaria | B62: =Inputs!$C$63 -> 12000000 | C62: =Inputs!$D$63 -> CLP neto | D62: =Inputs!$E$63 -> SUPUESTO | E62: =Inputs!$F$63 -> 07-local-habilitacion/index.html | F62: =Inputs!$G$63 -> Riesgo principal; reemplazar por presupuesto desglosado de un local real.
A63: =Inputs!$B$64 -> Trámites, análisis y rotulado | B63: =Inputs!$C$64 -> 1000000 | C63: =Inputs!$D$64 -> CLP neto | D63: =Inputs!$E$64 -> SUPUESTO | E63: =Inputs!$F$64 -> 08-legal-normativo/index.html | F63: =Inputs!$G$64 -> Aranceles, laboratorio y artes; cotización pendiente.
A64: =Inputs!$B$65 -> Preoperación | B64: =Inputs!$C$65 -> 1500000 | C64: =Inputs!$D$65 -> CLP neto | D64: =Inputs!$E$65 -> SUPUESTO | E64: =Inputs!$F$65 -> Etapa 10 | F64: =Inputs!$G$65 -> Pruebas, capacitación, muestras y apertura.
A65: =Inputs!$B$66 -> Contingencia | B65: =Inputs!$C$66 -> 0.15 | C65: =Inputs!$D$66 -> % sobre equipos, instalación y habilitación | D65: =Inputs!$E$66 -> SUPUESTO | E65: =Inputs!$F$66 -> https://services.austintexas.gov/edims/document.cfm?id=280770 | F65: =Inputs!$G$66 -> SE MANTIENE EN 15% Y SE DECLARA POR QUÉ. No se encontró estándar chileno citable de contingencia por clase de estimación, y AACE 18R-97 es explícita en que la contingencia se determina por análisis de riesgo del proyecto y nunca se predetermina; subirla a un número redondo sería relleno. Datos duros: con 15% la reserva es de $3.321.070, prácticamente idéntica a la holgura de $3.317.555 contra el límite de $50.000.000 — es decir, consumir la contingencia equivale a agotar la holgura. Valor crítico: 29,98%; por sobre ese punto el fondeo máximo supera $50.000.000. Gestión: presupuesto desglosado de arquitecto o constructor sobre un local candidato visitado (etapa 07).
A66: =Inputs!$B$67 -> Garantía de arriendo | B66: =Inputs!$C$67 -> 2 | C66: =Inputs!$D$67 -> meses | D66: =Inputs!$E$67 -> SUPUESTO | E66: =Inputs!$F$67 -> Etapa 10 | F66: =Inputs!$G$67 -> Activo recuperable al final si no hay daños.
A67: =Inputs!$B$68 -> Vida depreciable | B67: =Inputs!$C$68 -> 10 | C67: =Inputs!$D$68 -> años lineales | D67: =Inputs!$E$68 -> ESTIMADO | E67: =Inputs!$F$68 -> https://www.sii.cl/valores_y_fechas/tabla_vida_util_activo_inmovilizado.html | F67: =Inputs!$G$68 -> Promedio ponderado por monto de las vidas útiles NORMALES que publica el SII (Resolución Exenta 43 de 2002), aplicadas al envolvente base: equipos de aire y cámaras de refrigeración 10 años (abatidor $3.898.990); refrigeradores y conservadoras 9 años (congeladores $2.596.700, mesón refrigerado $620.000); cocinas 9 años (horno $400.000); maquinaria y equipos en general 15 años (amasadora $747.815, laminadora $231.000); instalaciones en general 10 años (campana $546.250, lavado $323.980); muebles y enseres 7 años (mesones $352.140, carros $403.362). Resultado 9,90 años, redondeado a 10. ADVERTENCIA PARA E10: esta es vida útil ECONÓMICA, no el calendario tributario. La etapa 10 ya supone régimen Pro Pyme 14 D N°3 al aplicar 12,5% el año 1; bajo ese régimen la depreciación del activo inmovilizado es INSTANTÁNEA E ÍNTEGRA en el ejercicio de adquisición (Circular SII 62/2020, https://www.sii.cl/normativa_legislacion/circulares/2020/circu62.pdf). El valor 5 que hoy usa E10 no es ninguna de las dos cosas: es la vida ACELERADA de maquinaria general, que no aplica al mix ni al régimen supuesto.
A68: =Inputs!$B$69 -> Valor residual | B68: =Inputs!$C$69 -> 0.1 | C68: =Inputs!$D$69 -> % del CAPEX depreciable | D68: =Inputs!$E$69 -> SUPUESTO | E68: =Inputs!$F$69 -> Etapa 10 | F68: =Inputs!$G$69 -> Valor de realización al año 5 antes de impuesto.
A69: =Inputs!$B$70 -> Pesimista: precio | B69: =Inputs!$C$70 -> 0.72 | C69: =Inputs!$D$70 -> multiplicador sobre el precio base | D69: =Inputs!$E$70 -> ESTIMADO | E69: =Inputs!$F$70 -> 02-competencia/index.html | F69: =Inputs!$G$70 -> Ancla: PF Listo familiar en promoción, $3.017 netos, precio retail regional observado en Temuco. 3.017 ÷ 4.200 = 0,718. Es un escenario definido, no un pronóstico. Consecuencia: la contribución unitaria cae de $1.547 a $364 contra un costo fijo anual de $50.969.179; VAN −$147.746.510. Recalcular si cambia precios.precio_venta_b2b_familiar_clp.
A70: =Inputs!$B$71 -> Pesimista: volumen | B70: =Inputs!$C$71 -> 1 | C70: =Inputs!$D$71 -> multiplicador | D70: =Inputs!$E$71 -> PENDIENTE | E70: =Inputs!$F$71 -> datos/supuestos.json#escenarios.volumen_pesimista_factor | F70: =Inputs!$G$71 -> SIN ANCLA — la etapa 12 no publicó banda para esta variable. Entra neutro (1,00) para no fabricar un escenario. Fórmula publicada: factor = mercado.som_ano1_pizzas_mes ÷ 2.500. No se inventa un 0,80. Referencias del modelo: a 2.254 pizzas/mes el fondeo máximo alcanza $50.000.000; a 1.972 pizzas/mes el VAN se anula; el equilibrio está en 2.666 pizzas/mes, por sobre el volumen base de 2.500.
A71: =Inputs!$B$72 -> Pesimista: costo variable | B71: =Inputs!$C$72 -> 1 | C71: =Inputs!$D$72 -> multiplicador | D71: =Inputs!$E$72 -> PENDIENTE | E71: =Inputs!$F$72 -> datos/supuestos.json#escenarios.costo_variable_pesimista_factor | F71: =Inputs!$G$72 -> SIN ANCLA — la etapa 12 no publicó banda para esta variable. Entra neutro (1,00) para no fabricar un escenario. Sin cotización industrial de mozzarella no hay ancla. Referencias del modelo sobre un costo variable base de $2.653/pizza: +3,89% lleva el fondeo máximo a $50.000.000; +11,68% anula el VAN.
A72: =Inputs!$B$73 -> Pesimista: costo fijo | B72: =Inputs!$C$73 -> 1 | C72: =Inputs!$D$73 -> multiplicador | D72: =Inputs!$E$73 -> PENDIENTE | E72: =Inputs!$F$73 -> datos/supuestos.json#escenarios.costo_fijo_pesimista_factor | F72: =Inputs!$G$73 -> SIN ANCLA — la etapa 12 no publicó banda para esta variable. Entra neutro (1,00) para no fabricar un escenario. Sin dotación de la etapa 09 ni canon real de la etapa 07 no hay ancla. Referencias del modelo sobre un costo fijo base de $4.123.720/mes: +6,51% lleva el fondeo máximo a $50.000.000; +31,35% anula el VAN.
A73: =Inputs!$B$74 -> Pesimista: CAPEX | B73: =Inputs!$C$74 -> 1.3 | C73: =Inputs!$D$74 -> multiplicador sobre equipos y habilitación | D73: =Inputs!$E$74 -> ESTIMADO | E73: =Inputs!$F$74 -> AACE International 18R-97 (rev. 01-03-2016), Tabla 1 — https://services.austintexas.gov/edims/document.cfm?id=280770 | F73: =Inputs!$G$74 -> El CAPEX vigente es una estimación Clase 5 (definición 0–2%, método de juicio y analogía, precios de publicación web y ninguna cotización de habilitación). AACE asigna a la Clase 5 un rango alto de +30% a +100% DESPUÉS de aplicar contingencia. Se toma el extremo MENOS alarmante de esa banda, +30%. Consecuencia: fondeo máximo $54.320.905, es decir NO CABE en $50.000.000. El valor de quiebre es apenas +13,03%, muy por dentro del rango propio de la clase de estimación.
A74: =Inputs!$B$75 -> Base: precio | B74: =Inputs!$C$75 -> 1 | C74: =Inputs!$D$75 -> multiplicador | D74: =Inputs!$E$75 -> VERIFICADO | E74: =Inputs!$F$75 -> datos/parametros-10-financiero.json#modelo.precio_b2b_familiar_base_clp | F74: =Inputs!$G$75 -> Identidad. El nivel base sigue siendo SUPUESTO; lo verificado es el multiplicador.
A75: =Inputs!$B$76 -> Base: volumen | B75: =Inputs!$C$76 -> 1 | C75: =Inputs!$D$76 -> multiplicador | D75: =Inputs!$E$76 -> VERIFICADO | E75: =Inputs!$F$76 -> datos/parametros-10-financiero.json#modelo.volumen_ano1_unidades | F75: =Inputs!$G$76 -> Identidad.
A76: =Inputs!$B$77 -> Base: costo variable | B76: =Inputs!$C$77 -> 1 | C76: =Inputs!$D$77 -> multiplicador | D76: =Inputs!$E$77 -> VERIFICADO | E76: =Inputs!$F$77 -> 10-financiero/modelo.js | F76: =Inputs!$G$77 -> Identidad.
A77: =Inputs!$B$78 -> Base: costo fijo | B77: =Inputs!$C$78 -> 1 | C77: =Inputs!$D$78 -> multiplicador | D77: =Inputs!$E$78 -> VERIFICADO | E77: =Inputs!$F$78 -> 10-financiero/modelo.js | F77: =Inputs!$G$78 -> Identidad.
A78: =Inputs!$B$79 -> Base: CAPEX | B78: =Inputs!$C$79 -> 1 | C78: =Inputs!$D$79 -> multiplicador | D78: =Inputs!$E$79 -> VERIFICADO | E78: =Inputs!$F$79 -> 10-financiero/modelo.js | F78: =Inputs!$G$79 -> Identidad.
A79: =Inputs!$B$80 -> Optimista: precio | B79: =Inputs!$C$80 -> 1.2 | C79: =Inputs!$D$80 -> multiplicador sobre el precio base | D79: =Inputs!$E$80 -> ESTIMADO | E79: =Inputs!$F$80 -> 02-competencia/index.html | F79: =Inputs!$G$80 -> Ancla: pizza familiar foodservice publicada a $5.034 netos (Meta Food, Santiago). 5.034 ÷ 4.200 = 1,199. Límite: ese precio no incluye flete a Temuco ni prueba disposición a pagar del canal local.
A80: =Inputs!$B$81 -> Optimista: volumen | B80: =Inputs!$C$81 -> 1 | C80: =Inputs!$D$81 -> multiplicador | D80: =Inputs!$E$81 -> PENDIENTE | E80: =Inputs!$F$81 -> datos/supuestos.json#escenarios.volumen_optimista_factor | F80: =Inputs!$G$81 -> SIN ANCLA — la etapa 12 no publicó banda para esta variable. Entra neutro (1,00) para no fabricar un escenario. Misma fórmula. Debe además quedar acotado por produccion.capacidad_instalada_pizzas_dia; hoy esa restricción no muerde porque la etapa 04 no la publicó.
A81: =Inputs!$B$82 -> Optimista: costo variable | B81: =Inputs!$C$82 -> 1 | C81: =Inputs!$D$82 -> multiplicador | D81: =Inputs!$E$82 -> PENDIENTE | E81: =Inputs!$F$82 -> datos/supuestos.json#escenarios.costo_variable_optimista_factor | F81: =Inputs!$G$82 -> SIN ANCLA — la etapa 12 no publicó banda para esta variable. Entra neutro (1,00) para no fabricar un escenario. Debe salir del descuento por escalón de volumen que entregue la etapa 06, no de un supuesto.
A82: =Inputs!$B$83 -> Optimista: costo fijo | B82: =Inputs!$C$83 -> 1 | C82: =Inputs!$D$83 -> multiplicador | D82: =Inputs!$E$83 -> PENDIENTE | E82: =Inputs!$F$83 -> datos/supuestos.json#escenarios.costo_fijo_optimista_factor | F82: =Inputs!$G$83 -> SIN ANCLA — la etapa 12 no publicó banda para esta variable. Entra neutro (1,00) para no fabricar un escenario. No se propone un factor menor a 1: el costo fijo del caso base ya asume una dotación mínima sin verificar.
A83: =Inputs!$B$84 -> Optimista: CAPEX | B83: =Inputs!$C$84 -> 0.8 | C83: =Inputs!$D$84 -> multiplicador sobre equipos y habilitación | D83: =Inputs!$E$84 -> ESTIMADO | E83: =Inputs!$F$84 -> AACE International 18R-97 (rev. 01-03-2016), Tabla 1 — https://services.austintexas.gov/edims/document.cfm?id=280770 | F83: =Inputs!$G$84 -> Extremo estrecho de la banda baja de Clase 5 (−20% a −50%). Consecuencia: CAPEX $22.869.227 y fondeo máximo $41.590.138. Simetría falsa: la banda de AACE es asimétrica hacia arriba y así debe leerse.
A84: =Inputs!$B$85 -> Sensibilidad: precio bajo | B84: =Inputs!$C$85 -> 0.72 | C84: =Inputs!$D$85 -> multiplicador sobre el precio base | D84: =Inputs!$E$85 -> ESTIMADO | E84: =Inputs!$F$85 -> 02-competencia/index.html | F84: =Inputs!$G$85 -> Ancla: PF Listo familiar en promoción, $3.017 netos, precio retail regional observado en Temuco. 3.017 ÷ 4.200 = 0,718. Es un escenario definido, no un pronóstico. Consecuencia: la contribución unitaria cae de $1.547 a $364 contra un costo fijo anual de $50.969.179; VAN −$147.746.510. Recalcular si cambia precios.precio_venta_b2b_familiar_clp.
A85: =Inputs!$B$86 -> Sensibilidad: precio alto | B85: =Inputs!$C$86 -> 1.2 | C85: =Inputs!$D$86 -> multiplicador sobre el precio base | D85: =Inputs!$E$86 -> ESTIMADO | E85: =Inputs!$F$86 -> 02-competencia/index.html | F85: =Inputs!$G$86 -> Ancla: pizza familiar foodservice publicada a $5.034 netos (Meta Food, Santiago). 5.034 ÷ 4.200 = 1,199. Límite: ese precio no incluye flete a Temuco ni prueba disposición a pagar del canal local.
A86: =Inputs!$B$87 -> Sensibilidad: volumen bajo | B86: =Inputs!$C$87 -> 1 | C86: =Inputs!$D$87 -> multiplicador | D86: =Inputs!$E$87 -> PENDIENTE | E86: =Inputs!$F$87 -> datos/supuestos.json#escenarios.volumen_pesimista_factor | F86: =Inputs!$G$87 -> SIN ANCLA — eje neutro mientras la etapa 12 no publique banda.
A87: =Inputs!$B$88 -> Sensibilidad: volumen alto | B87: =Inputs!$C$88 -> 1 | C87: =Inputs!$D$88 -> multiplicador | D87: =Inputs!$E$88 -> PENDIENTE | E87: =Inputs!$F$88 -> datos/supuestos.json#escenarios.volumen_optimista_factor | F87: =Inputs!$G$88 -> SIN ANCLA — eje neutro mientras la etapa 12 no publique banda.

Sheet Calculos
A1: MOTOR DE CÁLCULO
A2: Bloques formulados para escenario activo, escenarios comparables y sensibilidad.
A4: Escenario activo
A5: Precio | B5: =IF(Inputs!$C$5="Pesimista",Inputs!$C$70,IF(Inputs!$C$5="Optimista",Inputs!$C$80,Inputs!$C$75)) -> 1
A6: Volumen | B6: =IF(Inputs!$C$5="Pesimista",Inputs!$C$71,IF(Inputs!$C$5="Optimista",Inputs!$C$81,Inputs!$C$76)) -> 1
A7: Costo variable | B7: =IF(Inputs!$C$5="Pesimista",Inputs!$C$72,IF(Inputs!$C$5="Optimista",Inputs!$C$82,Inputs!$C$77)) -> 1
A8: Costo fijo | B8: =IF(Inputs!$C$5="Pesimista",Inputs!$C$73,IF(Inputs!$C$5="Optimista",Inputs!$C$83,Inputs!$C$78)) -> 1
A9: CAPEX | B9: =IF(Inputs!$C$5="Pesimista",Inputs!$C$74,IF(Inputs!$C$5="Optimista",Inputs!$C$84,Inputs!$C$79)) -> 1
A11: Equipos | B11: =IF(Inputs!$C$61>0,Inputs!$C$61,Inputs!$C$53+Inputs!$C$54+Inputs!$C$55+Inputs!$C$56+Inputs!$C$57+Inputs!$C$58+Inputs!$C$59+Inputs!$C$60) -> 10120237
A12: Flete/instalación | B12: =Calculos!$B$11*Inputs!$C$62 -> 1518035.6
A13: Arriendo mensual | B13: =IF(Inputs!$C$39>0,Inputs!$C$39,Inputs!$C$37*Inputs!$C$38) -> 759720
A14: Costo variable unitario base | B14: =((Inputs!$C$26*Inputs!$C$34+Inputs!$C$27*Inputs!$C$35+Inputs!$C$28*Inputs!$C$36+Inputs!$C$29)*(1+Inputs!$C$33)+Inputs!$C$30+Inputs!$C$31+Inputs!$C$32) -> 2433.274
A15: Costo fijo mensual base | B15: =(Calculos!$B$13+IF(Inputs!$C$50>0,Inputs!$C$50,Inputs!$C$40*Inputs!$C$41)+Inputs!$C$42+Inputs!$C$43+Inputs!$C$44+Inputs!$C$45+Inputs!$C$46) -> 3833550
A16: CAPEX depreciable | B16: =(Calculos!$B$11+Calculos!$B$12+Inputs!$C$63)*(1+Inputs!$C$66)*Calculos!$B$9 -> 27184013
A17: CAPEX total | B17: =Calculos!$B$16+(Inputs!$C$64+Inputs!$C$65)*Calculos!$B$9 -> 29684013
A18: Depreciación anual | B18: =Calculos!$B$16/Inputs!$C$68 -> 2718401.3
A19: Valor residual bruto | B19: =Calculos!$B$16*Inputs!$C$69 -> 2718401.3
A20: Garantía arriendo | B20: =Calculos!$B$13*Inputs!$C$67 -> 1519440
A22: Concepto | B22: Año 0 | C22: Año 1 | D22: Año 2 | E22: Año 3 | F22: Año 4 | G22: Año 5
A23: Volumen | C23: =IF(AND(Inputs!$C$51>0,Inputs!$C$52>0),MIN((IF(Inputs!$C$11>0,Inputs!$C$11*12,Inputs!$C$12))*Calculos!$B$6,Inputs!$C$51*Inputs!$C$52*12),(IF(Inputs!$C$11>0,Inputs!$C$11*12,Inputs!$C$12))*Calculos!$B$6) -> 15840 | D23: =IF(AND(Inputs!$C$51>0,Inputs!$C$52>0),MIN((IF(Inputs!$C$11>0,Inputs!$C$11*12,Inputs!$C$12)*IF(Inputs!$C$17>0,Inputs!$C$17,Inputs!$C$13/Inputs!$C$12))*Calculos!$B$6,Inputs!$C$51*Inputs!$C$52*12),(IF(Inputs!$C$11>0,Inputs!$C$11*12,Inputs!$C$12)*IF(Inputs!$C$17>0,Inputs!$C$17,Inputs!$C$13/Inputs!$C$12))*Calculos!$B$6) -> 15840 | E23: =IF(AND(Inputs!$C$51>0,Inputs!$C$52>0),MIN((IF(Inputs!$C$11>0,Inputs!$C$11*12,Inputs!$C$12)*IF(Inputs!$C$18>0,Inputs!$C$18,Inputs!$C$14/Inputs!$C$12))*Calculos!$B$6,Inputs!$C$51*Inputs!$C$52*12),(IF(Inputs!$C$11>0,Inputs!$C$11*12,Inputs!$C$12)*IF(Inputs!$C$18>0,Inputs!$C$18,Inputs!$C$14/Inputs!$C$12))*Calculos!$B$6) -> 15840 | F23: =IF(AND(Inputs!$C$51>0,Inputs!$C$52>0),MIN((IF(Inputs!$C$11>0,Inputs!$C$11*12,Inputs!$C$12)*IF(Inputs!$C$19>0,Inputs!$C$19,Inputs!$C$15/Inputs!$C$12))*Calculos!$B$6,Inputs!$C$51*Inputs!$C$52*12),(IF(Inputs!$C$11>0,Inputs!$C$11*12,Inputs!$C$12)*IF(Inputs!$C$19>0,Inputs!$C$19,Inputs!$C$15/Inputs!$C$12))*Calculos!$B$6) -> 15840 | G23: =IF(AND(Inputs!$C$51>0,Inputs!$C$52>0),MIN((IF(Inputs!$C$11>0,Inputs!$C$11*12,Inputs!$C$12)*IF(Inputs!$C$20>0,Inputs!$C$20,Inputs!$C$16/Inputs!$C$12))*Calculos!$B$6,Inputs!$C$51*Inputs!$C$52*12),(IF(Inputs!$C$11>0,Inputs!$C$11*12,Inputs!$C$12)*IF(Inputs!$C$20>0,Inputs!$C$20,Inputs!$C$16/Inputs!$C$12))*Calculos!$B$6) -> 15840
A24: Escalador | C24: =(1+Inputs!$C$7)^1 -> 1.03 | D24: =(1+Inputs!$C$7)^2 -> 1.0609 | E24: =(1+Inputs!$C$7)^3 -> 1.092727 | F24: =(1+Inputs!$C$7)^4 -> 1.1255088 | G24: =(1+Inputs!$C$7)^5 -> 1.1592741
A25: Precio | C25: =Inputs!$C$10*Calculos!$B$5*Calculos!$C$24 -> 4326 | D25: =Inputs!$C$10*Calculos!$B$5*Calculos!$D$24 -> 4455.78 | E25: =Inputs!$C$10*Calculos!$B$5*Calculos!$E$24 -> 4589.4534 | F25: =Inputs!$C$10*Calculos!$B$5*Calculos!$F$24 -> 4727.137 | G25: =Inputs!$C$10*Calculos!$B$5*Calculos!$G$24 -> 4868.9511
A26: Costo variable unitario | C26: =Calculos!$B$14*Calculos!$B$7*Calculos!$C$24 -> 2506.2722 | D26: =Calculos!$B$14*Calculos!$B$7*Calculos!$D$24 -> 2581.4604 | E26: =Calculos!$B$14*Calculos!$B$7*Calculos!$E$24 -> 2658.9042 | F26: =Calculos!$B$14*Calculos!$B$7*Calculos!$F$24 -> 2738.6713 | G26: =Calculos!$B$14*Calculos!$B$7*Calculos!$G$24 -> 2820.8315
A27: Ingresos | C27: =Calculos!$C$23*Calculos!$C$25 -> 68523840 | D27: =Calculos!$D$23*Calculos!$D$25 -> 70579555 | E27: =Calculos!$E$23*Calculos!$E$25 -> 72696942 | F27: =Calculos!$F$23*Calculos!$F$25 -> 74877850 | G27: =Calculos!$G$23*Calculos!$G$25 -> 77124186
A28: Costos variables | C28: =Calculos!$C$23*Calculos!$C$26 -> 39699352 | D28: =Calculos!$D$23*Calculos!$D$26 -> 40890333 | E28: =Calculos!$E$23*Calculos!$E$26 -> 42117042 | F28: =Calculos!$F$23*Calculos!$F$26 -> 43380554 | G28: =Calculos!$G$23*Calculos!$G$26 -> 44681970
A29: Costos fijos | C29: =Calculos!$B$15*12*Calculos!$B$8*Calculos!$C$24 -> 47382678 | D29: =Calculos!$B$15*12*Calculos!$B$8*Calculos!$D$24 -> 48804158 | E29: =Calculos!$B$15*12*Calculos!$B$8*Calculos!$E$24 -> 50268283 | F29: =Calculos!$B$15*12*Calculos!$B$8*Calculos!$F$24 -> 51776332 | G29: =Calculos!$B$15*12*Calculos!$B$8*Calculos!$G$24 -> 53329622
A30: EBITDA | C30: =Calculos!$C$27-Calculos!$C$28-Calculos!$C$29 -> -18558190 | D30: =Calculos!$D$27-Calculos!$D$28-Calculos!$D$29 -> -19114936 | E30: =Calculos!$E$27-Calculos!$E$28-Calculos!$E$29 -> -19688384 | F30: =Calculos!$F$27-Calculos!$F$28-Calculos!$F$29 -> -20279035 | G30: =Calculos!$G$27-Calculos!$G$28-Calculos!$G$29 -> -20887406
A31: Depreciación | C31: =Calculos!$B$18 -> 2718401.3 | D31: =Calculos!$B$18 -> 2718401.3 | E31: =Calculos!$B$18 -> 2718401.3 | F31: =Calculos!$B$18 -> 2718401.3 | G31: =Calculos!$B$18 -> 2718401.3
A32: EBIT | C32: =Calculos!$C$30-Calculos!$C$31 -> -21276591 | D32: =Calculos!$D$30-Calculos!$D$31 -> -21833337 | E32: =Calculos!$E$30-Calculos!$E$31 -> -22406785 | F32: =Calculos!$F$30-Calculos!$F$31 -> -22997437 | G32: =Calculos!$G$30-Calculos!$G$31 -> -23605808
A33: Pérdida tributaria inicial | C33: =0 -> 0 | D33: =Calculos!$C$36 -> 21276591 | E33: =Calculos!$D$36 -> 43109928 | F33: =Calculos!$E$36 -> 65516713 | G33: =Calculos!$F$36 -> 88514150
A34: Renta imponible | C34: =MAX(0,Calculos!$C$32-Calculos!$C$33) -> 0 | D34: =MAX(0,Calculos!$D$32-Calculos!$D$33) -> 0 | E34: =MAX(0,Calculos!$E$32-Calculos!$E$33) -> 0 | F34: =MAX(0,Calculos!$F$32-Calculos!$F$33) -> 0 | G34: =MAX(0,Calculos!$G$32-Calculos!$G$33) -> 0
A35: Impuesto | C35: =Calculos!$C$34*Inputs!$C$21 -> 0 | D35: =Calculos!$D$34*Inputs!$C$22 -> 0 | E35: =Calculos!$E$34*Inputs!$C$23 -> 0 | F35: =Calculos!$F$34*Inputs!$C$24 -> 0 | G35: =Calculos!$G$34*Inputs!$C$25 -> 0
A36: Pérdida tributaria final | C36: =MAX(0,Calculos!$C$33-Calculos!$C$32) -> 21276591 | D36: =MAX(0,Calculos!$D$33-Calculos!$D$32) -> 43109928 | E36: =MAX(0,Calculos!$E$33-Calculos!$E$32) -> 65516713 | F36: =MAX(0,Calculos!$F$33-Calculos!$F$32) -> 88514150 | G36: =MAX(0,Calculos!$G$33-Calculos!$G$32) -> 1.1211996e+08
A37: Capital de trabajo | C37: =Calculos!$C$27*Inputs!$C$47/365+Calculos!$C$28*Inputs!$C$48/365-Calculos!$C$28*Inputs!$C$49/365 -> 7263576.7 | D37: =Calculos!$D$27*Inputs!$C$47/365+Calculos!$D$28*Inputs!$C$48/365-Calculos!$D$28*Inputs!$C$49/365 -> 7481484 | E37: =Calculos!$E$27*Inputs!$C$47/365+Calculos!$E$28*Inputs!$C$48/365-Calculos!$E$28*Inputs!$C$49/365 -> 7705928.5 | F37: =Calculos!$F$27*Inputs!$C$47/365+Calculos!$F$28*Inputs!$C$48/365-Calculos!$F$28*Inputs!$C$49/365 -> 7937106.3 | G37: =Calculos!$G$27*Inputs!$C$47/365+Calculos!$G$28*Inputs!$C$48/365-Calculos!$G$28*Inputs!$C$49/365 -> 8175219.5
A38: Variación capital de trabajo | C38: =Calculos!$C$37-Calculos!$C$37 -> 0 | D38: =Calculos!$D$37-Calculos!$C$37 -> 217907.3 | E38: =Calculos!$E$37-Calculos!$D$37 -> 224444.52 | F38: =Calculos!$F$37-Calculos!$E$37 -> 231177.85 | G38: =Calculos!$G$37-Calculos!$F$37 -> 238113.19
A39: Recuperaciones terminales | C39: =0 -> 0 | D39: =0 -> 0 | E39: =0 -> 0 | F39: =0 -> 0 | G39: =Calculos!$B$19-MAX(0,(Calculos!$B$19-MAX(0,Calculos!$B$16-Calculos!$B$18*5)))*Inputs!$C$25+Calculos!$G$37+Calculos!$B$20 -> 12413061
A40: Flujo libre | B40: =-(Calculos!$B$17+Calculos!$B$20+Calculos!$C$37) -> -38467030 | C40: =Calculos!$C$30-Calculos!$C$35-Calculos!$C$38+Calculos!$C$39 -> -18558190 | D40: =Calculos!$D$30-Calculos!$D$35-Calculos!$D$38+Calculos!$D$39 -> -19332843 | E40: =Calculos!$E$30-Calculos!$E$35-Calculos!$E$38+Calculos!$E$39 -> -19912828 | F40: =Calculos!$F$30-Calculos!$F$35-Calculos!$F$38+Calculos!$F$39 -> -20510213 | G40: =Calculos!$G$30-Calculos!$G$35-Calculos!$G$38+Calculos!$G$39 -> -8712458.6
A41: Factor descuento | B41: 1 | C41: =1/(1+Inputs!$C$6)^1 -> 0.83015109 | D41: =1/(1+Inputs!$C$6)^2 -> 0.68915083 | E41: =1/(1+Inputs!$C$6)^3 -> 0.57209931 | F41: =1/(1+Inputs!$C$6)^4 -> 0.47492886 | G41: =1/(1+Inputs!$C$6)^5 -> 0.39426271
A42: Flujo descontado | B42: =Calculos!$B$40 -> -38467030 | C42: =Calculos!$C$40*Calculos!$C$41 -> -15406102 | D42: =Calculos!$D$40*Calculos!$D$41 -> -13323245 | E42: =Calculos!$E$40*Calculos!$E$41 -> -11392115 | F42: =Calculos!$F$40*Calculos!$F$41 -> -9740892.2 | G42: =Calculos!$G$40*Calculos!$G$41 -> -3434997.6
A43: Flujo acumulado | B43: =Calculos!$B$40 -> -38467030 | C43: =Calculos!$B$43+Calculos!$C$40 -> -57025220 | D43: =Calculos!$C$43+Calculos!$D$40 -> -76358063 | E43: =Calculos!$D$43+Calculos!$E$40 -> -96270891 | F43: =Calculos!$E$43+Calculos!$F$40 -> -1.167811e+08 | G43: =Calculos!$F$43+Calculos!$G$40 -> -1.2549356e+08
A44: Flujo descontado acumulado | B44: =Calculos!$B$42 -> -38467030 | C44: =Calculos!$B$44+Calculos!$C$42 -> -53873132 | D44: =Calculos!$C$44+Calculos!$D$42 -> -67196376 | E44: =Calculos!$D$44+Calculos!$E$42 -> -78588492 | F44: =Calculos!$E$44+Calculos!$F$42 -> -88329384 | G44: =Calculos!$F$44+Calculos!$G$42 -> -91764381
A46: Inversión inicial | B46: =-Calculos!$B$40 -> 38467030
A47: VAN | B47: =SUM(Calculos!$B$42:$G$42) -> -91764381
A48: TIR | B48: =IFERROR(IRR(Calculos!$B$40:$G$40),NA()) -> #N/A
A49: Payback descontado | B49: =IFERROR(IF(Calculos!$C$44>=0,0+(-Calculos!$B$44/Calculos!$C$42),IF(Calculos!$D$44>=0,1+(-Calculos!$C$44/Calculos!$D$42),IF(Calculos!$E$44>=0,2+(-Calculos!$D$44/Calculos!$E$42),IF(Calculos!$F$44>=0,3+(-Calculos!$E$44/Calculos!$F$42),IF(Calculos!$G$44>=0,4+(-Calculos!$F$44/Calculos!$G$42),NA()))))),NA()) -> #N/A
A50: Índice de rentabilidad | B50: =(Calculos!$C$42+Calculos!$D$42+Calculos!$E$42+Calculos!$F$42+Calculos!$G$42)/(-Calculos!$B$40) -> -1.3855333
A51: Fondeo máximo | B51: =-MIN(Calculos!$B$43:$G$43) -> 1.2549356e+08
A52: Punto de equilibrio mensual | B52: =IF((Calculos!$C$25-Calculos!$C$26)>0,Calculos!$C$29/(Calculos!$C$25-Calculos!$C$26)/12,NA()) -> 2169.8611
A53: Capacidad instalada anual | B53: =IF(AND(Inputs!$C$51>0,Inputs!$C$52>0),Inputs!$C$51*Inputs!$C$52*12,NA()) -> 15840
A54: Uso de capacidad año 5 | B54: =IFERROR(Calculos!$G$23/Calculos!$B$53,NA()) -> 1
A55: Equilibrio sobre capacidad | B55: =IFERROR(Calculos!$B$52*12/Calculos!$B$53,NA()) -> 1.6438342
A56: VAN por peso de fondeo | B56: =IFERROR(Calculos!$B$47/Calculos!$B$51,NA()) -> -0.7312278
A59: Escenario Pesimista
A60: Precio | B60: =Inputs!$C$70 -> 0.72
A61: Volumen | B61: =Inputs!$C$71 -> 1
A62: Costo variable | B62: =Inputs!$C$72 -> 1
A63: Costo fijo | B63: =Inputs!$C$73 -> 1
A64: CAPEX | B64: =Inputs!$C$74 -> 1.3
A66: Equipos | B66: =IF(Inputs!$C$61>0,Inputs!$C$61,Inputs!$C$53+Inputs!$C$54+Inputs!$C$55+Inputs!$C$56+Inputs!$C$57+Inputs!$C$58+Inputs!$C$59+Inputs!$C$60) -> 10120237
A67: Flete/instalación | B67: =Calculos!$B$66*Inputs!$C$62 -> 1518035.6
A68: Arriendo mensual | B68: =IF(Inputs!$C$39>0,Inputs!$C$39,Inputs!$C$37*Inputs!$C$38) -> 759720
A69: Costo variable unitario base | B69: =((Inputs!$C$26*Inputs!$C$34+Inputs!$C$27*Inputs!$C$35+Inputs!$C$28*Inputs!$C$36+Inputs!$C$29)*(1+Inputs!$C$33)+Inputs!$C$30+Inputs!$C$31+Inputs!$C$32) -> 2433.274
A70: Costo fijo mensual base | B70: =(Calculos!$B$68+IF(Inputs!$C$50>0,Inputs!$C$50,Inputs!$C$40*Inputs!$C$41)+Inputs!$C$42+Inputs!$C$43+Inputs!$C$44+Inputs!$C$45+Inputs!$C$46) -> 3833550
A71: CAPEX depreciable | B71: =(Calculos!$B$66+Calculos!$B$67+Inputs!$C$63)*(1+Inputs!$C$66)*Calculos!$B$64 -> 35339217
A72: CAPEX total | B72: =Calculos!$B$71+(Inputs!$C$64+Inputs!$C$65)*Calculos!$B$64 -> 38589217
A73: Depreciación anual | B73: =Calculos!$B$71/Inputs!$C$68 -> 3533921.7
A74: Valor residual bruto | B74: =Calculos!$B$71*Inputs!$C$69 -> 3533921.7
A75: Garantía arriendo | B75: =Calculos!$B$68*Inputs!$C$67 -> 1519440
A77: Concepto | B77: Año 0 | C77: Año 1 | D77: Año 2 | E77: Año 3 | F77: Año 4 | G77: Año 5
A78: Volumen | C78: =IF(AND(Inputs!$C$51>0,Inputs!$C$52>0),MIN((IF(Inputs!$C$11>0,Inputs!$C$11*12,Inputs!$C$12))*Calculos!$B$61,Inputs!$C$51*Inputs!$C$52*12),(IF(Inputs!$C$11>0,Inputs!$C$11*12,Inputs!$C$12))*Calculos!$B$61) -> 15840 | D78: =IF(AND(Inputs!$C$51>0,Inputs!$C$52>0),MIN((IF(Inputs!$C$11>0,Inputs!$C$11*12,Inputs!$C$12)*IF(Inputs!$C$17>0,Inputs!$C$17,Inputs!$C$13/Inputs!$C$12))*Calculos!$B$61,Inputs!$C$51*Inputs!$C$52*12),(IF(Inputs!$C$11>0,Inputs!$C$11*12,Inputs!$C$12)*IF(Inputs!$C$17>0,Inputs!$C$17,Inputs!$C$13/Inputs!$C$12))*Calculos!$B$61) -> 15840 | E78: =IF(AND(Inputs!$C$51>0,Inputs!$C$52>0),MIN((IF(Inputs!$C$11>0,Inputs!$C$11*12,Inputs!$C$12)*IF(Inputs!$C$18>0,Inputs!$C$18,Inputs!$C$14/Inputs!$C$12))*Calculos!$B$61,Inputs!$C$51*Inputs!$C$52*12),(IF(Inputs!$C$11>0,Inputs!$C$11*12,Inputs!$C$12)*IF(Inputs!$C$18>0,Inputs!$C$18,Inputs!$C$14/Inputs!$C$12))*Calculos!$B$61) -> 15840 | F78: =IF(AND(Inputs!$C$51>0,Inputs!$C$52>0),MIN((IF(Inputs!$C$11>0,Inputs!$C$11*12,Inputs!$C$12)*IF(Inputs!$C$19>0,Inputs!$C$19,Inputs!$C$15/Inputs!$C$12))*Calculos!$B$61,Inputs!$C$51*Inputs!$C$52*12),(IF(Inputs!$C$11>0,Inputs!$C$11*12,Inputs!$C$12)*IF(Inputs!$C$19>0,Inputs!$C$19,Inputs!$C$15/Inputs!$C$12))*Calculos!$B$61) -> 15840 | G78: =IF(AND(Inputs!$C$51>0,Inputs!$C$52>0),MIN((IF(Inputs!$C$11>0,Inputs!$C$11*12,Inputs!$C$12)*IF(Inputs!$C$20>0,Inputs!$C$20,Inputs!$C$16/Inputs!$C$12))*Calculos!$B$61,Inputs!$C$51*Inputs!$C$52*12),(IF(Inputs!$C$11>0,Inputs!$C$11*12,Inputs!$C$12)*IF(Inputs!$C$20>0,Inputs!$C$20,Inputs!$C$16/Inputs!$C$12))*Calculos!$B$61) -> 15840
A79: Escalador | C79: =(1+Inputs!$C$7)^1 -> 1.03 | D79: =(1+Inputs!$C$7)^2 -> 1.0609 | E79: =(1+Inputs!$C$7)^3 -> 1.092727 | F79: =(1+Inputs!$C$7)^4 -> 1.1255088 | G79: =(1+Inputs!$C$7)^5 -> 1.1592741
A80: Precio | C80: =Inputs!$C$10*Calculos!$B$60*Calculos!$C$79 -> 3114.72 | D80: =Inputs!$C$10*Calculos!$B$60*Calculos!$D$79 -> 3208.1616 | E80: =Inputs!$C$10*Calculos!$B$60*Calculos!$E$79 -> 3304.4064 | F80: =Inputs!$C$10*Calculos!$B$60*Calculos!$F$79 -> 3403.5386 | G80: =Inputs!$C$10*Calculos!$B$60*Calculos!$G$79 -> 3505.6448
A81: Costo variable unitario | C81: =Calculos!$B$69*Calculos!$B$62*Calculos!$C$79 -> 2506.2722 | D81: =Calculos!$B$69*Calculos!$B$62*Calculos!$D$79 -> 2581.4604 | E81: =Calculos!$B$69*Calculos!$B$62*Calculos!$E$79 -> 2658.9042 | F81: =Calculos!$B$69*Calculos!$B$62*Calculos!$F$79 -> 2738.6713 | G81: =Calculos!$B$69*Calculos!$B$62*Calculos!$G$79 -> 2820.8315
A82: Ingresos | C82: =Calculos!$C$78*Calculos!$C$80 -> 49337165 | D82: =Calculos!$D$78*Calculos!$D$80 -> 50817280 | E82: =Calculos!$E$78*Calculos!$E$80 -> 52341798 | F82: =Calculos!$F$78*Calculos!$F$80 -> 53912052 | G82: =Calculos!$G$78*Calculos!$G$80 -> 55529414
A83: Costos variables | C83: =Calculos!$C$78*Calculos!$C$81 -> 39699352 | D83: =Calculos!$D$78*Calculos!$D$81 -> 40890333 | E83: =Calculos!$E$78*Calculos!$E$81 -> 42117042 | F83: =Calculos!$F$78*Calculos!$F$81 -> 43380554 | G83: =Calculos!$G$78*Calculos!$G$81 -> 44681970
A84: Costos fijos | C84: =Calculos!$B$70*12*Calculos!$B$63*Calculos!$C$79 -> 47382678 | D84: =Calculos!$B$70*12*Calculos!$B$63*Calculos!$D$79 -> 48804158 | E84: =Calculos!$B$70*12*Calculos!$B$63*Calculos!$E$79 -> 50268283 | F84: =Calculos!$B$70*12*Calculos!$B$63*Calculos!$F$79 -> 51776332 | G84: =Calculos!$B$70*12*Calculos!$B$63*Calculos!$G$79 -> 53329622
A85: EBITDA | C85: =Calculos!$C$82-Calculos!$C$83-Calculos!$C$84 -> -37744865 | D85: =Calculos!$D$82-Calculos!$D$83-Calculos!$D$84 -> -38877211 | E85: =Calculos!$E$82-Calculos!$E$83-Calculos!$E$84 -> -40043527 | F85: =Calculos!$F$82-Calculos!$F$83-Calculos!$F$84 -> -41244833 | G85: =Calculos!$G$82-Calculos!$G$83-Calculos!$G$84 -> -42482178
A86: Depreciación | C86: =Calculos!$B$73 -> 3533921.7 | D86: =Calculos!$B$73 -> 3533921.7 | E86: =Calculos!$B$73 -> 3533921.7 | F86: =Calculos!$B$73 -> 3533921.7 | G86: =Calculos!$B$73 -> 3533921.7
A87: EBIT | C87: =Calculos!$C$85-Calculos!$C$86 -> -41278787 | D87: =Calculos!$D$85-Calculos!$D$86 -> -42411133 | E87: =Calculos!$E$85-Calculos!$E$86 -> -43577449 | F87: =Calculos!$F$85-Calculos!$F$86 -> -44778755 | G87: =Calculos!$G$85-Calculos!$G$86 -> -46016100
A88: Pérdida tributaria inicial | C88: =0 -> 0 | D88: =Calculos!$C$91 -> 41278787 | E88: =Calculos!$D$91 -> 83689920 | F88: =Calculos!$E$91 -> 1.2726737e+08 | G88: =Calculos!$F$91 -> 1.7204612e+08
A89: Renta imponible | C89: =MAX(0,Calculos!$C$87-Calculos!$C$88) -> 0 | D89: =MAX(0,Calculos!$D$87-Calculos!$D$88) -> 0 | E89: =MAX(0,Calculos!$E$87-Calculos!$E$88) -> 0 | F89: =MAX(0,Calculos!$F$87-Calculos!$F$88) -> 0 | G89: =MAX(0,Calculos!$G$87-Calculos!$G$88) -> 0
A90: Impuesto | C90: =Calculos!$C$89*Inputs!$C$21 -> 0 | D90: =Calculos!$D$89*Inputs!$C$22 -> 0 | E90: =Calculos!$E$89*Inputs!$C$23 -> 0 | F90: =Calculos!$F$89*Inputs!$C$24 -> 0 | G90: =Calculos!$G$89*Inputs!$C$25 -> 0
A91: Pérdida tributaria final | C91: =MAX(0,Calculos!$C$88-Calculos!$C$87) -> 41278787 | D91: =MAX(0,Calculos!$D$88-Calculos!$D$87) -> 83689920 | E91: =MAX(0,Calculos!$E$88-Calculos!$E$87) -> 1.2726737e+08 | F91: =MAX(0,Calculos!$F$88-Calculos!$F$87) -> 1.7204612e+08 | G91: =MAX(0,Calculos!$G$88-Calculos!$G$87) -> 2.1806222e+08
A92: Capital de trabajo | C92: =Calculos!$C$82*Inputs!$C$47/365+Calculos!$C$83*Inputs!$C$48/365-Calculos!$C$83*Inputs!$C$49/365 -> 5686589.7 | D92: =Calculos!$D$82*Inputs!$C$47/365+Calculos!$D$83*Inputs!$C$48/365-Calculos!$D$83*Inputs!$C$49/365 -> 5857187.3 | E92: =Calculos!$E$82*Inputs!$C$47/365+Calculos!$E$83*Inputs!$C$48/365-Calculos!$E$83*Inputs!$C$49/365 -> 6032903 | F92: =Calculos!$F$82*Inputs!$C$47/365+Calculos!$F$83*Inputs!$C$48/365-Calculos!$F$83*Inputs!$C$49/365 -> 6213890.1 | G92: =Calculos!$G$82*Inputs!$C$47/365+Calculos!$G$83*Inputs!$C$48/365-Calculos!$G$83*Inputs!$C$49/365 -> 6400306.8
A93: Variación capital de trabajo | C93: =Calculos!$C$92-Calculos!$C$92 -> 0 | D93: =Calculos!$D$92-Calculos!$C$92 -> 170597.69 | E93: =Calculos!$E$92-Calculos!$D$92 -> 175715.62 | F93: =Calculos!$F$92-Calculos!$E$92 -> 180987.09 | G93: =Calculos!$G$92-Calculos!$F$92 -> 186416.7
A94: Recuperaciones terminales | C94: =0 -> 0 | D94: =0 -> 0 | E94: =0 -> 0 | F94: =0 -> 0 | G94: =Calculos!$B$74-MAX(0,(Calculos!$B$74-MAX(0,Calculos!$B$71-Calculos!$B$73*5)))*Inputs!$C$25+Calculos!$G$92+Calculos!$B$75 -> 11453668
A95: Flujo libre | B95: =-(Calculos!$B$72+Calculos!$B$75+Calculos!$C$92) -> -45795247 | C95: =Calculos!$C$85-Calculos!$C$90-Calculos!$C$93+Calculos!$C$94 -> -37744865 | D95: =Calculos!$D$85-Calculos!$D$90-Calculos!$D$93+Calculos!$D$94 -> -39047809 | E95: =Calculos!$E$85-Calculos!$E$90-Calculos!$E$93+Calculos!$E$94 -> -40219243 | F95: =Calculos!$F$85-Calculos!$F$90-Calculos!$F$93+Calculos!$F$94 -> -41425820 | G95: =Calculos!$G$85-Calculos!$G$90-Calculos!$G$93+Calculos!$G$94 -> -31214926
A96: Factor descuento | B96: 1 | C96: =1/(1+Inputs!$C$6)^1 -> 0.83015109 | D96: =1/(1+Inputs!$C$6)^2 -> 0.68915083 | E96: =1/(1+Inputs!$C$6)^3 -> 0.57209931 | F96: =1/(1+Inputs!$C$6)^4 -> 0.47492886 | G96: =1/(1+Inputs!$C$6)^5 -> 0.39426271
A97: Flujo descontado | B97: =Calculos!$B$95 -> -45795247 | C97: =Calculos!$C$95*Calculos!$C$96 -> -31333941 | D97: =Calculos!$D$95*Calculos!$D$96 -> -26909830 | E97: =Calculos!$E$95*Calculos!$E$96 -> -23009401 | F97: =Calculos!$F$95*Calculos!$F$96 -> -19674318 | G97: =Calculos!$G$95*Calculos!$G$96 -> -12306882
A98: Flujo acumulado | B98: =Calculos!$B$95 -> -45795247 | C98: =Calculos!$B$98+Calculos!$C$95 -> -83540112 | D98: =Calculos!$C$98+Calculos!$D$95 -> -1.2258792e+08 | E98: =Calculos!$D$98+Calculos!$E$95 -> -1.6280716e+08 | F98: =Calculos!$E$98+Calculos!$F$95 -> -2.0423298e+08 | G98: =Calculos!$F$98+Calculos!$G$95 -> -2.3544791e+08
A99: Flujo descontado acumulado | B99: =Calculos!$B$97 -> -45795247 | C99: =Calculos!$B$99+Calculos!$C$97 -> -77129188 | D99: =Calculos!$C$99+Calculos!$D$97 -> -1.0403902e+08 | E99: =Calculos!$D$99+Calculos!$E$97 -> -1.2704842e+08 | F99: =Calculos!$E$99+Calculos!$F$97 -> -1.4672274e+08 | G99: =Calculos!$F$99+Calculos!$G$97 -> -1.5902962e+08
A101: Inversión inicial | B101: =-Calculos!$B$95 -> 45795247
A102: VAN | B102: =SUM(Calculos!$B$97:$G$97) -> -1.5902962e+08
A103: TIR | B103: =IFERROR(IRR(Calculos!$B$95:$G$95),NA()) -> #N/A
A104: Payback descontado | B104: =IFERROR(IF(Calculos!$C$99>=0,0+(-Calculos!$B$99/Calculos!$C$97),IF(Calculos!$D$99>=0,1+(-Calculos!$C$99/Calculos!$D$97),IF(Calculos!$E$99>=0,2+(-Calculos!$D$99/Calculos!$E$97),IF(Calculos!$F$99>=0,3+(-Calculos!$E$99/Calculos!$F$97),IF(Calculos!$G$99>=0,4+(-Calculos!$F$99/Calculos!$G$97),NA()))))),NA()) -> #N/A
A105: Índice de rentabilidad | B105: =(Calculos!$C$97+Calculos!$D$97+Calculos!$E$97+Calculos!$F$97+Calculos!$G$97)/(-Calculos!$B$95) -> -2.4726228
A106: Fondeo máximo | B106: =-MIN(Calculos!$B$98:$G$98) -> 2.3544791e+08
A107: Punto de equilibrio mensual | B107: =IF((Calculos!$C$80-Calculos!$C$81)>0,Calculos!$C$84/(Calculos!$C$80-Calculos!$C$81)/12,NA()) -> 6489.5569
A108: Capacidad instalada anual | B108: =IF(AND(Inputs!$C$51>0,Inputs!$C$52>0),Inputs!$C$51*Inputs!$C$52*12,NA()) -> 15840
A109: Uso de capacidad año 5 | B109: =IFERROR(Calculos!$G$78/Calculos!$B$108,NA()) -> 1
...

Sheet Listas
A1: Pesimista | C1: Origen de las validaciones del libro. No editar.
A2: Base
A3: Optimista

Sheet Tornado
A1: TORNADO · SENSIBILIDAD DE UNA VÍA
A2: Cada parámetro movido solo, entre su banda declarada. Ordenado por impacto en el VAN.
A4: Estado de esta hoja | B4: =IF(ABS(Calculos!$B$47-(-91764381.4776))>1,"DESACTUALIZADO — reejecute generar_modelo_excel.py","VIGENTE") -> VIGENTE
A5: Calculado el 2026-08-06 18:18 sobre VAN base -91,764,381 CLP.
A7: Parámetro | B7: Base | C7: Bajo | D7: Alto | E7: VAN bajo | F7: VAN alto | G7: Δ VAN | H7: Δ Fondeo | I7: Impacto | J7: Origen de la banda
A8: Precio B2B familiar | B8: 4200 | C8: 3024 | D8: 5040 | E8: -1.5044594e+08 | F8: -49848980 | G8: 1.0059696e+08 | H8: 1.6668189e+08 | I8: ██████████████████████ | J8: escenarios.precio_*_factor · PF Listo $3.017 / Meta Food $5.034
A9: Costo de personal | B9: 2393830 | C9: 1915064 | D9: 2872596 | E9: -73362995 | F9: -1.1016577e+08 | G9: 36802772 | H9: 62834129 | I9: ████████ | J9: swing exploratorio ±20% — sin banda publicada
A10: Capacidad instalada | B10: 60 | C10: 48 | D10: 72 | E10: -1.0878655e+08 | F10: -74742209 | G10: 34044345 | H10: 61213249 | I10: ███████ | J10: swing exploratorio ±20% — sin banda publicada
A11: Días de operación | B11: 22 | C11: 17.6 | D11: 26.4 | E11: -1.0878655e+08 | F11: -74742209 | G11: 34044345 | H11: 61213249 | I11: ███████ | J11: swing exploratorio ±20% — sin banda publicada
A12: Gramaje mozzarella | B12: 0.1 | C12: 0.08 | D12: 0.12 | E12: -82737609 | F12: -1.0079115e+08 | G12: 18053545 | H12: 30571623 | I12: ████ | J12: swing exploratorio ±20% — sin banda publicada
A13: Mozzarella $/kg | B13: 8403.36 | C13: 6722.69 | D13: 10084.03 | E13: -82737620 | F13: -1.0079114e+08 | G13: 18053523 | H13: 30571587 | I13: ████ | J13: swing exploratorio ±20% — sin banda publicada
A14: Arriendo mensual | B14: 759720 | C14: 607776 | D14: 911664 | E14: -85740333 | F14: -97788430 | G14: 12048097 | H14: 19941410 | I14: ███ | J14: swing exploratorio ±20% — sin banda publicada
A15: Otros ingredientes | B15: 550 | C15: 440 | D15: 660 | E15: -85856358 | F15: -97672405 | G15: 11816047 | H15: 20009131 | I15: ███ | J15: swing exploratorio ±20% — sin banda publicada
A16: TMAR | B16: 20.46 | C16: 16.368 | D16: 24.552 | E16: -96596196 | F16: -87564071 | G16: 9032125.1 | H16: 0 | I16: ██ | J16: swing exploratorio ±20% — sin banda publicada
A17: Habilitación sanitaria | B17: 12000000 | C17: 9600000 | D17: 15600000 | E17: -89113198 | F17: -95741157 | G17: 6627958.7 | H17: 6210000 | I17: █ | J17: AACE 18R-97 Clase 5 · escenarios.capex_*_factor
A18: Envolvente de equipos | B18: 10120237 | C18: 8096189.6 | D18: 13156308 | E18: -89193115 | F18: -95621281 | G18: 6428165.8 | H18: 6022806 | I18: █ | J18: AACE 18R-97 Clase 5 · escenarios.capex_*_factor
A19: Envase por unidad | B19: 300 | C19: 240 | D19: 360 | E19: -88695278 | F19: -94833485 | G19: 6138206.1 | H19: 10394354 | I19: █ | J19: swing exploratorio ±20% — sin banda publicada
... A21: Plazo de cobro | B21: 30 | C21: 30 | D21: 60 | E21: -91764381 | F21: -95271186 | G21: 3506804.8 | H21: 0 | I21: █ | J21: statement §8 · rango declarado 30–60 días
A22: Merma | B22: 5 | C22: 4 | D22: 6 | E22: -90890772 | F22: -92637991 | G22: 1747219.9 | H22: 2958718.1 | J22: swing exploratorio ±20% — sin banda publicada
A23: Contingencia | B23: 15 | C23: 12 | D23: 18 | E23: -91083192 | F23: -92445571 | G23: 1362378.2 | H23: 1276466.7 | J23: swing exploratorio ±20% — sin banda publicada
A24: Vida depreciable | B24: 10 | C24: 8 | D24: 12 | E24: -91764381 | F24: -91764381 | G24: 0 | H24: 0 | J24: swing exploratorio ±20% — sin banda publicada

Sheet Valores_Quiebre
A1: VALORES DE QUIEBRE
A2: Valor de cada parámetro que anula el VAN y valor que lleva el fondeo máximo al límite de capital.
A4: Estado de esta hoja | B4: =IF(ABS(Calculos!$B$47-(-91764381.4776))>1,"DESACTUALIZADO — reejecute generar_modelo_excel.py","VIGENTE") -> VIGENTE
A5: Calculado el 2026-08-06 18:18 sobre VAN base -91,764,381 CLP.
A6: El fondeo máximo actual ($125,493,563) supera el límite de $50,000,000. La columna «fondeo = límite» ya no marca un punto de quiebre sino la MEJORA REQUERIDA para volver a caber.
A8: Parámetro | B8: Base | C8: VAN = 0 | D8: Variación exigida | E8: Fondeo = límite | F8: Variación exigida | G8: Origen de la banda
A9: Precio B2B familiar | B9: 4200 | C9: 6151.6877 | D9: 0.46468754 | E9: SIN QUIEBRE EN EL RANGO | F9: — | G9: escenarios.precio_*_factor · PF Listo $3.017 / Meta Food $5.034
A10: Envolvente de equipos | B10: 10120237 | C10: SIN QUIEBRE EN EL RANGO | D10: — | E10: SIN QUIEBRE EN EL RANGO | F10: — | G10: AACE 18R-97 Clase 5 · escenarios.capex_*_factor
A11: Habilitación sanitaria | B11: 12000000 | C11: SIN QUIEBRE EN EL RANGO | D11: — | E11: SIN QUIEBRE EN EL RANGO | F11: — | G11: AACE 18R-97 Clase 5 · escenarios.capex_*_factor
A12: Plazo de cobro | B12: 30 | C12: SIN QUIEBRE EN EL RANGO | D12: — | E12: SIN QUIEBRE EN EL RANGO | F12: — | G12: statement §8 · rango declarado 30–60 días
A13: Capacidad instalada | B13: 60 | C13: 134.81996 | D13: 1.2469994 | E13: 95.567964 | F13: 0.5927994 | G13: swing exploratorio ±20% — sin banda publicada
A14: Días de operación | B14: 22 | C14: 49.433987 | D14: 1.2469994 | E14: 35.041587 | F14: 0.5927994 | G14: swing exploratorio ±20% — sin banda publicada
A15: Mozzarella $/kg | B15: 8403.36 | C15: SIN QUIEBRE EN EL RANGO | D15: — | E15: SIN QUIEBRE EN EL RANGO | F15: — | G15: swing exploratorio ±20% — sin banda publicada
A16: Gramaje mozzarella | B16: 0.1 | C16: SIN QUIEBRE EN EL RANGO | D16: — | E16: SIN QUIEBRE EN EL RANGO | F16: — | G16: swing exploratorio ±20% — sin banda publicada
A17: Costo de personal | B17: 2393830 | C17: SIN QUIEBRE EN EL RANGO | D17: — | E17: 1102366.4 | F17: -0.53949678 | G17: swing exploratorio ±20% — sin banda publicada
A18: Arriendo mensual | B18: 759720 | C18: SIN QUIEBRE EN EL RANGO | D18: — | E18: SIN QUIEBRE EN EL RANGO | F18: — | G18: swing exploratorio ±20% — sin banda publicada
A19: TMAR | B19: 20.46 | C19: SIN QUIEBRE EN EL RANGO | D19: — | E19: SIN QUIEBRE EN EL RANGO | F19: — | G19: swing exploratorio ±20% — sin banda publicada
A20: Contingencia | B20: 15 | C20: SIN QUIEBRE EN EL RANGO | D20: — | E20: SIN QUIEBRE EN EL RANGO | F20: — | G20: swing exploratorio ±20% — sin banda publicada
A21: Merma | B21: 5 | C21: SIN QUIEBRE EN EL RANGO | D21: — | E21: SIN QUIEBRE EN EL RANGO | F21: — | G21: swing exploratorio ±20% — sin banda publicada
A22: Vida depreciable | B22: 10 | C22: SIN QUIEBRE EN EL RANGO | D22: — | E22: SIN QUIEBRE EN EL RANGO | F22: — | G22: swing exploratorio ±20% — sin banda publicada
A23: Otros ingredientes | B23: 550 | C23: SIN QUIEBRE EN EL RANGO | D23: — | E23: SIN QUIEBRE EN EL RANGO | F23: — | G23: swing exploratorio ±20% — sin banda publicada
A24: Distribución por unidad | B24: 220 | C24: SIN QUIEBRE EN EL RANGO | D24: — | E24: SIN QUIEBRE EN EL RANGO | F24: — | G24: swing exploratorio ±20% — sin banda publicada
A25: Envase por unidad | B25: 300 | C25: SIN QUIEBRE EN EL RANGO | D25: — | E25: SIN QUIEBRE EN EL RANGO | F25: — | G25: swing exploratorio ±20% — sin banda publicada

Sheet Monte_Carlo
A1: MONTE CARLO · PERFIL DE RIESGO
A2: Distribuciones triangulares sobre los parámetros CON banda publicada. Semilla fija.
A4: PERFIL ILUSTRATIVO DE RIESGO. Las distribuciones son SUPUESTO; sólo sus anclas están citadas. No es evidencia y no altera ninguna conclusión del dossier. Los parámetros sin banda publicada quedan FUERA de la simulación: inventarles una distribución sería exactamente la cifra plausible que la regla 7 prohíbe.
A6: Estado de esta hoja | B6: =IF(ABS(Calculos!$B$47-(-91764381.4776))>1,"DESACTUALIZADO — reejecute generar_modelo_excel.py","VIGENTE") -> VIGENTE
A7: Calculado el 2026-08-06 18:18 sobre VAN base -91,764,381 CLP.
A9: Distribuciones simuladas
A10: Parámetro | B10: Mínimo | C10: Moda | D10: Máximo | E10: Ancla citada
A11: Precio B2B familiar | B11: 3024 | C11: 4200 | D11: 5040 | E11: escenarios.precio_*_factor · PF Listo $3.017 / Meta Food $5.034
A12: Envolvente de equipos | B12: 8096189.6 | C12: 10120237 | D12: 13156308 | E12: AACE 18R-97 Clase 5 · escenarios.capex_*_factor
A13: Habilitación sanitaria | B13: 9600000 | C13: 12000000 | D13: 15600000 | E13: AACE 18R-97 Clase 5 · escenarios.capex_*_factor
A14: Plazo de cobro | B14: 30 | C14: 30 | D14: 60 | E14: statement §8 · rango declarado 30–60 días
A17: Resultados
A18: Iteraciones | B18: 10000
A19: Semilla | B19: 20260804
A20: VAN P10 | B20: -1.2812973e+08
A21: VAN P50 (mediana) | B21: -98394492
A22: VAN P90 | B22: -73437127
A23: VAN medio | B23: -99590671
A24: P(VAN > 0) | B24: 0
A25: P(fondeo máximo ≤ límite de capital) | B25: 0
A28: Distribución del VAN
A29: Desde | B29: Hasta | C29: Casos | D29: Frecuencia
A30: -1.5365308e+08 | B30: -1.4842251e+08 | C30: 30 | D30: █
A31: -1.4842251e+08 | B31: -1.4319194e+08 | C31: 117 | D31: ███
A32: -1.4319194e+08 | B32: -1.3796138e+08 | C32: 179 | D32: █████
A33: -1.3796138e+08 | B33: -1.3273081e+08 | C33: 319 | D33: █████████
A34: -1.3273081e+08 | B34: -1.2750024e+08 | C34: 415 | D34: ████████████
A35: -1.2750024e+08 | B35: -1.2226968e+08 | C35: 459 | D35: █████████████
A36: -1.2226968e+08 | B36: -1.1703911e+08 | C36: 543 | D36: ████████████████
A37: -1.1703911e+08 | B37: -1.1180854e+08 | C37: 721 | D37: █████████████████████
A38: -1.1180854e+08 | B38: -1.0657797e+08 | C38: 774 | D38: ██████████████████████
A39: -1.0657797e+08 | B39: -1.0134741e+08 | C39: 896 | D39: ██████████████████████████
A40: -1.0134741e+08 | B40: -96116841 | C40: 943 | D40: ███████████████████████████
A41: -96116841 | B41: -90886274 | C41: 1040 | D41: ██████████████████████████████
... A49: -54272306 | B49: -49041739 | C49: 22 | D49: █

Sheet Tasa_Descuento
A1: TASA DE DESCUENTO
A2: Construcción de la TMAR y perfil del VAN frente a la tasa.
A4: Construcción declarada
A5: Componente | B5: % | C5: Nota
A6: TPM Banco Central | B6: 0.045 | C6: Tasa de política monetaria vigente a la fecha base.
A7: Interés corriente CMF 200–5.000 UF ≥90 días | B7: 0.2046 | C7: CMF Certificado 07/2026. Es lo que los bancos cobraron por dinero del tamaño y plazo del proyecto.
A8: Spread sobre TPM | B8: 0.1596 | C8: NO SE DESCOMPONE riesgo por riesgo: no hay fuente pública que lo permita. Se declara el spread observado, no una construcción inventada.
A9: TMAR usada por el modelo | B9: 0.2046 | C9: Piso observado. El capital propio es subordinado a esa deuda, así que la TMAR correcta es mayor; usar el piso es conservador respecto del rechazo.
A12: Perfil del VAN frente a la tasa (vivo)
A13: Tasa | B13: VAN | C13: Magnitud
A14: 0.05 | B14: =Calculos!$B$46*-1+Calculos!$B$40/(1+$A$14)^0+Calculos!$C$40/(1+$A$14)^1+Calculos!$D$40/(1+$A$14)^2+Calculos!$E$40/(1+$A$14)^3+Calculos!$F$40/(1+$A$14)^4+Calculos!$G$40/(1+$A$14)^5 -> -1.5304568e+08
A15: 0.08 | B15: =Calculos!$B$46*-1+Calculos!$B$40/(1+$A$15)^0+Calculos!$C$40/(1+$A$15)^1+Calculos!$D$40/(1+$A$15)^2+Calculos!$E$40/(1+$A$15)^3+Calculos!$F$40/(1+$A$15)^4+Calculos!$G$40/(1+$A$15)^5 -> -1.4750498e+08
A16: 0.11 | B16: =Calculos!$B$46*-1+Calculos!$B$40/(1+$A$16)^0+Calculos!$C$40/(1+$A$16)^1+Calculos!$D$40/(1+$A$16)^2+Calculos!$E$40/(1+$A$16)^3+Calculos!$F$40/(1+$A$16)^4+Calculos!$G$40/(1+$A$16)^5 -> -1.4258534e+08
A17: 0.14 | B17: =Calculos!$B$46*-1+Calculos!$B$40/(1+$A$17)^0+Calculos!$C$40/(1+$A$17)^1+Calculos!$D$40/(1+$A$17)^2+Calculos!$E$40/(1+$A$17)^3+Calculos!$F$40/(1+$A$17)^4+Calculos!$G$40/(1+$A$17)^5 -> -1.3819843e+08
A18: 0.17 | B18: =Calculos!$B$46*-1+Calculos!$B$40/(1+$A$18)^0+Calculos!$C$40/(1+$A$18)^1+Calculos!$D$40/(1+$A$18)^2+Calculos!$E$40/(1+$A$18)^3+Calculos!$F$40/(1+$A$18)^4+Calculos!$G$40/(1+$A$18)^5 -> -1.3427077e+08
A19: 0.2 | B19: =Calculos!$B$46*-1+Calculos!$B$40/(1+$A$19)^0+Calculos!$C$40/(1+$A$19)^1+Calculos!$D$40/(1+$A$19)^2+Calculos!$E$40/(1+$A$19)^3+Calculos!$F$40/(1+$A$19)^4+Calculos!$G$40/(1+$A$19)^5 -> -1.3074089e+08
A20: 0.23 | B20: =Calculos!$B$46*-1+Calculos!$B$40/(1+$A$20)^0+Calculos!$C$40/(1+$A$20)^1+Calculos!$D$40/(1+$A$20)^2+Calculos!$E$40/(1+$A$20)^3+Calculos!$F$40/(1+$A$20)^4+Calculos!$G$40/(1+$A$20)^5 -> -1.2755706e+08
A21: 0.26 | B21: =Calculos!$B$46*-1+Calculos!$B$40/(1+$A$21)^0+Calculos!$C$40/(1+$A$21)^1+Calculos!$D$40/(1+$A$21)^2+Calculos!$E$40/(1+$A$21)^3+Calculos!$F$40/(1+$A$21)^4+Calculos!$G$40/(1+$A$21)^5 -> -1.2467556e+08
A22: 0.29 | B22: =Calculos!$B$46*-1+Calculos!$B$40/(1+$A$22)^0+Calculos!$C$40/(1+$A$22)^1+Calculos!$D$40/(1+$A$22)^2+Calculos!$E$40/(1+$A$22)^3+Calculos!$F$40/(1+$A$22)^4+Calculos!$G$40/(1+$A$22)^5 -> -1.2205928e+08
A23: 0.32 | B23: =Calculos!$B$46*-1+Calculos!$B$40/(1+$A$23)^0+Calculos!$C$40/(1+$A$23)^1+Calculos!$D$40/(1+$A$23)^2+Calculos!$E$40/(1+$A$23)^3+Calculos!$F$40/(1+$A$23)^4+Calculos!$G$40/(1+$A$23)^5 -> -1.1967651e+08
A24: 0.35 | B24: =Calculos!$B$46*-1+Calculos!$B$40/(1+$A$24)^0+Calculos!$C$40/(1+$A$24)^1+Calculos!$D$40/(1+$A$24)^2+Calculos!$E$40/(1+$A$24)^3+Calculos!$F$40/(1+$A$24)^4+Calculos!$G$40/(1+$A$24)^5 -> -1.1750012e+08

Sheet Estructura_Capital
A1: ESTRUCTURA DE CAPITAL
A2: Configuraciones comparadas contra dos techos de capital: $30.000.000 y $50.000.000.
A4: Estado de esta hoja | B4: =IF(ABS(Calculos!$B$47-(-91764381.4776))>1,"DESACTUALIZADO — reejecute generar_modelo_excel.py","VIGENTE") -> VIGENTE
A5: Calculado el 2026-08-06 18:18 sobre VAN base -91,764,381 CLP.
A7: Configuración | B7: CAPEX | C7: Inversión inicial | D7: Fondeo máximo | E7: Holgura vs $30M | F7: Holgura vs $50M | G7: VAN | H7: Lectura
A8: Planta propia · $15M + $15M, sin deuda | B8: 29684013 | C8: 38467030 | D8: 1.2549356e+08 | E8: -95493563 | F8: -75493563 | G8: -91764381 | H8: Los socios aportan $30M. La brecha contra el fondeo exigido no la cierra ninguna estructura.
A9: Planta propia · $30M + crédito de consumo | B9: 29684013 | C9: 38467030 | D9: 1.2549356e+08 | E9: -95493563 | F9: -75493563 | G9: -91764381 | H9: La deuda no cambia el fondeo requerido: cambia quién lo aporta y añade costo financiero y riesgo personal.
A10: Maquila · sin planta propia, tarifa $0 | B10: 2500000 | C10: 17776214 | D10: 17776214 | E10: 12223786 | F10: 32223786 | G10: 90427836 | H10: Cota superior: falta la tarifa del maquilador. Sin habilitación ni equipos propios y sin tope de capacidad propia.
A12: Tarifa máxima de maquila admisible
A13: La tarifa del maquilador no es dato público, así que el modelo no la supone: acota cuánto se puede pagar. Por bisección sobre el fondeo máximo, con los volúmenes del caso base.
A14: Techo de capital | B14: Tarifa máxima CLP/pizza
A15: $30.000.000 | B15: 560
A16: $50.000.000 | B16: 810
A19: Crédito de consumo · tramo CMF 200 a 5.000 UF, 90 días o más
A20: En el crédito de consumo el deudor es la persona natural: la SpA no es parte del contrato, así que su responsabilidad limitada no llega a activarse y la deuda sobrevive a la empresa. La cuota no depende de que el negocio funcione.
A21: Monto | B21: Tasa anual | C21: Plazo | D21: Cuota mensual | E21: Total pagado | F21: Costo financiero | G21: % de la brecha que cubre
A22: 15000000 | B22: Corriente 20,46% | C22: 48 | D22: 446603.4 | E22: 21436963 | F22: 6436963.3 | G22: 0.15707865
A23: 20000000 | B23: Corriente 20,46% | C23: 48 | D23: 595471.2 | E23: 28582618 | F23: 8582617.7 | G23: 0.2094382
A24: 20000000 | B24: Máxima convencional 30,69% | C24: 48 | D24: 686401.75 | E24: 32947284 | F24: 12947284 | G24: 0.2094382
A25: 30000000 | B25: Corriente 20,46% | C25: 48 | D25: 893206.8 | E25: 42873927 | F25: 12873927 | G25: 0.3141573
A27: Brecha a cubrir con planta propia contra el techo de $30.000.000: $95.493.563. Ningún crédito de consumo de este tamaño la cierra.

Sheet Estado_Resultados
A1: ESTADO DE RESULTADOS
A2: Por año, con margen de contribución y porcentaje sobre ingresos.
A5: Concepto | B5: Año 1 | C5: Año 2 | D5: Año 3 | E5: Año 4 | F5: Año 5 | G5: % ingresos año 1
A6: Volumen (unidades) | B6: 15840 | C6: 15840 | D6: 15840 | E6: 15840 | F6: 15840 | G6: —
A7: Ingresos | B7: 68523840 | C7: 70579555 | D7: 72696942 | E7: 74877850 | F7: 77124186 | G7: 1
A8: Costos variables | B8: -39699352 | C8: -40890333 | D8: -42117042 | E8: -43380554 | F8: -44681970 | G8: -0.57935095
A9: Margen de contribución | B9: 28824488 | C9: 29689223 | D9: 30579899 | E9: 31497296 | F9: 32442215 | G9: 0.42064905
A10: Costos fijos | B10: -47382678 | C10: -48804158 | D10: -50268283 | E10: -51776332 | F10: -53329622 | G10: -0.69147727
A11: EBITDA | B11: -18558190 | C11: -19114936 | D11: -19688384 | E11: -20279035 | F11: -20887406 | G11: -0.27082823
A12: Depreciación | B12: -2718401.3 | C12: -2718401.3 | D12: -2718401.3 | E12: -2718401.3 | F12: -2718401.3 | G12: -0.039670885
A13: EBIT | B13: -21276591 | C13: -21833337 | D13: -22406785 | E13: -22997437 | F13: -23605808 | G13: -0.31049911
A14: Renta imponible | B14: 0 | C14: 0 | D14: 0 | E14: 0 | F14: 0 | G14: 0
A15: Impuesto | B15: 0 | C15: 0 | D15: 0 | E15: 0 | F15: 0 | G15: 0
A16: Resultado neto | B16: -21276591 | C16: -21833337 | D16: -22406785 | E16: -22997437 | F16: -23605808 | G16: -0.31049911

Sheet Capital_Trabajo
A1: CAPITAL DE TRABAJO
A2: Días de cobro, inventario y pago, y por qué un modelo anual subestima el peak.
A5: Concepto | B5: Año 1 | C5: Año 2 | D5: Año 3 | E5: Año 4 | F5: Año 5
A6: Cuentas por cobrar | B6: 5632096.4 | C6: 5801059.3 | D6: 5975091.1 | E6: 6154343.8 | F6: 6338974.2
A7: Inventario | B7: 1631480.2 | C7: 1680424.6 | D7: 1730837.4 | E7: 1782762.5 | F7: 1836245.4
A8: Cuentas por pagar | B8: 0 | C8: 0 | D8: 0 | E8: 0 | F8: 0
A9: Capital de trabajo neto | B9: 7263576.7 | C9: 7481484 | D9: 7705928.5 | E9: 7937106.3 | F9: 8175219.5
A10: Variación del período | B10: 0 | C10: 217907.3 | D10: 224444.52 | E10: 231177.85 | F10: 238113.19
A13: Indicadores de ciclo
A14: DSO · días de cobro | B14: 30
A15: DIO · días de inventario | B15: 15
A16: DPO · días de pago | B16: 0
A17: Ciclo de conversión de caja | B17: 45
A20: ADVERTENCIA. Este modelo es anual y no tiene perfil mensual de caja, así que el fondeo máximo que reporta IGNORA el valle intra-anual. Con DPO en cero se supone además que ningún proveedor da crédito, supuesto conservador que nadie ha verificado. La etapa 11 publicó un ratio peak/valle de 2,1 para pernoctaciones INE, pero es un proxy turístico y no una serie de demanda de pizza: usarlo como índice de estacionalidad sería inventar. El perfil mensual queda pendiente.

Sheet Ratios
A1: RATIOS Y ECONOMÍA UNITARIA
A2: Por qué el proyecto no cierra, en indicadores.
A5: Indicador | B5: Valor | C5: Lectura
A6: Precio neto por pizza | B6: 4326 | C6: Año 1, con escalador de inflación.
A7: Costo variable por pizza | B7: 2506.2722 | C7: Insumos con merma, envase, energía y distribución.
A8: Margen de contribución por pizza | B8: 1819.7278 | C8: Lo que deja cada pizza para pagar costos fijos.
A9: Margen de contribución % | B9: 0.42064905 | C9: Sobre precio de venta.
A10: Costo fijo mensual | B10: 3833550 | C10: Arriendo, personal y gastos de estructura.
A11: Punto de equilibrio mensual | B11: 2169.8611 | C11: Unidades que igualan contribución y costo fijo.
A12: Capacidad instalada mensual | B12: 1320 | C12: Etapa 04, desde la geometría del abatidor.
A13: Equilibrio sobre capacidad | B13: 1.6438342 | C13: Por sobre 100% el equilibrio es inalcanzable.
A14: Apalancamiento operativo (DOL) | B14: No definido | C14: Contribución total sobre EBITDA; no definido con EBITDA negativo.
A15: Margen de seguridad | B15: No definido | C15: No definido: la operación no alcanza el equilibrio.
A16: VAN por peso de fondeo máximo | B16: -0.7312278 | C16: Índice correcto bajo racionamiento de capital: el denominador es la caja que hay que poner, no la inversión inicial.
A17: Índice de rentabilidad | B17: -1.3855333 | C17: Criterio > 1. Usa la inversión inicial como denominador.

Sheet Respuestas
A1: LAS SEIS PREGUNTAS DEL STATEMENT
A2: Respuesta actual de cada una, la etapa responsable y qué falta para cerrarla.
A5: # | B5: Pregunta | C5: Respuesta | D5: Etapa | E5: Qué falta
A6: 1 | B6: ¿Cuántos establecimientos HORECA hay y cuánto consumen? | C6: 1.187 en Temuco y 1.588 en el anillo 1. El consumo por establecimiento sigue sin medir. | D6: 01 · 03 | E6: Entrevistas en terreno con el instrumento de la etapa 03.
A7: 2 | B7: ¿A qué precio compran hoy y cuánto pagarían por la alternativa local? | C7: Referencias de retail y foodservice levantadas. La disposición a pagar no está medida. | D7: 02 · 03 | E7: Prueba monádica de tres precios, etapa 03.
A8: 3 | B8: ¿Cuál es el CAPEX mínimo con cotizaciones reales? | C8: $29.684.013 con precios de publicación. Cinco de las ocho líneas heredadas no resistieron la auditoría. | D8: 05 · 07 | E8: Cotizaciones formales; el escenario de equipo usado no pudo construirse por ausencia de mercado publicado.
A9: 4 | B9: ¿Cuánto capital de trabajo exige el ciclo de cobro? | C9: $7.263.577 inicial, con plazo de cobro supuesto de 30 días. | D9: 10 | E9: Plazo de cobro real por segmento, y un perfil mensual que capture el valle intra-anual.
A10: 5 | B10: ¿Cuál es el punto de equilibrio y qué porcentaje de la capacidad representa? | C10: 2.170 pizzas/mes contra una capacidad de 1.320/mes: 164% de la capacidad instalada. | D10: 04 · 10 | E10: Medir el ciclo real de abatimiento con sonda al centro térmico; los 240 min son un techo prestado.
A11: 6 | B11: ¿Cabe en $50 millones? Si no, ¿cuál es el mínimo real y qué caminos existen? | C11: No con planta propia: exige $125.493.563 de fondeo. Sí por maquila, mientras la tarifa no supere $810/pizza ($560 si el techo es $30 millones). | D11: 10 · 12 · 13 | E11: Cotizar la maquila. Es el único camino que cabe en el capital disponible.

Sheet Auditoria
A1: AUDITORÍA DE LA CONSTRUCCIÓN
A2: Capacidades logradas o degradadas, y controles internos del modelo.
A4: Capacidad | B4: Estado
A5: Formato condicional | B5: LOGRADO
A6: Validacion | B6: LOGRADO
A7: Autofiltro | B7: sólo ODS (el exportador xlsx no lo emite)
A8: Rangos con nombre | B8: LOGRADO
A9: Titulos impresion | B9: LOGRADO
A10: Graficos | B10: LOGRADO
A11: Proteccion | B11: LOGRADO
A13: Sello de construcción
A14: Generado | B14: 2026-08-06 18:18
A15: Control VAN | B15: =Resumen!$E$12 -> OK
A16: Flujo convencional | B16: =Resumen!$E$13 -> REVISAR TIR
A17: TIR calculable | B17: =IF(ISNA(Calculos!$B$48),"NO — flujo sin cambio de signo","sí") -> NO — flujo sin cambio de signo
